Workbook

Sheet Main Sheet
A1: Updated Job Spreadsheet
A2: Job Number | B2: Job Name | C2: Job Owner | D2: Contract Signed & Returned. Retention % loaded correctly into Katipolt | E2: Warranty Signed & Returned | F2: Construction Programme Received | G2: Into Work Calculator 2 Weekly | H2: Temp Application Done | I2: Mains Connection Application | J2: POs Sent to Sub contractors | K2: Switchboard Drawing Sent for Approval | L2: Email Sent to QS/Builder to Confirm Order Gear | M2: Long Lead Time Materials Ordered | O2: Client Walk Through | P2: Pre Job Meeting Completed with Staff Job Pack Made | Q2: O&M Manual underway (notes for what's needed) | R2: QA Completed By Others | T2: Job Completion Paperwork Completed | U2: All V.Os captured | W2: Last toolbox date
M3: Ordered | N3: Lead Times Comm. | R3: 1st Fix | S3: 2nd Fix
A4: 7658 | B4: Charity Hospital | C4: Cameron | D4: Yes | F4: Yes | G4: Yes | H4: N/A | I4: N/A | J4: Yes | K4: Yes | L4: Yes | M4: Yes | P4: Yes
A6: 8142 | B6: Fisher Developements | C6: Cameron | D6: Yes | F6: Yes | G6: yes | H6: Yes | I6: Yes | J6: Yes | K6: Yes | M6: Yes
A8: 8824 | B8: 3 Innovation Road | C8: Cameron | F8: Yes | G8: N/A | H8: N/A | I8: Yes | J8: Yes | K8: Yes | L8: Yes | M8: N/A | N8: N/A | O8: Yes | Q8: Yes | R8: Yes | S8: Yes | U8: Yes
A10: 8127 | B10: Rolly Autowash | C10: Cameron | D10: Yes | F10: Yes | G10: No | H10: Yes | I10: Yes | J10: N/A | K10: Yes | M10: Yes
A12: 8183 | B12: Murney - 1 Freight Drive + 109 Iport | C12: Cameron | D12: Yes | F12: Yes | G12: Yes | H12: Yes | I12: Yes | J12: Yes | K12: Yes | L12: Yes | M12: Yes | O12: Yes | P12: Yes | Q12: Yes | R12: Yes | S12: Yes | U12: Yes
A14: 8886 | B14: Monkey Toe - Fisher fit out | C14: Cameron | F14: Yes | G14: No | H14: N/A | I14: Yes | J14: Yes | K14: Yes
A16: 8887 | B16: Tenancy 2 - Fisher Fit out | C16: Cameron | F16: Yes | G16: No | H16: N/A | I16: Yes | J16: Yes | K16: Yes
A18: 8670 | B18: Studio DB - tautara fit out | C18: Cameron | D18: Yes
A20: 8907 | B20: 35 Mania | C20: Cameron | D20: Yes
A22: 9065 | B22: Cooltranz stage 4 | C22: Cameron | D22: Yes | F22: Yes | G22: Yes | H22: N/A | I22: Yes | J22: Yes | K22: Yes | L22: Yes | M22: Yes | N22: Yes | Q22: Yes | R22: Yes | S22: N/A | U22: Yes
A24: 9259 | B24: Andrew Reeve Stage 2 | C24: Cameron | D24: Yes | F24: Yes | G24: Yes | H24: N/A | I24: Yes | J24: Yes | K24: Yes | L24: Yes | M24: Yes | N24: Yes | O24: Yes | P24: Yes | Q24: Yes | R24: Yes | S24: N/A | U24: Yes
A26: 8352 | B26: 5 Sanscrit Place | C26: Tom | D26: Yes | E26: N/A | F26: Yes | H26: N/A | I26: N/A | K26: N/A | L26: Yes | O26: Yes
A28: 8234 | B28: Melhuish House | C28: Tom
A30: 8214 | B30: 6 Tiroroa Lane | C30: Tom | D30: Yes | E30: N/A | K30: N/A
A32: 6792 | B32: Major Hornbrook | C32: Tom | D32: Yes | E32: Yes | F32: Yes | G32: Yes | H32: N/A | I32: Yes | J32: Yes | K32: Yes | L32: Yes | M32: N/A | N32: Yes | O32: Yes | Q32: NA | U32: Yes
A34: 8840 | B34: Inline Architecture | C34: Tom
A36: 8769 | B36: Percival Bach
A38: 7901 | B38: St Albans Street
A40: 8923 | B40: 4 Perry St
A42: 7864 | B42: Ryans House
A44: 7912 | B44: 71A Fendalton Road | C44: Tom | D44: Yes | E44: N/A | G44: 45979 | J44: N/A | K44: N/A | O44: No
A46: 8360 | B46: Dixon House | C46: Tom | D46: Yes | E46: N/A | F46: Yes | G46: 45979 | H46: N/A | I46: Yes | J46: N/A | K46: N/A | L46: N/A | M46: N/A | O46: Yes
A48: 8337 | B48: Waimak Dairys
A50: 9240 | B50: Daves Twizel Shack
A52: 7428 | B52: FAB Pegasus Lakeside | C52: Tom | D52: Yes | E52: N/A | F52: Yes | G52: 45979 | H52: Yes | J52: N/A | K52: N/A | L52: N/A | O52: No
A54: 9351 | B54: Harewood Golf Club | C54: Tom
A56: 7429 | B56: Taggart House | C56: Tom | D56: Yes | E56: N/A | F56: Yes | G56: 45979 | H56: N/A | I56: N/A | J56: N/A | K56: N/A | L56: N/A | O56: No
A58: 9508 | B58: St Barnabas Church | C58: Tom | E58: N/A | F58: Yes | G58: 45979 | H58: N/A | I58: N/A | J58: N/A | K58: N/A | L58: N/A | O58: No
E60: N/A | F60: Yes | H60: N/A | J60: N/A
B62: Contracting
A64: 8946 | B64: Westcoast Vaults | C64: Cameron | D64: Yes | E64: N/A | F64: Yes | G64: Yes | H64: Yes | I64: Yes | J64: Yes | K64: Yes | L64: Yes | N64: Yes | Q64: Yes | R64: Yes | S64: Yes | U64: Yes
A66: 8308 | B66: Roydvale | C66: Tom | E66: N/A | F66: Yes | H66: N/A | J66: N/A
A68: 8530 | B68: 224 Cashel St - Eastern WC Block Reno

Sheet Deliverables Sheet
A1: Updated Job Spreadsheet
A2: Job Number | B2: Job Name | C2: Week | D2: Quoted Price | E2: Claim to date | F2: Remaining to claim | G2: % Claim remaining | H2: Total quoted cost | I2: Total actual cost | J2: Quoted material cost | K2: Actual material cost | L2: Material cost remaining | M2: Material % remaining | N2: Estimated % of materials recieved | O2: Quoted labour cost | P2: Actual labour cost | Q2: Labour cost remaining | R2: Labour cost % remaining | S2: Quoted labour hours | T2: Actual labour hours | U2: Labour hours remaining | V2: Labour hour % remaining | W2: Estimated % of job complete | X2: GP $ Per Hour | Y2: Quoted GP $ Per Hour | Z2: Margin to date | AA2: Quoted margin
AH3: Hours calcs | AI3: Materials calcs
A4: 7658 | B4: Charity Hospital | C4: Start of month | D4: 245679.5 | E4: 216530.08 | F4: 29149.42 | G4: 0.11864816 | H4: 208360.5 | I4: 167957.68 | J4: 180366.49 | K4: 138548.02 | L4: 41818.47 | M4: 0.23185277 | N4: 0.9 | O4: 27994.01 | P4: 29409.66 | Q4: -1415.65 | R4: -0.050569747 | S4: 565.45 | T4: 588.25 | U4: -22.8 | V4: -0.040321868 | X4: 82.571016 | Y4: 65.998776 | Z4: 0.2243 | AA4: 0.1519 | AD4: Hours calc for monthly claims | AE4: -418 | AH4: -418 | AI4: -92952.56
C5: Week 1 | D5: 245679.5 | E5: 216530.08 | F5: 29149.42 | G5: 0.11864816 | H5: 208360.5 | I5: 168361.6 | J5: 180366.49 | K5: 138438.46 | L5: 41928.03 | M5: 0.2324602 | O5: 27994.01 | P5: 29923.14 | Q5: -1929.13 | R5: -0.068912242 | S5: 565.45 | T5: 600.25 | U5: -34.8 | V5: -0.061543903 | X5: 80.247364 | Y5: 65.998776 | Z5: 0.2225 | AA5: 0.1519 | AD5: Materials calc for monthly claims | AE5: -92952.56
C6: Week 2 | D6: 245679.5 | E6: 216530.08 | F6: 29149.42 | G6: 0.11864816 | H6: 208360.5 | I6: 168361.6 | J6: 180366.49 | K6: 138438.46 | L6: 41928.03 | M6: 0.2324602 | O6: 27994.01 | P6: 29923.14 | Q6: -1929.13 | R6: -0.068912242 | S6: 565.45 | T6: 600.25 | U6: -34.8 | V6: -0.061543903 | X6: 80.247364 | Y6: 65.998776 | Z6: 0.2225 | AA6: 0.1519
C7: Week 3 | AD7: Estimated months claim | AE7: 0
C8: Week 4
C9: Week 5 | AH9: -418 | AI9: -92952.56
A11: 8142 | B11: Fisher Developements | C11: Start of month | D11: 129074.86 | E11: 85864.08 | F11: 43210.78 | G11: 0.33477301 | H11: 101420.72 | I11: 74137.32 | J11: 83645.65 | K11: 69538.04 | L11: 14107.61 | M11: 0.16865922 | O11: 17775.07 | P11: 4599.28 | Q11: 13175.79 | R11: 0.74125109 | S11: 356.07 | T11: 93.25 | U11: 262.82 | V11: 0.73811329 | W11: 0.3 | X11: 125.75614 | Y11: 77.66491 | Z11: 0.1366 | AA11: 0.2142 | AD11: Hours calc for monthly claims | AE11: -52.5 | AH11: -52.5 | AI11: -45701.86
C12: Week 1 | D12: 129074.86 | E12: 85864.08 | F12: 43210.78 | G12: 0.33477301 | H12: 101420.72 | I12: 79791.03 | J12: 83645.65 | K12: 71604.5 | L12: 12041.15 | M12: 0.14395429 | O12: 17775.07 | P12: 8186.53 | Q12: 9588.54 | R12: 0.53943754 | S12: 356.07 | T12: 168.25 | U12: 187.82 | V12: 0.52748055 | X12: 36.095394 | Y12: 77.66491 | Z12: 0.0707 | AA12: 0.2142 | AD12: Materials calc for monthly claims | AE12: -45701.86
C13: Week 2 | D13: 129996.92 | E13: 85864.08 | F13: 44132.84 | G13: 0.33949143 | H13: 101885.52 | I13: 79864.19 | J13: 83735.42 | K13: 71677.66 | L13: 12057.76 | M13: 0.14399832 | O13: 18150.1 | P13: 8186.53 | Q13: 9963.57 | R13: 0.548954 | S13: 363.57 | T13: 168.25 | U13: 195.32 | V13: 0.53722804 | X13: 35.660565 | Y13: 77.320439 | Z13: 0.0699 | AA13: 0.2162
C14: Week 3 | AD14: Estimated months claim | AE14: 0
C15: Week 4
C16: Week 5 | AH16: -52.5 | AI16: -45701.86
A18: 8824 | B18: 3 Innovation Road | C18: Start of month | D18: 27500.32 | E18: 11999.08 | F18: 15501.24 | G18: 0.5636749 | H18: 19565.83 | I18: 7621.92 | J18: 13767.34 | K18: 5911.24 | L18: 7856.1 | M18: 0.57063311 | O18: 5798.49 | P18: 1710.68 | Q18: 4087.81 | R18: 0.70497837 | S18: 125.39 | T18: 34.75 | U18: 90.64 | V18: 0.72286466 | W18: 0.25 | X18: 125.96144 | Y18: 63.278465 | Z18: 0.3648 | AA18: 0.2885 | AD18: Hours calc for monthly claims | AE18: -34.75 | AH18: -34.75 | AI18: -5911.24
C19: Week 1 | D19: 27500.32 | E19: 11999.08 | F19: 15501.24 | G19: 0.5636749 | H19: 19565.83 | I19: 7921.92 | J19: 13767.34 | K19: 6211.24 | L19: 7556.1 | M19: 0.54884241 | O19: 5798.49 | P19: 1710.68 | Q19: 4087.81 | R19: 0.70497837 | S19: 125.39 | T19: 34.75 | U19: 90.64 | V19: 0.72286466 | X19: 117.32835 | Y19: 63.278465 | Z19: 0.3398 | AA19: 0.2885 | AD19: Materials calc for monthly claims | AE19: -5911.24
C20: Week 2 | D20: 27500.32 | E20: 11999.08 | F20: 15501.24 | G20: 0.5636749 | H20: 19565.83 | I20: 7921.92 | J20: 13767.34 | K20: 6211.24 | L20: 7556.1 | M20: 0.54884241 | O20: 5798.49 | P20: 1710.68 | Q20: 4087.81 | R20: 0.70497837 | S20: 125.39 | T20: 34.75 | U20: 90.64 | V20: 0.72286466 | X20: 117.32835 | Y20: 63.278465 | Z20: 0.3398 | AA20: 0.2885
C21: Week 3 | AD21: Estimated months claim | AE21: 0
C22: Week 4
C23: Week 5 | AH23: -34.75 | AI23: -5911.24
A25: 8127 | B25: Rolly Autowash | C25: Start of month | D25: 150850.82 | E25: 144370.8 | F25: 6480.02 | G25: 0.042956478 | H25: 102178.42 | I25: 85848.41 | J25: 62464.86 | K25: 57454 | L25: 5010.86 | M25: 0.080218862 | N25: 0.9 | O25: 39713.56 | P25: 28394.41 | Q25: 11319.15 | R25: 0.28501978 | S25: 795.22 | T25: 577.75 | U25: 217.47 | V25: 0.27347149 | W25: 0.6 | X25: 101.29362 | Y25: 61.206215 | Z25: 0.4054 | AA25: 0.3227 | AD25: Hours calc for monthly claims | AE25: -388.25 | AH25: -388.25 | AI25: -56964.81
C26: Week 1 | D26: 150850.82 | E26: 144370.8 | F26: 6480.02 | G26: 0.042956478 | H26: 102178.42 | I26: 89222.05 | J26: 62464.86 | K26: 58984 | L26: 3480.86 | M26: 0.055725091 | O26: 39713.56 | P26: 30238.05 | Q26: 9475.51 | R26: 0.23859634 | S26: 795.22 | T26: 615 | U26: 180.22 | V26: 0.22662911 | X26: 89.672764 | Y26: 61.206215 | Z26: 0.382 | AA26: 0.3227 | AD26: Materials calc for monthly claims | AE26: -56964.81
C27: Week 2 | D27: 153553.67 | E27: 144370.8 | F27: 9182.87 | G27: 0.059802348 | H27: 104026.09 | I27: 89600.47 | J27: 63812.49 | K27: 59331.43 | L27: 4481.06 | M27: 0.070222303 | O27: 40213.6 | P27: 30269.04 | Q27: 9944.56 | R27: 0.24729345 | S27: 805.22 | T27: 615.5 | U27: 189.72 | V27: 0.23561263 | X27: 88.985102 | Y27: 61.50814 | Z27: 0.3794 | AA27: 0.3225
C28: Week 3 | AD28: Estimated months claim | AE28: 0
C29: Week 4
C30: Week 5 | AH30: -388.25 | AI30: -56964.81
A32: 8183 | B32: Murney - 1 Freight Drive + 109 Iport | C32: Start of month | D32: 396422.03 | E32: 259347.71 | F32: 137074.32 | G32: 0.34577877 | H32: 327431.12 | I32: 216344.6 | J32: 271519.78 | K32: 195955.93 | L32: 75563.85 | M32: 0.27829961 | O32: 55911.34 | P32: 20388.67 | Q32: 35522.67 | R32: 0.63533927 | S32: 1120.27 | T32: 476.25 | U32: 644.02 | V32: 0.57487927 | W32: 0.4 | X32: 90.295244 | Y32: 61.584182 | Z32: 0.1658 | AA32: 0.174 | AD32: Hours calc for monthly claims | AE32: -387.5 | AH32: -387.5 | AI32: -132316.71
C33: Week 1 | D33: 396422.03 | E33: 259347.71 | F33: 137074.32 | G33: 0.34577877 | H33: 327431.12 | I33: 223659.54 | J33: 271519.78 | K33: 197370.72 | L33: 74149.06 | M33: 0.27308898 | O33: 55911.34 | P33: 26288.82 | Q33: 29622.52 | R33: 0.52981238 | S33: 1120.27 | T33: 607.75 | U33: 512.52 | V33: 0.45749685 | X33: 58.721794 | Y33: 61.584182 | Z33: 0.1376 | AA33: 0.174 | AD33: Materials calc for monthly claims | AE33: -132316.71
C34: Week 2 | D34: 397238.61 | E34: 259347.71 | F34: 137890.9 | G34: 0.34712361 | H34: 328046.93 | I34: 223743.65 | J34: 271925.57 | K34: 197386.58 | L34: 74538.99 | M34: 0.27411541 | O34: 56121.36 | P34: 26357.07 | Q34: 29764.29 | R34: 0.53035582 | S34: 1124.47 | T34: 609 | U34: 515.47 | V34: 0.45841152 | X34: 58.463153 | Y34: 61.532703 | Z34: 0.1373 | AA34: 0.1742
C35: Week 3 | AD35: Estimated months claim | AE35: 0
C36: Week 4
C37: Week 5 | AH37: -387.5 | AI37: -132316.71
A39: 8886 | B39: Monkey Toe - Fisher fit out | C39: Start of month | D39: 128258.5 | E39: 53944.83 | F39: 74313.67 | G39: 0.57940542 | H39: 94098.32 | I39: 42273.69 | J39: 69042.09 | K39: 35075.75 | L39: 33966.34 | M39: 0.4919657 | O39: 25056.23 | P39: 7197.94 | Q39: 17858.29 | R39: 0.71272853 | S39: 501.83 | T39: 143 | U39: 358.83 | V39: 0.71504294 | W39: 0.4 | X39: 81.616364 | Y39: 68.071224 | Z39: 0.2164 | AA39: 0.2663 | AD39: Hours calc for monthly claims | AE39: -112 | AH39: -112 | AI39: -26847.46
C40: Week 1 | D40: 128258.5 | E40: 53944.83 | F40: 74313.67 | G40: 0.57940542 | H40: 94098.32 | I40: 49261.61 | J40: 69042.09 | K40: 35683.74 | L40: 33358.35 | M40: 0.48315962 | O40: 25056.23 | P40: 13577.87 | Q40: 11478.36 | R40: 0.45810403 | S40: 501.83 | T40: 299.5 | U40: 202.33 | V40: 0.40318435 | X40: 15.636795 | Y40: 68.071224 | Z40: 0.0868 | AA40: 0.2663 | AD40: Materials calc for monthly claims | AE40: -26847.46
C41: Week 2 | D41: 128258.5 | E41: 53944.83 | F41: 74313.67 | G41: 0.57940542 | H41: 94098.32 | I41: 49519.82 | J41: 69042.09 | K41: 35683.74 | L41: 33358.35 | M41: 0.48315962 | O41: 25056.23 | P41: 13836.08 | Q41: 11220.15 | R41: 0.44779881 | S41: 501.83 | T41: 308.25 | U41: 193.58 | V41: 0.38574816 | X41: 14.355264 | Y41: 68.071224 | Z41: 0.082 | AA41: 0.2663
C42: Week 3 | AD42: Estimated months claim | AE42: 0
C43: Week 4
C44: Week 5 | AH44: -112 | AI44: -26847.46
A46: 8887 | B46: Tenancy 2 - Fisher Fit out | C46: Start of month | D46: 65693.36 | E46: 33326.49 | F46: 32366.87 | G46: 0.49269622 | H46: 50582.37 | I46: 25211.58 | J46: 39438.99 | K46: 20456.64 | L46: 18982.35 | M46: 0.48130923 | N46: 0 | O46: 11143.38 | P46: 4754.94 | Q46: 6388.44 | R46: 0.57329464 | S46: 223.22 | T46: 104.25 | U46: 118.97 | V46: 0.53297196 | W46: 0.4 | X46: 77.840863 | Y46: 67.695505 | Z46: 0.2435 | AA46: 0.23 | AD46: Hours calc for monthly claims | AE46: -86.75 | AH46: -86.75 | AI46: -15639.05
C47: Week 1 | D47: 65693.36 | E47: 33326.49 | F47: 32366.87 | G47: 0.49269622 | H47: 50582.37 | I47: 25196.36 | J47: 39438.99 | K47: 20036.42 | L47: 19402.57 | M47: 0.49196417 | O47: 11143.38 | P47: 5159.94 | Q47: 5983.44 | R47: 0.53695019 | S47: 223.22 | T47: 113.25 | U47: 109.97 | V47: 0.49265299 | X47: 71.789227 | Y47: 67.695505 | Z47: 0.244 | AA47: 0.23 | AD47: Materials calc for monthly claims | AE47: -15639.05
C48: Week 2 | D48: 65693.36 | E48: 33326.49 | F48: 32366.87 | G48: 0.49269622 | H48: 50582.37 | I48: 25196.36 | J48: 39438.99 | K48: 20036.42 | L48: 19402.57 | M48: 0.49196417 | O48: 11143.38 | P48: 5159.94 | Q48: 5983.44 | R48: 0.53695019 | S48: 223.22 | T48: 113.25 | U48: 109.97 | V48: 0.49265299 | X48: 71.789227 | Y48: 67.695505 | Z48: 0.244 | AA48: 0.23
C49: Week 3 | AD49: Estimated months claim | AE49: 0
C50: Week 4
C51: Week 5 | AH51: -86.75 | AI51: -15639.05
A53: 8670 | B53: Studio DB - tautara fit out | C53: Start of month | D53: 155296.79 | E53: 127814.48 | F53: 27482.31 | G53: 0.17696638 | H53: 109364.97 | I53: 95320.51 | J53: 75135.01 | K53: 71614.55 | L53: 3520.46 | M53: 0.046855121 | O53: 34229.96 | P53: 23705.96 | Q53: 10524 | R53: 0.30744996 | S53: 685.48 | T53: 502.25 | U53: 183.23 | V53: 0.26730174 | W53: 0.3 | X53: 64.696804 | Y53: 67.006795 | Z53: 0.2542 | AA53: 0.2958 | AD53: Hours calc for monthly claims | AE53: -269 | AH53: -269 | AI53: -66399.88
C54: Week 1 | D54: 155296.79 | E54: 127814.48 | F54: 27482.31 | G54: 0.17696638 | H54: 109364.97 | I54: 96483.38 | J54: 75135.01 | K54: 71221.34 | L54: 3913.67 | M54: 0.0520885 | O54: 34229.96 | P54: 25262.04 | Q54: 8967.92 | R54: 0.26199037 | S54: 685.48 | T54: 533.75 | U54: 151.73 | V54: 0.22134854 | X54: 58.699953 | Y54: 67.006795 | Z54: 0.2451 | AA54: 0.2958 | AD54: Materials calc for monthly claims | AE54: -66399.88
C55: Week 2 | D55: 155296.79 | E55: 127814.48 | F55: 27482.31 | G55: 0.17696638 | H55: 109364.97 | I55: 97978.14 | J55: 75135.01 | K55: 71357.43 | L55: 3777.58 | M55: 0.050277228 | O55: 34229.96 | P55: 26620.71 | Q55: 7609.25 | R55: 0.22229795 | S55: 685.48 | T55: 561.5 | U55: 123.98 | V55: 0.18086596 | X55: 53.136848 | Y55: 67.006795 | Z55: 0.2334 | AA55: 0.2958
C56: Week 3 | AD56: Estimated months claim | AE56: 0
C57: Week 4
C58: Week 5 | AH58: -269 | AI58: -66399.88
A60: 8907 | B60: 35 Mania | C60: Start of month | D60: 20420.56 | E60: 20420.56 | F60: 0 | G60: 0 | H60: 15859.68 | I60: 13435.12 | J60: 12689.1 | K60: 11478.25 | L60: 1210.85 | M60: 0.095424419 | O60: 3170.58 | P60: 1956.87 | Q60: 1213.71 | R60: 0.38280378 | S60: 63.5 | T60: 48.25 | U60: 15.25 | V60: 0.24015748 | W60: 0.4 | X60: 144.77596 | Y60: 71.824956 | Z60: 0.3421 | AA60: 0.2233 | AD60: Hours calc for monthly claims | AE60: -26.75 | AH60: -26.75 | AI60: -11159.14
C61: Week 1 | D61: 20420.56 | E61: 20420.56 | F61: 0 | G61: 0 | H61: 15859.68 | I61: 13435.12 | J61: 12689.1 | K61: 11478.25 | L61: 1210.85 | M61: 0.095424419 | O61: 3170.58 | P61: 1956.87 | Q61: 1213.71 | R61: 0.38280378 | S61: 63.5 | T61: 48.25 | U61: 15.25 | V61: 0.24015748 | X61: 144.77596 | Y61: 71.824956 | Z61: 0.3421 | AA61: 0.2233 | AD61: Materials calc for monthly claims | AE61: -11159.14
C62: Week 2 | D62: 20420.56 | E62: 20420.56 | F62: 0 | G62: 0 | H62: 15859.68 | I62: 13435.12 | J62: 12689.1 | K62: 11478.25 | L62: 1210.85 | M62: 0.095424419 | O62: 3170.58 | P62: 1956.87 | Q62: 1213.71 | R62: 0.38280378 | S62: 63.5 | T62: 48.25 | U62: 15.25 | V62: 0.24015748 | X62: 144.77596 | Y62: 71.824956 | Z62: 0.3421 | AA62: 0.2233
C63: Week 3 | AD63: Estimated months claim | AE63: 0
C64: Week 4
C65: Week 5 | AH65: -26.75 | AI65: -11159.14
A67: 9065 | B67: Cooltranz stage 4 | C67: Start of month | D67: 47801.68 | E67: 10650.43 | F67: 37151.25 | G67: 0.77719549 | H67: 35572.59 | I67: 9981.43 | J67: 27136.55 | K67: 9832.65 | L67: 17303.9 | M67: 0.63766028 | O67: 8436.04 | P67: 148.78 | Q67: 8287.26 | R67: 0.98236376 | S67: 169.32 | T67: 2.75 | U67: 166.57 | V67: 0.98375856 | X67: 243.27273 | Y67: 72.224754 | Z67: 0.0628 | AA67: 0.2558 | AD67: Hours calc for monthly claims | AI67: -5397.27
C68: Week 1 | D68: 47801.68 | E68: 10650.43 | F68: 37151.25 | G68: 0.77719549 | H68: 35572.59 | I68: 10547.08 | J68: 27136.55 | K68: 10398.3 | L68: 16738.25 | M68: 0.6168157 | O68: 8436.04 | P68: 148.78 | Q68: 8287.26 | R68: 0.98236376 | S68: 169.32 | T68: 2.75 | U68: 166.57 | V68: 0.98375856 | X68: 37.581818 | Y68: 72.224754 | Z68: 0.0097 | AA68: 0.2558 | AD68: Materials calc for monthly claims | AE68: -5397.27
C69: Week 2 | D69: 53029.71 | E69: 10650.43 | F69: 42379.28 | G69: 0.79916107 | H69: 39055.78 | I69: 16807.92 | J69: 29537.29 | K69: 16659.14 | L69: 12878.15 | M69: 0.43599633 | O69: 9518.49 | P69: 148.78 | Q69: 9369.71 | R69: 0.98436937 | S69: 193.32 | T69: 2.75 | U69: 190.57 | V69: 0.98577488 | X69: -2239.0873 | Y69: 72.283966 | Z69: -0.5781 | AA69: 0.2635
C70: Week 3 | AD70: Estimated months claim | AE70: 0
C71: Week 4
C72: Week 5 | AI72: -5397.27
A74: 9259 | B74: Andrew Reeve Stage 2 | C74: Start of month | D74: 77166.16 | E74: 44764.99 | F74: 32401.17 | G74: 0.41988833 | H74: 54302.66 | I74: 31918.93 | J74: 31383.39 | K74: 27205.52 | L74: 4177.87 | M74: 0.1331236 | O74: 22919.27 | P74: 4713.41 | Q74: 18205.86 | R74: 0.79434729 | S74: 470.62 | T74: 96.25 | U74: 374.37 | V74: 0.79548255 | W74: 0 | X74: 133.46556 | Y74: 48.58166 | Z74: 0.287 | AA74: 0.2963 | AD74: Hours calc for monthly claims
C75: Week 1 | D75: 77166.16 | E75: 44764.99 | F75: 32401.17 | G75: 0.41988833 | H75: 54302.66 | I75: 29696.65 | J75: 31383.39 | K75: 23592.6 | L75: 7790.79 | M75: 0.24824565 | O75: 22919.27 | P75: 6104.05 | Q75: 16815.22 | R75: 0.73367171 | S75: 470.62 | T75: 120.25 | U75: 350.37 | V75: 0.744486 | X75: 125.30844 | Y75: 48.58166 | Z75: 0.3366 | AA75: 0.2963 | AD75: Materials calc for monthly claims
C76: Week 2 | D76: 77408.3 | E76: 44764.99 | F76: 32643.31 | G76: 0.42170297 | H76: 54446.73 | I76: 31054.89 | J76: 31451.7 | K76: 23776.52 | L76: 7675.18 | M76: 0.24403069 | O76: 22995.03 | P76: 7278.37 | Q76: 15716.66 | R76: 0.68348073 | S76: 472.14 | T76: 144.25 | U76: 327.89 | V76: 0.69447621 | X76: 95.044021 | Y76: 48.632968 | Z76: 0.3063 | AA76: 0.2966
C77: Week 3 | AD77: Estimated months claim | AE77: 0
C78: Week 4
C79: Week 5
A81: 8352 | B81: 5 Sanscrit Place | C81: Start of month | D81: 25467.84 | E81: 19598.41 | F81: 5869.43 | G81: 0.23046438 | H81: 16606.83 | I81: 12958.24 | J81: 9659.99 | K81: 5354.12 | L81: 4305.87 | M81: 0.4457427 | N81: 0 | O81: 6946.84 | P81: 7604.12 | Q81: -657.28 | R81: -0.094615681 | S81: 139.07 | T81: 147.75 | U81: -8.68 | V81: -0.062414611 | X81: 44.941929 | Y81: 63.716216 | Z81: 0.3388 | AA81: 0.3479 | AD81: Hours calc for monthly claims | AE81: -143.25 | AH81: -143.25 | AI81: -5569.48
C82: Week 1 | D82: 25467.84 | E82: 19598.41 | F82: 5869.43 | G82: 0.23046438 | H82: 16606.83 | I82: 12958.24 | J82: 9659.99 | K82: 5354.12 | L82: 4305.87 | M82: 0.4457427 | O82: 6946.84 | P82: 7604.12 | Q82: -657.28 | R82: -0.094615681 | S82: 139.07 | T82: 147.75 | U82: -8.68 | V82: -0.062414611 | X82: 44.941929 | Y82: 63.716216 | Z82: 0.3388 | AA82: 0.3479 | AD82: Materials calc for monthly claims | AE82: -5569.48
C83: Week 2 | D83: 25467.84 | E83: 19598.41 | F83: 5869.43 | G83: 0.23046438 | H83: 16606.83 | I83: 11832.36 | J83: 9659.99 | K83: 4228.24 | L83: 5431.75 | M83: 0.56229354 | O83: 6946.84 | P83: 7604.12 | Q83: -657.28 | R83: -0.094615681 | S83: 139.07 | T83: 147.75 | U83: -8.68 | V83: -0.062414611 | X83: 52.562098 | Y83: 63.716216 | Z83: 0.3963 | AA83: 0.3479
C84: Week 3 | AD84: Estimated months claim | AE84: 0
C85: Week 4
C86: Week 5 | AH86: -143.25 | AI86: -5569.48
A88: 8234 | B88: Melhuish House | C88: Start of month | D88: 37083.03 | E88: 36381.33 | F88: 701.7 | G88: 0.018922402 | H88: 27002.93 | I88: 26005.99 | J88: 15440.32 | K88: 14988.44 | L88: 451.88 | M88: 0.029266233 | N88: 0 | O88: 11562.61 | P88: 11017.55 | Q88: 545.06 | R88: 0.047139876 | S88: 231.75 | T88: 224.25 | U88: 7.5 | V88: 0.03236246 | X88: 46.266845 | Y88: 43.495571 | Z88: 0.2852 | AA88: 0.2718 | AD88: Hours calc for monthly claims | AE88: -148.5 | AH88: -148.5 | AI88: -14143.19
C89: Week 1 | D89: 37083.03 | E89: 36381.33 | F89: 701.7 | G89: 0.018922402 | H89: 27002.93 | I89: 25060.53 | J89: 15440.32 | K89: 13974.73 | L89: 1465.59 | M89: 0.094919665 | O89: 11562.61 | P89: 11085.8 | Q89: 476.81 | R89: 0.041237229 | S89: 231.75 | T89: 225.5 | U89: 6.25 | V89: 0.026968716 | X89: 50.203104 | Y89: 43.495571 | Z89: 0.3112 | AA89: 0.2718 | AD89: Materials calc for monthly claims | AE89: -14143.19
C90: Week 2 | D90: 37083.03 | E90: 36381.33 | F90: 701.7 | G90: 0.018922402 | H90: 27002.93 | I90: 25060.53 | J90: 15440.32 | K90: 13974.73 | L90: 1465.59 | M90: 0.094919665 | O90: 11562.61 | P90: 11085.8 | Q90: 476.81 | R90: 0.041237229 | S90: 231.75 | T90: 225.5 | U90: 6.25 | V90: 0.026968716 | X90: 50.203104 | Y90: 43.495571 | Z90: 0.3112 | AA90: 0.2718
C91: Week 3 | AD91: Estimated months claim | AE91: 0
C92: Week 4
C93: Week 5 | AH93: -148.5 | AI93: -14143.19
A95: 8214 | B95: 6 Tiroroa Lane | C95: Start of month | D95: 26186.14 | E95: 5762.27 | F95: 20423.87 | G95: 0.77994962 | H95: 19428.98 | I95: 7925.81 | J95: 12051.32 | K95: 7679.91 | L95: 4371.41 | M95: 0.36273288 | N95: 0 | O95: 7377.66 | P95: 245.9 | Q95: 7131.76 | R95: 0.96666965 | S95: 147.9 | T95: 5 | U95: 142.9 | V95: 0.96619337 | X95: -432.708 | Y95: 45.687352 | Z95: -0.3755 | AA95: 0.258 | AD95: Hours calc for monthly claims | AE95: -5 | AH95: -5 | AI95: -7679.91
C96: Week 1 | D96: 26186.14 | E96: 5762.27 | F96: 20423.87 | G96: 0.77994962 | H96: 19428.98 | I96: 7925.81 | J96: 12051.32 | K96: 7679.91 | L96: 4371.41 | M96: 0.36273288 | O96: 7377.66 | P96: 245.9 | Q96: 7131.76 | R96: 0.96666965 | S96: 147.9 | T96: 5 | U96: 142.9 | V96: 0.96619337 | X96: -432.708 | Y96: 45.687352 | Z96: -0.3755 | AA96: 0.258 | AD96: Materials calc for monthly claims | AE96: -7679.91
C97: Week 2 | D97: 26186.14 | E97: 5762.27 | F97: 20423.87 | G97: 0.77994962 | H97: 19428.98 | I97: 7925.81 | J97: 12051.32 | K97: 7679.91 | L97: 4371.41 | M97: 0.36273288 | O97: 7377.66 | P97: 245.9 | Q97: 7131.76 | R97: 0.96666965 | S97: 147.9 | T97: 5 | U97: 142.9 | V97: 0.96619337 | X97: -432.708 | Y97: 45.687352 | Z97: -0.3755 | AA97: 0.258
C98: Week 3 | AD98: Estimated months claim | AE98: 0
C99: Week 4
C100: Week 5 | AH100: -5 | AI100: -7679.91
A102: 6792 | B102: Major Hornbrook | C102: Start of month | D102: 32473.02 | E102: 33188.03 | F102: -715.01 | G102: -0.022018587 | H102: 23075.07 | I102: 30925.21 | J102: 12691.21 | K102: 15184.27 | L102: -2493.06 | M102: -0.1964399 | N102: 0 | O102: 10383.86 | P102: 15740.94 | Q102: -5357.08 | R102: -0.51590449 | S102: 208.2 | T102: 317.25 | U102: -109.05 | V102: -0.52377522 | X102: 7.1326084 | Y102: 45.139085 | Z102: 0.0682 | AA102: 0.2894 | AD102: Hours calc for monthly claims | AE102: -317.25 | AH102: -317.25 | AI102: -16562.52
C103: Week 1 | D103: 32473.02 | E103: 33188.03 | F103: -715.01 | G103: -0.022018587 | H103: 23075.07 | I103: 30925.21 | J103: 12691.21 | K103: 15184.27 | L103: -2493.06 | M103: -0.1964399 | O103: 10383.86 | P103: 15740.94 | Q103: -5357.08 | R103: -0.51590449 | S103: 208.2 | T103: 317.25 | U103: -109.05 | V103: -0.52377522 | X103: 7.1326084 | Y103: 45.139085 | Z103: 0.0682 | AA103: 0.2894 | AD103: Materials calc for monthly claims | AE103: -16562.52
C104: Week 2 | D104: 32473.02 | E104: 32473.03 | F104: -0.01 | G104: -3.0794795e-07 | H104: 23075.07 | I104: 31170.94 | J104: 12691.21 | K104: 15089.13 | L104: -2397.92 | M104: -0.18894337 | O104: 10383.86 | P104: 16081.81 | Q104: -5697.95 | R104: -0.5487314 | S104: 208.2 | T104: 324.25 | U104: -116.05 | V104: -0.55739673 | X104: 4.0156978 | Y104: 45.139085 | Z104: 0.0401 | AA104: 0.2894
C105: Week 3 | AD105: Estimated months claim | AE105: 0
C106: Week 4
C107: Week 5 | AH107: -317.25 | AI107: -16562.52
A109: 8840 | B109: Inline Architecture | C109: Start of month | D109: 58902.56 | E109: 0 | F109: 58902.56 | G109: 1 | H109: 37601.88 | I109: 44893.89 | J109: 21415.85 | K109: 23634.19 | L109: -2218.34 | M109: -0.10358403 | N109: 0 | O109: 16186.03 | P109: 21259.7 | Q109: -5073.67 | R109: -0.31345982 | S109: 324.19 | T109: 461.5 | U109: -137.31 | V109: -0.42354792 | W109: 0 | X109: -20.453868 | Y109: 65.704314 | Z109: -0.2662 | AA109: 0.3616 | AD109: Hours calc for monthly claims | AE109: -204.75 | AH109: -204.75 | AI109: -12155.27
C110: Week 1 | D110: 58902.56 | E110: 0 | F110: 58902.56 | G110: 1 | H110: 37601.88 | I110: 45817.77 | J110: 21415.85 | K110: 23939.39 | L110: -2523.54 | M110: -0.11783515 | O110: 16186.03 | P110: 21878.38 | Q110: -5692.35 | R110: -0.3516829 | S110: 324.19 | T110: 472.75 | U110: -148.56 | V110: -0.45824979 | X110: 48.973178 | Y110: 65.704314 | Z110: 0.3357 | AA110: 0.3616 | AD110: Materials calc for monthly claims | AE110: -12155.27
C111: Week 2 | D111: 58902.56 | E111: 0 | F111: 58902.56 | G111: 1 | H111: 37601.88 | I111: 45817.77 | J111: 21415.85 | K111: 23939.39 | L111: -2523.54 | M111: -0.11783515 | O111: 16186.03 | P111: 21878.38 | Q111: -5692.35 | R111: -0.3516829 | S111: 324.19 | T111: 472.75 | U111: -148.56 | V111: -0.45824979 | X111: 48.973178 | Y111: 65.704314 | Z111: 0.3357 | AA111: 0.3616
C112: Week 3 | AD112: Estimated months claim | AE112: 0
C113: Week 4
C114: Week 5 | AH114: -204.75 | AI114: -12155.27
A116: 8769 | B116: Percival Bach | C116: Start of month | D116: 21404.82 | E116: 0 | F116: 21404.82 | G116: 1 | H116: 17514.09 | I116: 0 | J116: 13318.88 | K116: 0 | L116: 13318.88 | M116: 1 | N116: 0 | O116: 4195.21 | P116: 0 | Q116: 4195.21 | R116: 1 | S116: 84.05 | T116: 0 | U116: 84.05 | V116: 1 | W116: 0 | X116: 0 | Y116: 46.290622 | Z116: 0 | AA116: 0.1818 | AD116: Hours calc for monthly claims
...

Sheet Claim Calculator By Month
A1: Updated Job Spreadsheet
A2: Job Number | B2: Job Name | C2: Claim | D2: Costs | E2: Profit | F2: Retention | G2: Margin | H2: Quoted Margin | I2: Hours to complete before E.O.M | J2: Costs to come before E.O.M | K2: Total cost to come before E.O.M | L2: Estimated margin E.O.M | M2: GP End of month | N2: Hours this month | O2: GP $ per hour this month
A4: 7658 | B4: Charity Hospital | C4: 0 | D4: 403.92 | E4: -403.92 | F4: 0 | G4: 0 | H4: 0.2149 | I4: 50 | J4: 5000 | K4: 7000 | L4: 0 | M4: -7403.92 | N4: 20 | O4: -105.77029
A6: 8142 | B6: Fisher Developements | C6: 0 | D6: 5726.87 | E6: -5726.87 | F6: 0 | G6: 0 | H6: 0.23921459 | I6: 40 | J6: 272.6 | K6: 1872.6 | L6: 0 | M6: -7599.47 | N6: -52.5 | O6: 607.9576 | Q6: 14 Mirrors and 49 Downlights have been ordered
A8: 8824 | B8: 3 Innovation Road | C8: 0 | D8: 300 | E8: -300 | G8: 0 | H8: 0.28852355 | I8: 16 | K8: 640 | L8: 0 | M8: -940 | N8: -34.75 | O8: 50.133333
A10: 8127 | B10: Rolly Autowash | C10: 0 | D10: 3752.06 | E10: -3752.06 | F10: 0 | G10: 0 | H10: 0.32265254 | I10: 48 | J10: 3000 | K10: 4920 | L10: 0 | M10: -8672.06 | N10: -388.25 | O10: 25.487318
A12: 8183 | B12: Murney Custodian - 1 Freight Drive | C12: 0 | D12: 7399.05 | E12: -7399.05 | F12: 3 | G12: 0 | H12: 0.17631626 | I12: 16 | J12: 2000 | K12: 2640 | L12: 0 | M12: -10036.05 | N12: 53 | O12: -145.45 | Q12: Couldnt get this rite because of ers but they re claiming 30%
A14: 8886 | B14: Monkey Toe - Fisher fit out | C14: 0 | D14: 7246.13 | E14: -7246.13 | F14: 0 | G14: 0 | H14: 0.26633853 | I14: 0 | J14: 3000 | K14: 3000 | L14: 0 | M14: -10246.13 | N14: -112 | O14: 91.483304
A16: 8887 | B16: Tenancy 2 - Fisher Fit out | C16: 0 | D16: -15.22 | E16: 15.22 | G16: 0 | H16: 0.22635382 | I16: 0 | J16: 3000 | K16: 3000 | L16: 0 | M16: -2984.78 | N16: -86.75 | O16: 34.406686
A18: 8670 | B18: Studio DB - tautara fit out | C18: 0 | D18: 2657.63 | E18: -2657.63 | F18: 0 | G18: 0 | H18: 0.29653766 | I18: 80 | J18: 5000 | K18: 8200 | L18: 0 | M18: -10857.63 | N18: -269 | O18: 57.447778 | Q18: 48 Hours need to be made non Billable
A20: 8907 | B20: 35 Mania | C20: 0 | D20: 0 | E20: 0 | G20: 0 | H20: 0.22334745 | K20: 0 | L20: 0 | M20: 0 | O20: 0
A22: 9065 | B22: Cooltranz stage 4 | C22: 0 | D22: 6826.49 | E22: -6826.49 | F22: 3 | G22: 0 | H22: 0.25248826 | K22: 0 | L22: 0 | M22: -6823.49 | O22: 0
A24: 9259 | B24: Andrew Reeve Stage 2 | C24: 0 | D24: -864.04 | E24: 864.04 | F24: 3 | G24: 0 | K24: 0 | L24: 0 | M24: 867.04 | O24: 0
A26: 8352 | B26: 5 Sanscrit Place | C26: 0 | D26: -1125.88 | E26: 1125.88 | F26: 0 | G26: 0 | H26: 0.34792939 | J26: 0 | K26: 0 | L26: 0 | M26: 1125.88 | N26: -143.25 | O26: -7.8595462
A28: 8234 | B28: Melhuish House | C28: 0 | D28: -945.46 | E28: 945.46 | F28: 0 | G28: 0 | H28: 0.27182514 | K28: 0 | L28: 0 | M28: 945.46 | N28: -148.5 | O28: -6.366734
A30: 8214 | B30: 6 Tiroroa Lane | C30: 0 | D30: 0 | E30: 0 | F30: 0 | G30: 0 | H30: 0.25804338 | K30: 0 | L30: 0 | M30: 0 | N30: -5 | O30: 0
A32: 6792 | B32: Major Hornbrook | C32: -715 | D32: 245.73 | E32: -960.73 | F32: 0 | G32: 1.3436783 | H32: 0.28317296 | I32: 64 | J32: 0 | K32: 2560 | L32: 4.9240979 | M32: -3520.73 | N32: -317.25 | O32: 13.902192
A34: 8840 | B34: Inline Architecture | C34: 0 | D34: 923.88 | E34: -923.88 | F34: 0 | G34: 0 | H34: 0.36418204 | J34: 0 | K34: 0 | L34: 0 | M34: -923.88 | N34: -204.75 | O34: 4.5122344
A36: 8769 | B36: Percival Bach | C36: 0 | D36: 0 | E36: 0 | F36: 0 | G36: 0 | I36: 80 | J36: 0 | K36: 3200 | L36: 0 | M36: -3200 | O36: -40
A38: 7901 | B38: St Albans Street | C38: 52040.56 | D38: 576.98 | E38: 51463.58 | F38: 0 | G38: 0.98891288 | H38: 0.17509217 | K38: 0 | L38: 0.98891288 | M38: 51463.58 | O38: 0
A40: 8923 | B40: 4 Perry St | C40: 2127.81 | D40: 0 | E40: 2127.81 | F40: 0 | G40: 1 | H40: 0.26269298 | J40: 0 | K40: 0 | L40: 1 | M40: 2127.81 | N40: -2 | O40: -1063.905
A42: 7864 | B42: Ryans House | C42: 0 | D42: -13.37 | E42: 13.37 | G42: 0 | H42: 0.25724571 | I42: 0 | K42: 0 | L42: 0 | M42: 13.37 | N42: -266.75 | O42: -0.050121837
A44: 7912 | B44: 71A Fendalton Road | C44: 0 | D44: 0 | E44: 0 | G44: 0 | K44: 0 | L44: 0 | M44: 0 | O44: 0
A46: 8360 | B46: Dixon House | C46: 0 | D46: 0 | E46: 0 | G46: 0 | H46: 0.3058095 | K46: 0 | L46: 0 | M46: 0 | N46: -260.75 | O46: 0
A48: 8337 | B48: Waimak Dairys | C48: 0 | D48: 0 | E48: 0 | G48: 0 | H48: 0.22235078 | J48: 2530 | K48: 2530 | L48: 0 | M48: -2530 | N48: -44.75 | O48: 56.536313
A50: 9240 | B50: Daves Twizel Shack | C50: 0 | D50: 2116.21 | E50: -2116.21 | G50: 0 | I50: 0 | K50: 0 | L50: 0 | M50: -2116.21 | O50: 0 | Q50: $18627.12 from Sharp Electrical
A52: 7428 | B52: FAB Pegasus Lakeside | C52: 0 | D52: 2236.75 | E52: -2236.75 | G52: 0 | H52: 0.21598649 | I52: 32 | J52: 0 | K52: 1280 | L52: 0 | M52: -3516.75 | N52: -304.75 | O52: 12.893676
A54: 9351 | B54: Harewood Golf Club | C54: 0 | D54: 0 | E54: 0 | G54: 0 | H54: 0.45398706 | I54: 16 | J54: 0 | K54: 640 | L54: 0 | M54: -640 | N54: -11.25 | O54: -134.73684
A56: 7429 | B56: Taggart House | C56: 0 | D56: 0 | E56: 0 | G56: 0 | H56: 0.22356151 | I56: 10 | J56: 5000 | K56: 5400 | L56: 0 | M56: -5400 | N56: -32.25 | O56: 242.69663
A58: 9508 | B58: St Barnabas Church | C58: 0 | D58: 0 | E58: 0 | G58: 0 | K58: 0 | L58: 0 | M58: 0 | O58: 0
B62: Contracting | I62: 0
A64: 8946 | B64: Westcoast Vaults | C64: 0 | D64: 4470.96 | E64: -4470.96 | G64: 0 | H64: 0.14379005 | J64: 1750 | K64: 1750 | L64: 0 | M64: -6220.96 | O64: 0
A66: 8308 | B66: Roydvale | C66: 34650.4 | D66: 12036.18 | E66: 22614.22 | G66: 0.65263951 | H66: 0.25626552 | I66: 80 | J66: 0 | K66: 3200 | L66: 0.56028848 | M66: 19414.22 | N66: -1014.25 | O66: -20.780541
A67: ='Main Sheet'!A68 | B67: ='Main Sheet'!B68 | E67: =C67-D67 | G67: =(E67+F67)/C67 | H67: ='Deliverables Sheet'!AA228 | K67: =(I67*40)+J67 | L67: =((E67-K67)+F67)/C67 | M67: =SUM(E67:F67)-K67 | O67: =SUM(M67/(N67+I67))
A70: Totals | B70: Total | C70: 88103.77 | D70: 53954.87 | E70: 34148.9 | F70: GP% | G70: 0.38759862 | H70: E.O.M GP% | I70: -0.20071445
B71: Residential | C71: -22865.6 | D71: 32774.04 | E71: -55639.64 | G71: 2.4333339 | H71: E.O.M GP% | I71: 2.6852407

Sheet Upcoming Work Calculator
A1: Updated Job Spreadsheet
B2: Job | C2: Quoted Hours | D2: Hours Used | E2: Hours Remaining | F2: January | G2: February | H2: March | I2: April | J2: May | K2: June | L2: July | M2: August | N2: September | O2: October | P2: November | Q2: December
A3: Servicing | B3: Servicing work any job under 30 hours | F3: 500 | G3: 700 | H3: 700 | I3: 700 | J3: 700 | K3: 700 | L3: 700 | M3: 700 | N3: 700 | O3: 700 | P3: 700 | Q3: 500
A4: 7658 | B4: Charity Hospital | C4: 565.45 | D4: 600.25 | E4: -34.8 | F4: 0 | G4: 0 | H4: 0 | M4: 80 | S4: Programme Checked 24/03/26
A6: 8142 | B6: Fisher Developements | C6: 363.57 | D6: 168.25 | E6: 195.32 | N6: 80 | S6: Cant find a Programme for this.
A8: 8824 | B8: 3 Innovation Road | C8: 125.39 | D8: 34.75 | E8: 90.64 | N8: 90 | S8: Programme Checked 24/03/26
A10: 8127 | B10: Rolly Autowash | C10: 805.22 | D10: 615.5 | E10: 189.72 | M10: 200 | N10: 80 | O10: 0 | S10: Programme Checked 24/03/26
A12: 8183 | B12: Murney Custodian - 1 Freight Drive | C12: 1124.47 | D12: 609 | E12: 515.47 | M12: 160 | N12: 320 | O12: 80 | S12: Programme Checked 24/03/26
A14: 8886 | B14: Monkey Toe - Fisher fit out | C14: 501.83 | D14: 308.25 | E14: 193.58 | L14: 0 | M14: 80 | N14: 300 | S14: Programme Checked 24/03/26
A16: 8887 | B16: Tenancy 2 - Fisher Fit out | C16: 223.22 | D16: 113.25 | E16: 109.97 | M16: 16 | N16: 110
A18: 8670 | B18: Studio DB - tautara fit out | C18: 685.48 | D18: 561.5 | E18: 123.98 | M18: 240 | N18: 160
A20: 8907 | B20: 35 Mania | C20: 63.5 | D20: 48.25 | E20: 15.25 | M20: 36
A22: 9065 | B22: Cooltranz stage 4 | C22: 193.32 | D22: 2.75 | E22: 190.57 | M22: 20 | N22: 80 | O22: 60
A24: 9259 | B24: Andrew Reeve Stage 2 | C24: 472.14 | D24: 144.25 | E24: 327.89 | M24: 188 | N24: 282
A26: 8352 | B26: 5 Sanscrit Place | C26: 139.07 | D26: 147.75 | E26: -8.68 | M26: 48
A28: 8234 | B28: Melhuish House | C28: 231.75 | D28: 225.5 | E28: 6.25 | M28: 32
A30: 8214 | B30: 6 Tiroroa Lane | C30: 147.9 | D30: 5 | E30: 142.9 | N30: 48 | O30: 16 | P30: 64
A32: 6792 | B32: Major Hornbrook | C32: 208.2 | D32: 324.25 | E32: -116.05
A34: 8840 | B34: Inline Architecture | C34: 324.19 | D34: 472.75 | E34: -148.56 | M34: 130
A36: 8769 | B36: Percival Bach | C36: 84.05 | D36: 0 | E36: 84.05 | M36: 30 | N36: 50
A38: 7901 | B38: St Albans Street | C38: 317.92 | D38: 106 | E38: 211.92 | M38: 80 | N38: 40 | O38: 160
A40: 8923 | B40: 4 Perry St | C40: 156.69 | D40: 11.5 | E40: 145.19 | F40: 60 | G40: 15 | H40: 90
A42: 7864 | B42: Ryans House | C42: 200.82 | D42: 283.75 | E42: -82.93
A44: 7912 | B44: 71A Fendalton Road | C44: 497.55 | D44: 58.25 | E44: 439.3 | F44: 80 | N44: 40 | O44: 300 | P44: 150 | Q44: 150
A46: 8360 | B46: Dixon House | C46: 210.6 | D46: 260.75 | E46: -50.15
A48: 8337 | B48: Waimak Dairys | C48: 110.44 | D48: 60.75 | E48: 49.69 | M48: 16 | N48: 32
A50: 9240 | B50: Daves Twizel Shack | C50: 65.13 | D50: 24.33 | E50: 40.8 | M50: 16 | N50: 40
A52: 7428 | B52: FAB Pegasus Lakeside | C52: 659.73 | D52: 548.75 | E52: 110.98 | M52: 80 | N52: 80 | O52: 180
A54: 9351 | B54: Harewood Golf Club | C54: 125.17 | D54: 23.75 | E54: 101.42 | L54: 16 | M54: 32 | N54: 65
A56: 7429 | B56: Taggart House | C56: 130.62 | D56: 34.75 | E56: 95.87 | M56: 16 | N56: 70
A58: 9508 | B58: St Barnabas Church | C58: 140.15 | D58: 5.75 | E58: 134.4 | O58: 52 | P58: 13 | Q58: 69
B62: Contracting
A64: 8946 | B64: Westcoast Vaults | C64: 358.86 | D64: 0 | E64: 358.86 | N64: 143 | P64: 215
A66: 8308 | B66: Roydvale | C66: 2344.68 | D66: 1401.92 | E66: 942.76 | M66: 320 | N66: 250 | O66: 250 | P66: 240 | Q66: 80
A67: ='Main Sheet'!A68 | B67: ='Main Sheet'!B68 | C67: =LOOKUP(2,1/('Deliverables Sheet'!S229:S233<>0),'Deliverables Sheet'!S229:S233) | D67: =LOOKUP(2,1/('Deliverables Sheet'!T229:T233<>0),'Deliverables Sheet'!T229:T233) | E67: =LOOKUP(2,1/('Deliverables Sheet'!U229:U233<>0),'Deliverables Sheet'!U229:U233)
B71: Total Hours | F71: 640 | G71: 715 | H71: 790 | I71: 700 | J71: 700 | K71: 700 | L71: 716 | M71: 2520 | N71: 3060 | O71: 1316 | P71: 914 | Q71: 650
B72: Residential Hours | F72: 140 | G72: 15 | H72: 90 | L72: 16 | M72: 800 | N72: 858 | O72: 476 | P72: 214 | Q72: 150
B73: Commercial Hours | C73: 4490.26 | M73: 1020 | N73: 1502 | O73: 140
B74: Hours Available | F74: 1488 | G74: 2112 | H74: 1984 | I74: 1884.8 | J74: 1948.8 | K74: 2083.2 | L74: 2604.8 | M74: 2486.4 | N74: 2604.8 | O74: 2217.6 | P74: 2112 | Q74: 1478.4
B75: Balance Hours | F75: -848 | G75: -1397 | H75: -1194 | I75: -1184.8 | J75: -1248.8 | K75: -1383.2 | L75: -1888.8 | M75: 33.6 | N75: 455.2 | O75: -901.6 | P75: -1198 | Q75: -828.4
B77: Working Days In Month | C77: Check Staff Numbers | F77: 15 | G77: 20 | H77: 20 | I77: 19 | J77: 21 | K77: 21 | L77: 22 | M77: 21 | N77: 22 | O77: 21 | P77: 20 | Q77: 14
B78: No - Staff On Tools | F78: 15.5 | G78: 16.5 | H78: 15.5 | I78: 15.5 | J78: 14.5 | K78: 15.5 | L78: 18.5 | M78: 18.5 | N78: 18.5 | O78: 16.5 | P78: 16.5 | Q78: 16.5
B80: Staff | L80: 2 x PPLguys here for July and August
B81: Turbo | C81: 1
B82: Sean | C82: 1
B83: Jacob | C83: 1
B84: Hayden | C84: 1
B85: Doug | C85: 1
B86: Kyle | C86: 0.5
B87: Jack | C87: 1
B88: Andy | C88: 1
B89: Ben Ruffles | C89: 1
B90: Ben Dyer | C90: 0
B91: Jake | C91: 1
C92: 0
C93: 0
C94: 0
C95: 0
C96: 0
C97: 0
C98: 0
B99: Ethan | C99: 1
B100: Rhod | C100: 1
B101: George | C101: 1
B102: Jasper | C102: 1
B103: Logan | C103: 1
B104: Quin | C104: 1
B105: Regan | C105: 1
B110: Total Staff (enter in above spreadsheet) | C110: 16.5

Sheet Note Cam (To Do)
A2: Cams Notes
A3: Koawa:
A4: New job meeting set up for 8am wednesday - Tim, Dylan, VD, Cam - Perhaps bring in Jacob once back from leave??
A5: Tray shop drawings into engineers - waiting on geoff to send back multidraw drawings.
A6: DB dates for sites (livening 11 July)
A7: Confirm Warrenties agreement
A8: Go to tech submissions meeting on Wednesday 12th March
A9: Start getting orders in, (so far PDL gear ordered through rads) need to look at lights beign ordered that we can - confirm process.
A12: Tru Hire:
A13: Temp should be on Monday morning 14.04.25
A14: Craig would like an export/list for me please mate that captures all of the costs to date from you guys and ILS?
A15: Riccarton High:
... A50: Comes up with hours tracking solution

Sheet Note Tom (To Do) 
A2: Tom's Notes:
A38: Other:
A39: Comes up with hours tracking solution

Sheet Deliverables_RR_Test_Sheet (2)
A1: Updated Job Spreadsheet
A2: Job Number | B2: Job Name | C2: Week | D2: Quoted Price | E2: Claim to date | F2: Remaining to claim | G2: % Claim remaining | H2: Total quoted cost | I2: Total actual cost | J2: Quoted material cost | K2: Actual material cost | L2: Material cost remaining | M2: Material % remaining | N2: Estimated % of materials recieved | O2: Contractor Quoted Cost | P2: Contractor Actual Cost | Q2: Contractor Balance | R2: Quoted labour cost | S2: Actual labour cost | T2: Labour cost remaining | U2: Labour cost % remaining | V2: Quoted labour hours | W2: Actual labour hours | X2: Labour hours remaining | Y2: Labour hour % remaining | Z2: Estimated % of job complete | AA2: GP $ Per Hour | AB2: Quoted GP $ Per Hour | AC2: Margin to date | AD2: Quoted margin
AK3: Hours calcs | AL3: Materials calcs
A4: ='Main Sheet'!A4 -> 7658 | B4: ='Main Sheet'!B4 -> Charity Hospital | C4: Start of month | D4: 1914143.5 | E4: 1667392.4 | F4: =D4-E4 -> 246751.12 | G4: =F4/D4 -> 0.12890941 | H4: 1675578 | I4: 1406264.8 | J4: =SUM(H4-(R4+O4)) -> 1511021.4 | K4: =SUM(I4-(S4+P4)) -> 1215391.4 | L4: =J4-K4 -> 295630 | M4: =L4/J4 -> 0.19564911 | O4: 5 | P4: 4 | Q4: =O4-P4 -> 1 | R4: 164551.54 | S4: 190869.33 | T4: =R4-S4 -> -26317.79 | U4: =T4/R4 -> -0.15993646 | V4: 3296.1 | W4: 4599 | X4: =V4-W4 -> -1302.9 | Y4: =X4/V4 -> -0.39528534 | AA4: =(E4-K4-S4)/W4 -> 56.780087 | AB4: =(D4-J4-R4)/V4 -> 72.37964 | AC4: =(E4-K4-S4)/E4 -> 0.15661078 | AD4: =SUM(D4-H4)/D4 -> 0.12463304 | AG4: Hours calc for monthly claims | AH4: =AK9 -> -4599 | AK4: =SUM(W5-W4) -> 415.49 | AL4: =SUM(K5-K4) -> 48650.89
C5: Week 1 | D5: 1922479.9 | E5: 1667392.4 | F5: =D5-E5 -> 255087.52 | G5: =F5/D5 -> 0.1326867 | H5: 1681960.6 | I5: 1474477.1 | J5: =SUM(H5-R5) -> 1516687.4 | K5: =SUM(I5-S5) -> 1264042.3 | L5: =J5-K5 -> 252645.09 | M5: =L5/J5 -> 0.1665769 | R5: 165273.18 | S5: 210434.8 | T5: =R5-S5 -> -45161.62 | U5: =T5/R5 -> -0.27325438 | V5: 3312.1 | W5: 5014.49 | X5: =V5-W5 -> -1702.39 | Y5: =X5/V5 -> -0.51399112 | AA5: =(E5-K5-S5)/W5 -> 38.471561 | AB5: =(D5-J5-R5)/V5 -> 72.618372 | AC5: =(E5-K5-S5)/E5 -> 0.11569878 | AD5: =SUM(D5-H5)/D5 -> 0.12510888 | AG5: Materials calc for monthly claims | AH5: =AL9 -> -1215391.4 | AK5: =SUM(W6-W5) -> 134.5 | AL5: =SUM(K6-K5) -> 24752.67
C6: Week 2 | D6: 1922479.9 | E6: 1667392.4 | F6: =D6-E6 -> 255087.52 | G6: =F6/D6 -> 0.1326867 | H6: 1681960.6 | I6: 1505572.2 | J6: =SUM(H6-R6) -> 1516687.4 | K6: =SUM(I6-S6) -> 1288795 | L6: =J6-K6 -> 227892.42 | M6: =L6/J6 -> 0.15025668 | N6: 0.9 | R6: 165273.18 | S6: 216777.2 | T6: =R6-S6 -> -51504.02 | U6: =T6/R6 -> -0.31162963 | V6: 3312.1 | W6: 5148.99 | X6: =V6-W6 -> -1836.89 | Y6: =X6/V6 -> -0.5545998 | Z6: 0.9 | AA6: =(E6-K6-S6)/W6 -> 31.42756 | AB6: =(D6-J6-R6)/V6 -> 72.618372 | AC6: =(E6-K6-S6)/E6 -> 0.097049855 | AD6: =SUM(D6-H6)/D6 -> 0.12510888 | AK6: =SUM(W7-W6) -> -5148.99 | AL6: =SUM(K7-K6) -> -1288795
C7: Week 3 | F7: =D7-E7 -> 0 | G7: =F7/D7 -> #DIV/0! | J7: =SUM(H7-R7) -> 0 | K7: =SUM(I7-S7) -> 0 | L7: =J7-K7 -> 0 | M7: =L7/J7 -> #DIV/0! | T7: =R7-S7 -> 0 | U7: =T7/R7 -> #DIV/0! | X7: =V7-W7 -> 0 | Y7: =X7/V7 -> #DIV/0! | AA7: =(E7-K7-S7)/W7 -> #DIV/0! | AB7: =(D7-J7-R7)/V7 -> #DIV/0! | AC7: =(E7-K7-S7)/E7 -> #DIV/0! | AD7: =SUM(D7-H7)/D7 -> #DIV/0! | AG7: Estimated months claim | AH7: 0 | AK7: =SUM(W8-W7) -> 0 | AL7: =SUM(K8-K7) -> 0
C8: Week 4 | F8: =D8-E8 -> 0 | G8: =F8/D8 -> #DIV/0! | J8: =SUM(H8-R8) -> 0 | K8: =SUM(I8-S8) -> 0 | L8: =J8-K8 -> 0 | M8: =L8/J8 -> #DIV/0! | T8: =R8-S8 -> 0 | U8: =T8/R8 -> #DIV/0! | X8: =V8-W8 -> 0 | Y8: =X8/V8 -> #DIV/0! | AA8: =(E8-K8-S8)/W8 -> #DIV/0! | AB8: =(D8-J8-R8)/V8 -> #DIV/0! | AC8: =(E8-K8-S8)/E8 -> #DIV/0! | AD8: =SUM(D8-H8)/D8 -> #DIV/0! | AK8: =SUM(W9-W8) -> 0 | AL8: =SUM(K9-K8) -> 0
C9: Week 5 | F9: =D9-E9 -> 0 | G9: =F9/D9 -> #DIV/0! | J9: =SUM(H9-R9) -> 0 | K9: =SUM(I9-S9) -> 0 | L9: =J9-K9 -> 0 | M9: =L9/J9 -> #DIV/0! | T9: =R9-S9 -> 0 | U9: =T9/R9 -> #DIV/0! | X9: =V9-W9 -> 0 | Y9: =X9/V9 -> #DIV/0! | AA9: =(E9-K9-S9)/W9 -> #DIV/0! | AB9: =(D9-J9-R9)/V9 -> #DIV/0! | AC9: =(E9-K9-S9)/E9 -> #DIV/0! | AD9: =SUM(D9-H9)/D9 -> #DIV/0! | AK9: =SUM(AK4,AK5,AK6,AK7,AK8) -> -4599 | AL9: =SUM(AL4,AL5,AL6,AL7,AL8) -> -1215391.4
A11: ='Main Sheet'!A6 -> 8142 | B11: ='Main Sheet'!B6 -> Fisher Developements | C11: Start of month | D11: 381671.63 | E11: 144223.4 | F11: =D11-E11 -> 237448.23 | G11: =F11/D11 -> 0.62212701 | H11: 329257.09 | I11: 168819.17 | J11: =SUM(H11-R11) -> 288248.16 | K11: =SUM(I11-S11) -> 158648.53 | L11: =J11-K11 -> 129599.63 | M11: =L11/J11 -> 0.4496113 | R11: 41008.93 | S11: 10170.64 | T11: =R11-S11 -> 30838.29 | U11: =T11/R11 -> 0.75198963 | V11: 821.2 | W11: 241 | X11: =V11-W11 -> 580.2 | Y11: =X11/V11 -> 0.70652703 | AA11: =(E11-K11-S11)/W11 -> -102.05714 | AB11: =(D11-J11-R11)/V11 -> 63.826766 | AC11: =(E11-K11-S11)/E11 -> -0.17053939 | AD11: =SUM(D11-H11)/D11 -> 0.13732889 | AG11: Hours calc for monthly claims | AH11: =AK16 -> -241 | AK11: =SUM(W12-W11) -> 96.25 | AL11: =SUM(K12-K11) -> 30474.42
C12: Week 1 | D12: 382219.49 | E12: 240065.55 | F12: =D12-E12 -> 142153.94 | G12: =F12/D12 -> 0.37191704 | H12: 329585.81 | I12: 202828.2 | J12: =SUM(H12-R12) -> 288352.94 | K12: =SUM(I12-S12) -> 189122.95 | L12: =J12-K12 -> 99229.99 | M12: =L12/J12 -> 0.34412685 | R12: 41232.87 | S12: 13705.25 | T12: =R12-S12 -> 27527.62 | U12: =T12/R12 -> 0.66761348 | V12: 825.68 | W12: 337.25 | X12: =V12-W12 -> 488.43 | Y12: =X12/V12 -> 0.59154878 | AA12: =(E12-K12-S12)/W12 -> 110.41468 | AB12: =(D12-J12-R12)/V12 -> 63.745858 | AC12: =(E12-K12-S12)/E12 -> 0.15511326 | AD12: =SUM(D12-H12)/D12 -> 0.13770538 | AG12: Materials calc for monthly claims | AH12: =AL16 -> -158648.53 | AK12: =SUM(W13-W12) -> 101.75 | AL12: =SUM(K13-K12) -> 7119.32
C13: Week 2 | D13: 382219.49 | E13: 240065.55 | F13: =D13-E13 -> 142153.94 | G13: =F13/D13 -> 0.37191704 | H13: 329585.81 | I13: 213730.54 | J13: =SUM(H13-R13) -> 288352.94 | K13: =SUM(I13-S13) -> 196242.27 | L13: =J13-K13 -> 92110.67 | M13: =L13/J13 -> 0.31943725 | R13: 41232.87 | S13: 17488.27 | T13: =R13-S13 -> 23744.6 | U13: =T13/R13 -> 0.57586581 | V13: 825.68 | W13: 439 | X13: =V13-W13 -> 386.68 | Y13: =X13/V13 -> 0.46831702 | AA13: =(E13-K13-S13)/W13 -> 59.988633 | AB13: =(D13-J13-R13)/V13 -> 63.745858 | AC13: =(E13-K13-S13)/E13 -> 0.10969925 | AD13: =SUM(D13-H13)/D13 -> 0.13770538 | AK13: =SUM(W14-W13) -> -439 | AL13: =SUM(K14-K13) -> 23228
C14: Week 3 | D14: 383409.63 | E14: 240065.55 | F14: =D14-E14 -> 143344.08 | G14: =F14/D14 -> 0.37386667 | H14: 330537 | I14: 246817.11 | J14: 289155.03 | K14: 219470.27 | L14: =J14-K14 -> 69684.76 | M14: =L14/J14 -> 0.24099446 | N14: 0.75 | T14: =R14-S14 -> 0 | U14: =T14/R14 -> #DIV/0! | X14: =V14-W14 -> 0 | Y14: =X14/V14 -> #DIV/0! | AA14: =(E14-K14-S14)/W14 -> #DIV/0! | AB14: =(D16-J14-R14)/V14 -> #DIV/0! | AC14: =(E14-K14-S14)/E14 -> 0.085790235 | AD14: =SUM(D16-H14)/D16 -> 0.13790115 | AG14: Estimated months claim | AH14: 0 | AK14: =SUM(W15-W14) -> 0 | AL14: =SUM(K15-K14) -> -219470.27
C15: Week 4 | D15: 383409.63 | F15: =D15-E15 -> 383409.63 | G15: =F15/D15 -> 1 | J15: =SUM(H15-R15) -> 0 | K15: =SUM(I15-S15) -> 0 | L15: =J15-K15 -> 0 | M15: =L15/J15 -> #DIV/0! | T15: =R15-S15 -> 0 | U15: =T15/R15 -> #DIV/0! | X15: =V15-W15 -> 0 | Y15: =X15/V15 -> #DIV/0! | AA15: =(E15-K15-S15)/W15 -> #DIV/0! | AB15: =(D15-J15-R15)/V15 -> #DIV/0! | AC15: =(E15-K15-S15)/E15 -> #DIV/0! | AD15: =SUM(D15-H15)/D15 -> 1 | AK15: =SUM(W16-W15) -> 0 | AL15: =SUM(K16-K15) -> 0
C16: Week 5 | D16: 383409.63 | F16: =D16-E16 -> 383409.63 | G16: =F16/D16 -> 1 | J16: =SUM(H16-R16) -> 0 | K16: =SUM(I16-S16) -> 0 | L16: =J16-K16 -> 0 | M16: =L16/J16 -> #DIV/0! | N16: 0.55 | T16: =R16-S16 -> 0 | U16: =T16/R16 -> #DIV/0! | X16: =V16-W16 -> 0 | Y16: =X16/V16 -> #DIV/0! | Z16: 0.35 | AA16: =(E16-K16-S16)/W16 -> #DIV/0! | AB16: =(#REF!-J16-R16)/V16 -> #REF! | AC16: =(E16-K16-S16)/E16 -> #DIV/0! | AD16: =SUM(#REF!-H16)/#REF! -> #REF! | AK16: =SUM(AK11,AK12,AK13,AK14,AK15) -> -241 | AL16: =SUM(AL11,AL12,AL13,AL14,AL15) -> -158648.53
A18: 7104 | B18: ='Main Sheet'!B8 -> 3 Innovation Road | C18: Start of month | D18: 449818.08 | E18: 246538.95 | F18: =D18-E18 -> 203279.13 | G18: =F18/D18 -> 0.45191409 | H18: 329858.1 | I18: 251921.97 | J18: =SUM(H18-R18) -> 255282.19 | K18: =SUM(I18-S18) -> 219103.38 | L18: =J18-K18 -> 36178.81 | M18: =L18/J18 -> 0.14172085 | N18: 0 | R18: 74575.91 | S18: 32818.59 | T18: =R18-S18 -> 41757.32 | U18: =T18/R18 -> 0.55993041 | V18: 1493.36 | W18: 799.5 | X18: =V18-W18 -> 693.86 | Y18: =X18/V18 -> 0.4646301 | Z18: 0 | AA18: =(E18-K18-S18)/W18 -> -6.7329831 | AB18: =(D18-J18-R18)/V18 -> 80.328909 | AC18: =(E18-K18-S18)/E18 -> -0.021834359 | AD18: =SUM(D18-H18)/D18 -> 0.26668555 | AG18: Hours calc for monthly claims | AH18: =AK23 -> -799.5 | AK18: =SUM(W19-W18) -> 57.75 | AL18: =SUM(K19-K18) -> -918.26
C19: Week 1 | D19: 449818.08 | E19: 364039.73 | F19: =D19-E19 -> 85778.35 | G19: =F19/D19 -> 0.19069565 | H19: 329858.1 | I19: 253347.64 | J19: =SUM(H19-R19) -> 255282.19 | K19: =SUM(I19-S19) -> 218185.12 | L19: =J19-K19 -> 37097.07 | M19: =L19/J19 -> 0.14531789 | R19: 74575.91 | S19: 35162.52 | T19: =R19-S19 -> 39413.39 | U19: =T19/R19 -> 0.52850029 | V19: 1493.36 | W19: 857.25 | X19: =V19-W19 -> 636.11 | Y19: =X19/V19 -> 0.42595891 | Z19: 0.1 | AA19: =(E19-K19-S19)/W19 -> 129.12463 | AB19: =(D19-J19-R19)/V19 -> 80.328909 | AC19: =(E19-K19-S19)/E19 -> 0.30406596 | AD19: =SUM(D19-H19)/D19 -> 0.26668555 | AG19: Materials calc for monthly claims | AH19: =AL23 -> -219103.38 | AK19: =SUM(W20-W19) -> 93.75 | AL19: =SUM(K20-K19) -> 5813.69
C20: Week 2 | D20: 449818.08 | E20: 364039.73 | F20: =D20-E20 -> 85778.35 | G20: =F20/D20 -> 0.19069565 | H20: 329858.1 | I20: 262942.02 | J20: =SUM(H20-R20) -> 255282.19 | K20: =SUM(I20-S20) -> 223998.81 | L20: =J20-K20 -> 31283.38 | M20: =L20/J20 -> 0.12254431 | R20: 74575.91 | S20: 38943.21 | T20: =R20-S20 -> 35632.7 | U20: =T20/R20 -> 0.47780443 | V20: 1493.36 | W20: 951 | X20: =V20-W20 -> 542.36 | Y20: =X20/V20 -> 0.36318101 | Z20: 0.15 | AA20: =(E20-K20-S20)/W20 -> 106.30674 | AB20: =(D20-J20-R20)/V20 -> 80.328909 | AC20: =(E20-K20-S20)/E20 -> 0.27771065 | AD20: =SUM(D20-H20)/D20 -> 0.26668555 | AK20: =SUM(W21-W20) -> -951 | AL20: =SUM(K21-K20) -> -223998.81
C21: Week 3 | F21: =D21-E21 -> 0 | G21: =F21/D21 -> #DIV/0! | J21: =SUM(H21-R21) -> 0 | K21: =SUM(I21-S21) -> 0 | L21: =J21-K21 -> 0 | M21: =L21/J21 -> #DIV/0! | T21: =R21-S21 -> 0 | U21: =T21/R21 -> #DIV/0! | X21: =V21-W21 -> 0 | Y21: =X21/V21 -> #DIV/0! | Z21: 0.03 | AA21: =(E21-K21-S21)/W21 -> #DIV/0! | AB21: =(D21-J21-R21)/V21 -> #DIV/0! | AC21: =(E21-K21-S21)/E21 -> #DIV/0! | AD21: =SUM(D21-H21)/D21 -> #DIV/0! | AG21: Estimated months claim | AH21: 0 | AK21: =SUM(W22-W21) -> 0 | AL21: =SUM(K22-K21) -> 0
C22: Week 4 | F22: =D22-E22 -> 0 | G22: =F22/D22 -> #DIV/0! | J22: =SUM(H22-R22) -> 0 | K22: =SUM(I22-S22) -> 0 | L22: =J22-K22 -> 0 | M22: =L22/J22 -> #DIV/0! | T22: =R22-S22 -> 0 | U22: =T22/R22 -> #DIV/0! | X22: =V22-W22 -> 0 | Y22: =X22/V22 -> #DIV/0! | Z22: 0.03 | AA22: =(E22-K22-S22)/W22 -> #DIV/0! | AB22: =(D22-J22-R22)/V22 -> #DIV/0! | AC22: =(E22-K22-S22)/E22 -> #DIV/0! | AD22: =SUM(D22-H22)/D22 -> #DIV/0! | AK22: =SUM(W23-W22) -> 0 | AL22: =SUM(K23-K22) -> 0
C23: Week 5 | F23: =D23-E23 -> 0 | G23: =F23/D23 -> #DIV/0! | J23: =SUM(H23-R23) -> 0 | K23: =SUM(I23-S23) -> 0 | L23: =J23-K23 -> 0 | M23: =L23/J23 -> #DIV/0! | N23: 0.9 | T23: =R23-S23 -> 0 | U23: =T23/R23 -> #DIV/0! | X23: =V23-W23 -> 0 | Y23: =X23/V23 -> #DIV/0! | Z23: 0.65 | AA23: =(E23-K23-S23)/W23 -> #DIV/0! | AB23: =(D23-J23-R23)/V23 -> #DIV/0! | AC23: =(E23-K23-S23)/E23 -> #DIV/0! | AD23: =SUM(D23-H23)/D23 -> #DIV/0! | AK23: =SUM(AK18,AK19,AK20,AK21,AK22) -> -799.5 | AL23: =SUM(AL18,AL19,AL20,AL21,AL22) -> -219103.38
A25: ='Main Sheet'!A10 -> 8127 | B25: ='Main Sheet'!B10 -> Rolly Autowash | C25: Start of month | D25: 38856.96 | E25: 0 | F25: =D25-E25 -> 38856.96 | G25: =F25/D25 -> 1 | H25: 27050.88 | I25: 1129.12 | J25: =SUM(H25-R25) -> 16492.08 | K25: =SUM(I25-S25) -> 1129.12 | L25: =J25-K25 -> 15362.96 | M25: =L25/J25 -> 0.93153562 | N25: 0 | R25: 10558.8 | S25: 0 | T25: =R25-S25 -> 10558.8 | U25: =T25/R25 -> 1 | V25: 213 | W25: 0 | X25: =V25-W25 -> 213 | Y25: =X25/V25 -> 1 | Z25: 0 | AA25: =(E25-K25-S25)/W25 -> #DIV/0! | AB25: =(D25-J25-R25)/V25 -> 55.427606 | AC25: =(E25-K25-S25)/E25 -> #DIV/0! | AD25: =SUM(D25-H25)/D25 -> 0.30383437 | AG25: Hours calc for monthly claims | AH25: =AK30 -> 0 | AK25: =SUM(W26-W25) -> 9.25 | AL25: =SUM(K26-K25) -> 5779.58
C26: Week 1 | D26: 38856.96 | E26: 0 | F26: =D26-E26 -> 38856.96 | G26: =F26/D26 -> 1 | H26: 27050.88 | I26: 7293.59 | J26: =SUM(H26-R26) -> 16492.08 | K26: =SUM(I26-S26) -> 6908.7 | L26: =J26-K26 -> 9583.38 | M26: =L26/J26 -> 0.58108983 | N26: 0 | R26: 10558.8 | S26: 384.89 | T26: =R26-S26 -> 10173.91 | U26: =T26/R26 -> 0.96354794 | V26: 213.13 | W26: 9.25 | X26: =V26-W26 -> 203.88 | Y26: =X26/V26 -> 0.95659926 | Z26: 0 | AA26: =(E26-K26-S26)/W26 -> -788.49622 | AB26: =(D26-J26-R26)/V26 -> 55.393797 | AC26: =(E26-K26-S26)/E26 -> #DIV/0! | AD26: =SUM(D26-H26)/D26 -> 0.30383437 | AG26: Materials calc for monthly claims | AH26: =AL30 -> -1129.12 | AK26: =SUM(W27-W26) -> 101.75 | AL26: =SUM(K27-K26) -> 6796.13
C27: Week 2 | D27: 38856.96 | E27: 0 | F27: =D27-E27 -> 38856.96 | G27: =F27/D27 -> 1 | H27: 27050.88 | I27: 18431.21 | J27: =SUM(H27-R27) -> 16492.08 | K27: =SUM(I27-S27) -> 13704.83 | L27: =J27-K27 -> 2787.25 | M27: =L27/J27 -> 0.16900536 | N27: 0 | R27: 10558.8 | S27: 4726.38 | T27: =R27-S27 -> 5832.42 | U27: =T27/R27 -> 0.55237527 | V27: 213.13 | W27: 111 | X27: =V27-W27 -> 102.13 | Y27: =X27/V27 -> 0.4791911 | Z27: 0 | AA27: =(E27-K27-S27)/W27 -> -166.04694 | AB27: =(D27-J27-R27)/V27 -> 55.393797 | AC27: =(E27-K27-S27)/E27 -> #DIV/0! | AD27: =SUM(D27-H27)/D27 -> 0.30383437 | AK27: =SUM(W28-W27) -> -111 | AL27: =SUM(K28-K27) -> -13704.83
C28: Week 3 | E28: 0 | F28: =D28-E28 -> 0 | G28: =F28/D28 -> #DIV/0! | J28: =SUM(H28-R28) -> 0 | K28: =SUM(I28-S28) -> 0 | L28: =J28-K28 -> 0 | M28: =L28/J28 -> #DIV/0! | N28: 0 | S28: 0 | T28: =R28-S28 -> 0 | U28: =T28/R28 -> #DIV/0! | W28: 0 | X28: =V28-W28 -> 0 | Y28: =X28/V28 -> #DIV/0! | Z28: 0 | AA28: =(E28-K28-S28)/W28 -> #DIV/0! | AB28: =(D28-J28-R28)/V28 -> #DIV/0! | AC28: =(E28-K28-S28)/E28 -> #DIV/0! | AD28: =SUM(D28-H28)/D28 -> #DIV/0! | AG28: Estimated months claim | AH28: 0 | AK28: =SUM(W29-W28) -> 0 | AL28: =SUM(K29-K28) -> 0
C29: Week 4 | E29: 0 | F29: =D29-E29 -> 0 | G29: =F29/D29 -> #DIV/0! | J29: =SUM(H29-R29) -> 0 | K29: =SUM(I29-S29) -> 0 | L29: =J29-K29 -> 0 | M29: =L29/J29 -> #DIV/0! | N29: 0 | S29: 0 | T29: =R29-S29 -> 0 | U29: =T29/R29 -> #DIV/0! | W29: 0 | X29: =V29-W29 -> 0 | Y29: =X29/V29 -> #DIV/0! | Z29: 0 | AA29: =(E29-K29-S29)/W29 -> #DIV/0! | AB29: =(D29-J29-R29)/V29 -> #DIV/0! | AC29: =(E29-K29-S29)/E29 -> #DIV/0! | AD29: =SUM(D29-H29)/D29 -> #DIV/0! | AK29: =SUM(W30-W29) -> 0 | AL29: =SUM(K30-K29) -> 0
C30: Week 5 | E30: 0 | F30: =D30-E30 -> 0 | G30: =F30/D30 -> #DIV/0! | J30: =SUM(H30-R30) -> 0 | K30: =SUM(I30-S30) -> 0 | L30: =J30-K30 -> 0 | M30: =L30/J30 -> #DIV/0! | N30: 0 | S30: 0 | T30: =R30-S30 -> 0 | U30: =T30/R30 -> #DIV/0! | W30: 0 | X30: =V30-W30 -> 0 | Y30: =X30/V30 -> #DIV/0! | Z30: 0 | AA30: =(E30-K30-S30)/W30 -> #DIV/0! | AB30: =(D30-J30-R30)/V30 -> #DIV/0! | AC30: =(E30-K30-S30)/E30 -> #DIV/0! | AD30: =SUM(D30-H30)/D30 -> #DIV/0! | AK30: =SUM(AK25,AK26,AK27,AK28,AK29) -> 0 | AL30: =SUM(AL25,AL26,AL27,AL28,AL29) -> -1129.12
A32: ='Main Sheet'!A12 -> 8183 | B32: ='Main Sheet'!B12 -> Murney - 1 Freight Drive + 109 Iport | C32: Start of month | D32: 69191.71 | E32: 0 | F32: =D32-E32 -> 69191.71 | G32: =F32/D32 -> 1 | H32: 53243.87 | I32: 641.28 | J32: =SUM(H32-R32) -> 41588.94 | K32: =SUM(I32-S32) -> 171.84 | L32: =J32-K32 -> 41417.1 | M32: =L32/J32 -> 0.99586813 | R32: 11654.93 | S32: 469.44 | T32: =R32-S32 -> 11185.49 | U32: =T32/R32 -> 0.95972177 | V32: 233.59 | W32: 12.5 | X32: =V32-W32 -> 221.09 | Y32: =X32/V32 -> 0.94648744 | Z32: 0 | AA32: =(E32-K32-S32)/W32 -> -51.3024 | AB32: =(D32-J32-R32)/V32 -> 68.272786 | AC32: =(E32-K32-S32)/E32 -> #DIV/0! | AD32: =SUM(D32-H32)/D32 -> 0.23048773 | AG32: Hours calc for monthly claims | AH32: =AK37 -> -12.5 | AK32: =SUM(W33-W32) -> 4.5 | AL32: =SUM(K33-K32) -> 13.95
C33: Week 1 | D33: 69191.71 | E33: 1364.78 | F33: =D33-E33 -> 67826.93 | G33: =F33/D33 -> 0.98027538 | H33: 53243.87 | I33: 844.77 | J33: =SUM(H33-R33) -> 41588.94 | K33: =SUM(I33-S33) -> 185.79 | L33: =J33-K33 -> 41403.15 | M33: =L33/J33 -> 0.99553271 | R33: 11654.93 | S33: 658.98 | T33: =R33-S33 -> 10995.95 | U33: =T33/R33 -> 0.94345912 | V33: 233.59 | W33: 17 | X33: =V33-W33 -> 216.59 | Y33: =X33/V33 -> 0.92722291 | AA33: =(E33-K33-S33)/W33 -> 30.588824 | AB33: =(D33-J33-R33)/V33 -> 68.272786 | AC33: =(E33-K33-S33)/E33 -> 0.38102112 | AD33: =SUM(D33-H33)/D33 -> 0.23048773 | AG33: Materials calc for monthly claims | AH33: =AL37 -> -171.84 | AK33: =SUM(W34-W33) -> 3 | AL33: =SUM(K34-K33) -> 3907.37
C34: Week 2 | D34: 69191.71 | E34: 1364.78 | F34: =D34-E34 -> 67826.93 | G34: =F34/D34 -> 0.98027538 | H34: 53243.87 | I34: 4850.24 | J34: =SUM(H34-R34) -> 41588.94 | K34: =SUM(I34-S34) -> 4093.16 | L34: =J34-K34 -> 37495.78 | M34: =L34/J34 -> 0.90158056 | R34: 11654.93 | S34: 757.08 | T34: =R34-S34 -> 10897.85 | U34: =T34/R34 -> 0.93504208 | V34: 233.59 | W34: 20 | X34: =V34-W34 -> 213.59 | Y34: =X34/V34 -> 0.9143799 | AA34: =(E34-K34-S34)/W34 -> -174.273 | AB34: =(D34-J34-R34)/V34 -> 68.272786 | AC34: =(E34-K34-S34)/E34 -> -2.5538622 | AD34: =SUM(D34-H34)/D34 -> 0.23048773 | AK34: =SUM(W35-W34) -> -20 | AL34: =SUM(K35-K34) -> -4093.16
C35: Week 3 | F35: =D35-E35 -> 0 | G35: =F35/D35 -> #DIV/0! | J35: =SUM(H35-R35) -> 0 | K35: =SUM(I35-S35) -> 0 | L35: =J35-K35 -> 0 | M35: =L35/J35 -> #DIV/0! | T35: =R35-S35 -> 0 | U35: =T35/R35 -> #DIV/0! | X35: =V35-W35 -> 0 | Y35: =X35/V35 -> #DIV/0! | AA35: =(E35-K35-S35)/W35 -> #DIV/0! | AB35: =(D35-J35-R35)/V35 -> #DIV/0! | AC35: =(E35-K35-S35)/E35 -> #DIV/0! | AD35: =SUM(D35-H35)/D35 -> #DIV/0! | AG35: Estimated months claim | AH35: 0 | AK35: =SUM(W36-W35) -> 0 | AL35: =SUM(K36-K35) -> 0
C36: Week 4 | F36: =D36-E36 -> 0 | G36: =F36/D36 -> #DIV/0! | J36: =SUM(H36-R36) -> 0 | K36: =SUM(I36-S36) -> 0 | L36: =J36-K36 -> 0 | M36: =L36/J36 -> #DIV/0! | T36: =R36-S36 -> 0 | U36: =T36/R36 -> #DIV/0! | X36: =V36-W36 -> 0 | Y36: =X36/V36 -> #DIV/0! | AA36: =(E36-K36-S36)/W36 -> #DIV/0! | AB36: =(D36-J36-R36)/V36 -> #DIV/0! | AC36: =(E36-K36-S36)/E36 -> #DIV/0! | AD36: =SUM(D36-H36)/D36 -> #DIV/0! | AK36: =SUM(W37-W36) -> 0 | AL36: =SUM(K37-K36) -> 0
C37: Week 5 | F37: =D37-E37 -> 0 | G37: =F37/D37 -> #DIV/0! | J37: =SUM(H37-R37) -> 0 | K37: =SUM(I37-S37) -> 0 | L37: =J37-K37 -> 0 | M37: =L37/J37 -> #DIV/0! | T37: =R37-S37 -> 0 | U37: =T37/R37 -> #DIV/0! | X37: =V37-W37 -> 0 | Y37: =X37/V37 -> #DIV/0! | AA37: =(E37-K37-S37)/W37 -> #DIV/0! | AB37: =(D37-J37-R37)/V37 -> #DIV/0! | AC37: =(E37-K37-S37)/E37 -> #DIV/0! | AD37: =SUM(D37-H37)/D37 -> #DIV/0! | AK37: =SUM(AK32,AK33,AK34,AK35,AK36) -> -12.5 | AL37: =SUM(AL32,AL33,AL34,AL35,AL36) -> -171.84
A39: ='Main Sheet'!A14 -> 8886 | B39: ='Main Sheet'!B14 -> Monkey Toe - Fisher fit out | C39: Start of month | D39: 44956.29 | F39: =D39-E39 -> 44956.29 | G39: =F39/D39 -> 1 | H39: 30585.67 | I39: 0 | J39: =SUM(H39-R39) -> 19268.79 | K39: =SUM(I39-S39) -> 0 | L39: =J39-K39 -> 19268.79 | M39: =L39/J39 -> 1 | R39: 11316.88 | T39: =R39-S39 -> 11316.88 | U39: =T39/R39 -> 1 | V39: 234.28 | W39: 0 | X39: =V39-W39 -> 234.28 | Y39: =X39/V39 -> 1 | Z39: 0.8 | AA39: =(E39-K39-S39)/W39 -> #DIV/0! | AB39: =(D39-J39-R39)/V39 -> 61.339508 | AC39: =(E39-K39-S39)/E39 -> #DIV/0! | AD39: =SUM(D39-H39)/D39 -> 0.31965761 | AG39: Hours calc for monthly claims | AH39: =AK44 -> 0 | AK39: =SUM(W40-W39) -> 0 | AL39: =SUM(K40-K39) -> 0
C40: Week 1 | D40: 44956.29 | F40: =D40-E40 -> 44956.29 | G40: =F40/D40 -> 1 | H40: 30585.67 | J40: =SUM(H40-R40) -> 19268.79 | K40: =SUM(I40-S40) -> 0 | L40: =J40-K40 -> 19268.79 | M40: =L40/J40 -> 1 | R40: 11316.88 | T40: =R40-S40 -> 11316.88 | U40: =T40/R40 -> 1 | V40: 234.28 | W40: 0 | X40: =V40-W40 -> 234.28 | Y40: =X40/V40 -> 1 | Z40: 0.95 | AA40: =(E40-K40-S40)/W40 -> #DIV/0! | AB40: =(D40-J40-R40)/V40 -> 61.339508 | AC40: =(E40-K40-S40)/E40 -> #DIV/0! | AD40: =SUM(D40-H40)/D40 -> 0.31965761 | AG40: Materials calc for monthly claims | AH40: =AL44 -> 0 | AK40: =SUM(W41-W40) -> 2.5 | AL40: =SUM(K41-K40) -> 0
C41: Week 2 | D41: 44956.29 | F41: =D41-E41 -> 44956.29 | G41: =F41/D41 -> 1 | H41: 30585.67 | I41: 112.35 | J41: =SUM(H41-R41) -> 19268.79 | K41: =SUM(I41-S41) -> 0 | L41: =J41-K41 -> 19268.79 | M41: =L41/J41 -> 1 | R41: 11316.88 | S41: 112.35 | T41: =R41-S41 -> 11204.53 | U41: =T41/R41 -> 0.99007235 | V41: 234.28 | W41: 2.5 | X41: =V41-W41 -> 231.78 | Y41: =X41/V41 -> 0.98932901 | Z41: 0.98 | AA41: =(E41-K41-S41)/W41 -> -44.94 | AB41: =(D41-J41-R41)/V41 -> 61.339508 | AC41: =(E41-K41-S41)/E41 -> #DIV/0! | AD41: =SUM(D41-H41)/D41 -> 0.31965761 | AK41: =SUM(W42-W41) -> -2.5 | AL41: =SUM(K42-K41) -> 0
C42: Week 3 | F42: =D42-E42 -> 0 | G42: =F42/D42 -> #DIV/0! | J42: =SUM(H42-R42) -> 0 | K42: =SUM(I42-S42) -> 0 | L42: =J42-K42 -> 0 | M42: =L42/J42 -> #DIV/0! | T42: =R42-S42 -> 0 | U42: =T42/R42 -> #DIV/0! | W42: 0 | X42: =V42-W42 -> 0 | Y42: =X42/V41 -> 0 | Z42: 1 | AA42: =(E42-K42-S42)/W42 -> #DIV/0! | AB42: =(D42-J42-R42)/V41 -> 0 | AC42: =(E42-K42-S42)/E42 -> #DIV/0! | AD42: =SUM(D42-H42)/D42 -> #DIV/0! | AG42: Estimated months claim | AH42: 0 | AK42: =SUM(W43-W42) -> 0 | AL42: =SUM(K43-K42) -> 0
C43: Week 4 | F43: =D43-E43 -> 0 | G43: =F43/D43 -> #DIV/0! | J43: =SUM(H43-R43) -> 0 | K43: =SUM(I43-S43) -> 0 | L43: =J43-K43 -> 0 | M43: =L43/J43 -> #DIV/0! | T43: =R43-S43 -> 0 | U43: =T43/R43 -> #DIV/0! | W43: 0 | X43: =V43-W43 -> 0 | Y43: =X43/V43 -> #DIV/0! | Z43: 1 | AA43: =(E43-K43-S43)/W43 -> #DIV/0! | AB43: =(D43-J43-R43)/V43 -> #DIV/0! | AC43: =(E43-K43-S43)/E43 -> #DIV/0! | AD43: =SUM(D43-H43)/D43 -> #DIV/0! | AK43: =SUM(W44-W43) -> 0 | AL43: =SUM(K44-K43) -> 0
C44: Week 5 | F44: =D44-E44 -> 0 | G44: =F44/D44 -> #DIV/0! | J44: =SUM(H44-R44) -> 0 | K44: =SUM(I44-S44) -> 0 | L44: =J44-K44 -> 0 | M44: =L44/J44 -> #DIV/0! | T44: =R44-S44 -> 0 | U44: =T44/R44 -> #DIV/0! | W44: 0 | X44: =V44-W44 -> 0 | Y44: =X44/V44 -> #DIV/0! | Z44: 1 | AA44: =(E44-K44-S44)/W44 -> #DIV/0! | AB44: =(D44-J44-R44)/V44 -> #DIV/0! | AC44: =(E44-K44-S44)/E44 -> #DIV/0! | AD44: =SUM(D44-H44)/D44 -> #DIV/0! | AK44: =SUM(AK39,AK40,AK41,AK42,AK43) -> 0 | AL44: =SUM(AL39,AL40,AL41,AL42,AL43) -> 0
A46: ='Main Sheet'!A16 -> 8887 | B46: ='Main Sheet'!B16 -> Tenancy 2 - Fisher Fit out | C46: Start of month | D46: 7495.54 | E46: 0 | F46: =D46-E46 -> 7495.54 | G46: =F46/D46 -> 1 | H46: 5659.85 | I46: 0 | J46: =SUM(H46-R46) -> 3768.03 | K46: =SUM(I46-S46) -> 0 | L46: =J46-K46 -> 3768.03 | M46: =L46/J46 -> 1 | N46: 0 | R46: 1891.82 | S46: 0 | T46: =R46-S46 -> 1891.82 | U46: =T46/R46 -> 1 | V46: 37.84 | W46: 0 | X46: =V46-W46 -> 37.84 | Y46: =X46/V46 -> 1 | Z46: 0 | AA46: =(E46-K46-S46)/W46 -> #DIV/0! | AB46: =(D46-J46-R46)/V46 -> 48.511892 | AC46: =(E46-K46-S46)/E46 -> #DIV/0! | AD46: =SUM(D46-H46)/D46 -> 0.2449043 | AG46: Hours calc for monthly claims | AH46: =AK51 -> 0 | AK46: =SUM(W47-W46) -> 0 | AL46: =SUM(K47-K46) -> 0
C47: Week 1 | D47: 7495.54 | E47: 0 | F47: =D47-E47 -> 7495.54 | G47: =F47/D47 -> 1 | H47: 5659.85 | I47: 0 | J47: =SUM(H47-R47) -> 3768.03 | K47: =SUM(I47-S47) -> 0 | L47: =J47-K47 -> 3768.03 | M47: =L47/J47 -> 1 | N47: 0 | R47: 1891.82 | S47: 0 | T47: =R47-S47 -> 1891.82 | U47: =T47/R47 -> 1 | V47: 37.84 | W47: 0 | X47: =V47-W47 -> 37.84 | Y47: =X47/V47 -> 1 | Z47: 0 | AA47: =(E47-K47-S47)/W47 -> #DIV/0! | AB47: =(D47-J47-R47)/V47 -> 48.511892 | AC47: =(E47-K47-S47)/E47 -> #DIV/0! | AD47: =SUM(D47-H47)/D47 -> 0.2449043 | AG47: Materials calc for monthly claims | AH47: =AL51 -> 0 | AK47: =SUM(W48-W47) -> 0 | AL47: =SUM(K48-K47) -> 0
C48: Week 2 | D48: 7495.54 | E48: 0 | F48: =D48-E48 -> 7495.54 | G48: =F48/D48 -> 1 | H48: 5659.85 | I48: 0 | J48: =SUM(H48-R48) -> 3768.03 | K48: =SUM(I48-S48) -> 0 | L48: =J48-K48 -> 3768.03 | M48: =L48/J48 -> 1 | N48: 0 | R48: 1891.82 | S48: 0 | T48: =R48-S48 -> 1891.82 | U48: =T48/R48 -> 1 | V48: 37.84 | W48: 0 | X48: =V48-W48 -> 37.84 | Y48: =X48/V48 -> 1 | Z48: 0 | AA48: =(E48-K48-S48)/W48 -> #DIV/0! | AB48: =(D48-J48-R48)/V48 -> 48.511892 | AC48: =(E48-K48-S48)/E48 -> #DIV/0! | AD48: =SUM(D48-H48)/D48 -> 0.2449043 | AK48: =SUM(W49-W48) -> 0 | AL48: =SUM(K49-K48) -> 0
C49: Week 3 | E49: 0 | F49: =D49-E49 -> 0 | G49: =F49/D49 -> #DIV/0! | J49: =SUM(H49-R49) -> 0 | K49: =SUM(I49-S49) -> 0 | L49: =J49-K49 -> 0 | M49: =L49/J49 -> #DIV/0! | N49: 0 | S49: 0 | T49: =R49-S49 -> 0 | U49: =T49/R49 -> #DIV/0! | W49: 0 | X49: =V49-W49 -> 0 | Y49: =X49/V49 -> #DIV/0! | AA49: =(E49-K49-S49)/W49 -> #DIV/0! | AB49: =(D49-J49-R49)/V49 -> #DIV/0! | AC49: =(E49-K49-S49)/E49 -> #DIV/0! | AD49: =SUM(D49-H49)/D49 -> #DIV/0! | AG49: Estimated months claim | AH49: 0 | AK49: =SUM(W50-W49) -> 0 | AL49: =SUM(K50-K49) -> 0
C50: Week 4 | E50: 0 | F50: =D50-E50 -> 0 | G50: =F50/D50 -> #DIV/0! | J50: =SUM(H50-R50) -> 0 | K50: =SUM(I50-S50) -> 0 | L50: =J50-K50 -> 0 | M50: =L50/J50 -> #DIV/0! | N50: 0 | S50: 0 | T50: =R50-S50 -> 0 | U50: =T50/R50 -> #DIV/0! | W50: 0 | X50: =V50-W50 -> 0 | Y50: =X50/V50 -> #DIV/0! | AA50: =(E50-K50-S50)/W50 -> #DIV/0! | AB50: =(D50-J50-R50)/V50 -> #DIV/0! | AC50: =(E50-K50-S50)/E50 -> #DIV/0! | AD50: =SUM(D50-H50)/D50 -> #DIV/0! | AK50: =SUM(W51-W50) -> 0 | AL50: =SUM(K51-K50) -> 0
C51: Week 5 | E51: 0 | F51: =D51-E51 -> 0 | G51: =F51/D51 -> #DIV/0! | J51: =SUM(H51-R51) -> 0 | K51: =SUM(I51-S51) -> 0 | L51: =J51-K51 -> 0 | M51: =L51/J51 -> #DIV/0! | N51: 0 | S51: 0 | T51: =R51-S51 -> 0 | U51: =T51/R51 -> #DIV/0! | W51: 0 | X51: =V51-W51 -> 0 | Y51: =X51/V51 -> #DIV/0! | AA51: =(E51-K51-S51)/W51 -> #DIV/0! | AB51: =(D51-J51-R51)/V51 -> #DIV/0! | AC51: =(E51-K51-S51)/E51 -> #DIV/0! | AD51: =SUM(D51-H51)/D51 -> #DIV/0! | AK51: =SUM(AK46,AK47,AK48,AK49,AK50) -> 0 | AL51: =SUM(AL46,AL47,AL48,AL49,AL50) -> 0
A53: ='Main Sheet'!A18 -> 8670 | B53: ='Main Sheet'!B18 -> Studio DB - tautara fit out | C53: Start of month | D53: 100348.26 | E53: 91153 | F53: =D53-E53 -> 9195.26 | G53: =F53/D53 -> 0.091633477 | H53: 79103.46 | I53: 64224.89 | J53: =SUM(H53-R53) -> 62144.61 | K53: =SUM(I53-S53) -> 54357.06 | L53: =J53-K53 -> 7787.55 | M53: =L53/J53 -> 0.12531336 | N53: 0 | R53: 16958.85 | S53: 9867.83 | T53: =R53-S53 -> 7091.02 | U53: =T53/R53 -> 0.41813095 | V53: 340.12 | W53: 262 | X53: =V53-W53 -> 78.12 | Y53: =X53/V53 -> 0.22968364 | Z53: 0 | AA53: =(E53-K53-S53)/W53 -> 102.77905 | AB53: =(D53-J53-R53)/V53 -> 62.46266 | AC53: =(E53-K53-S53)/E53 -> 0.29541661 | AD53: =SUM(D53-H53)/D53 -> 0.2117107 | AG53: Hours calc for monthly claims | AH53: =AK58 -> -262 | AK53: =SUM(W54-W53) -> 10 | AL53: =SUM(K54-K53) -> 1582.92
C54: Week 1 | D54: 100348.26 | E54: 91153 | F54: =D54-E54 -> 9195.26 | G54: =F54/D54 -> 0.091633477 | H54: 79103.46 | I54: 66212.81 | J54: =SUM(H54-R54) -> 62144.61 | K54: =SUM(I54-S54) -> 55939.98 | L54: =J54-K54 -> 6204.63 | M54: =L54/J54 -> 0.099841804 | R54: 16958.85 | S54: 10272.83 | T54: =R54-S54 -> 6686.02 | U54: =T54/R54 -> 0.39424961 | V54: 340.12 | W54: 272 | X54: =V54-W54 -> 68.12 | Y54: =X54/V54 -> 0.20028225 | AA54: =(E54-K54-S54)/W54 -> 91.691875 | AB54: =(D54-J54-R54)/V54 -> 62.46266 | AC54: =(E54-K54-S54)/E54 -> 0.273608 | AD54: =SUM(D54-H54)/D54 -> 0.2117107 | AG54: Materials calc for monthly claims | AH54: =AL58 -> -54357.06 | AK54: =SUM(W55-W54) -> 44.25 | AL54: =SUM(K55-K54) -> 218.2
C55: Week 2 | D55: 100348.26 | E55: 91153 | F55: =D55-E55 -> 9195.26 | G55: =F55/D55 -> 0.091633477 | H55: 79103.46 | I55: 68039.14 | J55: =SUM(H55-R55) -> 62144.61 | K55: =SUM(I55-S55) -> 56158.18 | L55: =J55-K55 -> 5986.43 | M55: =L55/J55 -> 0.096330639 | R55: 16958.85 | S55: 11880.96 | T55: =R55-S55 -> 5077.89 | U55: =T55/R55 -> 0.29942419 | V55: 340.12 | W55: 316.25 | X55: =V55-W55 -> 23.87 | Y55: =X55/V55 -> 0.070181113 | AA55: =(E55-K55-S55)/W55 -> 73.087304 | AB55: =(D55-J55-R55)/V55 -> 62.46266 | AC55: =(E55-K55-S55)/E55 -> 0.25357213 | AD55: =SUM(D55-H55)/D55 -> 0.2117107 | AK55: =SUM(W56-W55) -> -316.25 | AL55: =SUM(K56-K55) -> -56158.18
C56: Week 3 | F56: =D56-E56 -> 0 | G56: =F56/D56 -> #DIV/0! | J56: =SUM(H56-R56) -> 0 | K56: =SUM(I56-S56) -> 0 | L56: =J56-K56 -> 0 | M56: =L56/J56 -> #DIV/0! | T56: =R56-S56 -> 0 | U56: =T56/R56 -> #DIV/0! | X56: =V56-W56 -> 0 | Y56: =X56/V56 -> #DIV/0! | AA56: =(E56-K56-S56)/W56 -> #DIV/0! | AB56: =(D56-J56-R56)/V56 -> #DIV/0! | AC56: =(E56-K56-S56)/E56 -> #DIV/0! | AD56: =SUM(D56-H56)/D56 -> #DIV/0! | AG56: Estimated months claim | AH56: 0 | AK56: =SUM(W57-W56) -> 0 | AL56: =SUM(K57-K56) -> 0
C57: Week 4 | F57: =D57-E57 -> 0 | G57: =F57/D57 -> #DIV/0! | J57: =SUM(H57-R57) -> 0 | K57: =SUM(I57-S57) -> 0 | L57: =J57-K57 -> 0 | M57: =L57/J57 -> #DIV/0! | T57: =R57-S57 -> 0 | U57: =T57/R57 -> #DIV/0! | X57: =V57-W57 -> 0 | Y57: =X57/V57 -> #DIV/0! | AA57: =(E57-K57-S57)/W57 -> #DIV/0! | AB57: =(D57-J57-R57)/V57 -> #DIV/0! | AC57: =(E57-K57-S57)/E57 -> #DIV/0! | AD57: =SUM(D57-H57)/D57 -> #DIV/0! | AK57: =SUM(W58-W57) -> 0 | AL57: =SUM(K58-K57) -> 0
C58: Week 5 | F58: =D58-E58 -> 0 | G58: =F58/D58 -> #DIV/0! | J58: =SUM(H58-R58) -> 0 | K58: =SUM(I58-S58) -> 0 | L58: =J58-K58 -> 0 | M58: =L58/J58 -> #DIV/0! | N58: 0.9 | T58: =R58-S58 -> 0 | U58: =T58/R58 -> #DIV/0! | X58: =V58-W58 -> 0 | Y58: =X58/V58 -> #DIV/0! | Z58: 0.9 | AA58: =(E58-K58-S58)/W58 -> #DIV/0! | AB58: =(D58-J58-R58)/V58 -> #DIV/0! | AC58: =(E58-K58-S58)/E58 -> #DIV/0! | AD58: =SUM(D58-H58)/D58 -> #DIV/0! | AK58: =SUM(AK53,AK54,AK55,AK56,AK57) -> -262 | AL58: =SUM(AL53,AL54,AL55,AL56,AL57) -> -54357.06
A60: ='Main Sheet'!A20 -> 8907 | B60: ='Main Sheet'!B20 -> 35 Mania | C60: Start of month | D60: 98524.85 | E60: 42682.56 | F60: =D60-E60 -> 55842.29 | G60: =F60/D60 -> 0.56678381 | H60: 82927.42 | I60: 59094.67 | J60: =SUM(H60-R60) -> 64755.29 | K60: =SUM(I60-S60) -> 50345.39 | L60: =J60-K60 -> 14409.9 | M60: =L60/J60 -> 0.22252854 | R60: 18172.13 | S60: 8749.28 | T60: =R60-S60 -> 9422.85 | U60: =T60/R60 -> 0.51853305 | V60: 363.99 | W60: 218.25 | X60: =V60-W60 -> 145.74 | Y60: =X60/V60 -> 0.40039562 | Z60: 0 | AA60: =(E60-K60-S60)/W60 -> -75.198671 | AB60: =(D60-J60-R60)/V60 -> 42.85126 | AC60: =(E60-K60-S60)/E60 -> -0.3845156 | AD60: =SUM(D60-H60)/D60 -> 0.1583096 | AG60: Hours calc for monthly claims | AH60: =AK65 -> -218.25 | AK60: =SUM(W61-W60) -> 163.25 | AL60: =SUM(K61-K60) -> 7441.38
C61: Week 1 | D61: 98524.85 | E61: 93329.71 | F61: =D61-E61 -> 5195.14 | G61: =F61/D61 -> 0.052729235 | H61: 82927.42 | I61: 73161.13 | J61: =SUM(H61-R61) -> 64755.29 | K61: =SUM(I61-S61) -> 57786.77 | L61: =J61-K61 -> 6968.52 | M61: =L61/J61 -> 0.10761314 | R61: 18172.13 | S61: 15374.36 | T61: =R61-S61 -> 2797.77 | U61: =T61/R61 -> 0.15395939 | V61: 363.99 | W61: 381.5 | X61: =V61-W61 -> -17.51 | Y61: =X61/V61 -> -0.048105717 | Z61: 0.2 | AA61: =(E61-K61-S61)/W61 -> 52.866527 | AB61: =(D61-J61-R61)/V61 -> 42.85126 | AC61: =(E61-K61-S61)/E61 -> 0.21610032 | AD61: =SUM(D61-H61)/D61 -> 0.1583096 | AG61: Materials calc for monthly claims | AH61: =AL65 -> -50345.39 | AK61: =SUM(W62-W61) -> 2 | AL61: =SUM(K62-K61) -> 728.1
C62: Week 2 | D62: 98524.85 | E62: 93329.71 | F62: =D62-E62 -> 5195.14 | G62: =F62/D62 -> 0.052729235 | H62: 82927.42 | I62: 73980.77 | J62: =SUM(H62-R62) -> 64755.29 | K62: =SUM(I62-S62) -> 58514.87 | L62: =J62-K62 -> 6240.42 | M62: =L62/J62 -> 0.09636927 | R62: 18172.13 | S62: 15465.9 | T62: =R62-S62 -> 2706.23 | U62: =T62/R62 -> 0.148922 | V62: 363.99 | W62: 383.5 | X62: =V62-W62 -> -19.51 | Y62: =X62/V62 -> -0.053600374 | Z62: 0.25 | AA62: =(E62-K62-S62)/W62 -> 50.453559 | AB62: =(D62-J62-R62)/V62 -> 42.85126 | AC62: =(E62-K62-S62)/E62 -> 0.20731812 | AD62: =SUM(D62-H62)/D62 -> 0.1583096 | AK62: =SUM(W63-W62) -> -383.5 | AL62: =SUM(K63-K62) -> -58514.87
C63: Week 3 | F63: =D63-E63 -> 0 | G63: =F63/D63 -> #DIV/0! | J63: =SUM(H63-R63) -> 0 | K63: =SUM(I63-S63) -> 0 | L63: =J63-K63 -> 0 | M63: =L63/J63 -> #DIV/0! | N63: 0.05 | T63: =R63-S63 -> 0 | U63: =T63/R63 -> #DIV/0! | X63: =V63-W63 -> 0 | Y63: =X63/V63 -> #DIV/0! | Z63: 0.02 | AA63: =(E63-K63-S63)/W63 -> #DIV/0! | AB63: =(D63-J63-R63)/V63 -> #DIV/0! | AC63: =(E63-K63-S63)/E63 -> #DIV/0! | AD63: =SUM(D63-H63)/D63 -> #DIV/0! | AG63: Estimated months claim | AH63: 0 | AK63: =SUM(W64-W63) -> 0 | AL63: =SUM(K64-K63) -> 0
C64: Week 4 | F64: =D64-E64 -> 0 | G64: =F64/D64 -> #DIV/0! | J64: =SUM(H64-R64) -> 0 | K64: =SUM(I64-S64) -> 0 | L64: =J64-K64 -> 0 | M64: =L64/J64 -> #DIV/0! | N64: 0.25 | T64: =R64-S64 -> 0 | U64: =T64/R64 -> #DIV/0! | X64: =V64-W64 -> 0 | Y64: =X64/V64 -> #DIV/0! | Z64: 0.1 | AA64: =(E64-K64-S64)/W64 -> #DIV/0! | AB64: =(D64-J64-R64)/V64 -> #DIV/0! | AC64: =(E64-K64-S64)/E64 -> #DIV/0! | AD64: =SUM(D64-H64)/D64 -> #DIV/0! | AK64: =SUM(W65-W64) -> 0 | AL64: =SUM(K65-K64) -> 0
C65: Week 5 | F65: =D65-E65 -> 0 | G65: =F65/D65 -> #DIV/0! | J65: =SUM(H65-R65) -> 0 | K65: =SUM(I65-S65) -> 0 | L65: =J65-K65 -> 0 | M65: =L65/J65 -> #DIV/0! | N65: 0.95 | T65: =R65-S65 -> 0 | U65: =T65/R65 -> #DIV/0! | X65: =V65-W65 -> 0 | Y65: =X65/V65 -> #DIV/0! | Z65: 0.1 | AA65: =(E65-K65-S65)/W65 -> #DIV/0! | AB65: =(D65-J65-R65)/V65 -> #DIV/0! | AC65: =(E65-K65-S65)/E65 -> #DIV/0! | AD65: =SUM(D65-H65)/D65 -> #DIV/0! | AK65: =SUM(AK60,AK61,AK62,AK63,AK64) -> -218.25 | AL65: =SUM(AL60,AL61,AL62,AL63,AL64) -> -50345.39
A67: ='Main Sheet'!A22 -> 9065 | B67: ='Main Sheet'!B22 -> Cooltranz stage 4 | C67: Start of month | D67: 87970.61 | E67: 48945.78 | F67: =D67-E67 -> 39024.83 | G67: =F67/D67 -> 0.44361213 | H67: 68471.73 | I67: 49900.98 | J67: =SUM(H67-R67) -> 52300.56 | K67: =SUM(I67-S67) -> 37733.03 | L67: =J67-K67 -> 14567.53 | M67: =L67/J67 -> 0.27853488 | R67: 16171.17 | S67: 12167.95 | T67: =R67-S67 -> 4003.22 | U67: =T67/R67 -> 0.2475529 | V67: 323.99 | W67: 350 | X67: =V67-W67 -> -26.01 | Y67: =X67/V67 -> -0.080280256 | AA67: =(E67-K67-S67)/W67 -> -2.7291429 | AB67: =(D67-J67-R67)/V67 -> 60.183586 | AC67: =(E67-K67-S67)/E67 -> -0.019515472 | AD67: =SUM(D67-H67)/D67 -> 0.22165221 | AG67: Hours calc for monthly claims | AH67: =AK72 -> -350 | AK67: =SUM(W68-W67) -> -39.5 | AL67: =SUM(K68-K67) -> 321.16
C68: Week 1 | D68: 87970.61 | E68: 85555.47 | F68: =D68-E68 -> 2415.14 | G68: =F68/D68 -> 0.027453942 | H68: 68471.73 | I68: 50194.4 | J68: =SUM(H68-R68) -> 52300.56 | K68: =SUM(I68-S68) -> 38054.19 | L68: =J68-K68 -> 14246.37 | M68: =L68/J68 -> 0.27239422 | R68: 16171.17 | S68: 12140.21 | T68: =R68-S68 -> 4030.96 | U68: =T68/R68 -> 0.2492683 | V68: 323.99 | W68: 310.5 | X68: =V68-W68 -> 13.49 | Y68: =X68/V68 -> 0.041637088 | Z68: 0.3 | AA68: =(E68-K68-S68)/W68 -> 113.88428 | AB68: =(D68-J68-R68)/V68 -> 60.183586 | AC68: =(E68-K68-S68)/E68 -> 0.41331162 | AD68: =SUM(D68-H68)/D68 -> 0.22165221 | AG68: Materials calc for monthly claims | AH68: =AL72 -> -37733.03 | AK68: =SUM(W69-W68) -> -310.5 | AL68: =SUM(K69-K68) -> -38054.19
C69: Week 2 | F69: =D69-E69 -> 0 | G69: =F69/D69 -> #DIV/0! | J69: =SUM(H69-R69) -> 0 | K69: =SUM(I69-S69) -> 0 | L69: =J69-K69 -> 0 | M69: =L69/J69 -> #DIV/0! | T69: =R69-S69 -> 0 | U69: =T69/R69 -> #DIV/0! | X69: =V69-W69 -> 0 | Y69: =X69/V69 -> #DIV/0! | Z69: 0.3 | AA69: =(E69-K69-S69)/W69 -> #DIV/0! | AB69: =(D69-J69-R69)/V69 -> #DIV/0! | AC69: =(E69-K69-S69)/E69 -> #DIV/0! | AD69: =SUM(D69-H69)/D69 -> #DIV/0! | AK69: =SUM(W70-W69) -> 0 | AL69: =SUM(K70-K69) -> 0
C70: Week 3 | F70: =D70-E70 -> 0 | G70: =F70/D70 -> #DIV/0! | J70: =SUM(H70-R70) -> 0 | K70: =SUM(I70-S70) -> 0 | L70: =J70-K70 -> 0 | M70: =L70/J70 -> #DIV/0! | T70: =R70-S70 -> 0 | U70: =T70/R70 -> #DIV/0! | X70: =V70-W70 -> 0 | Y70: =X70/V70 -> #DIV/0! | Z70: 0.1 | AA70: =(E70-K70-S70)/W70 -> #DIV/0! | AB70: =(D70-J70-R70)/V70 -> #DIV/0! | AC70: =(E70-K70-S70)/E70 -> #DIV/0! | AD70: =SUM(D70-H70)/D70 -> #DIV/0! | AG70: Estimated months claim | AH70: 0 | AK70: =SUM(W71-W70) -> 0 | AL70: =SUM(K71-K70) -> 0
C71: Week 4 | F71: =D71-E71 -> 0 | G71: =F71/D71 -> #DIV/0! | J71: =SUM(H71-R71) -> 0 | K71: =SUM(I71-S71) -> 0 | L71: =J71-K71 -> 0 | M71: =L71/J71 -> #DIV/0! | T71: =R71-S71 -> 0 | U71: =T71/R71 -> #DIV/0! | X71: =V71-W71 -> 0 | Y71: =X71/V71 -> #DIV/0! | Z71: 0.1 | AA71: =(E71-K71-S71)/W71 -> #DIV/0! | AB71: =(D71-J71-R71)/V71 -> #DIV/0! | AC71: =(E71-K71-S71)/E71 -> #DIV/0! | AD71: =SUM(D71-H71)/D71 -> #DIV/0! | AK71: =SUM(W72-W71) -> 0 | AL71: =SUM(K72-K71) -> 0
C72: Week 5 | F72: =D72-E72 -> 0 | G72: =F72/D72 -> #DIV/0! | J72: =SUM(H72-R72) -> 0 | K72: =SUM(I72-S72) -> 0 | L72: =J72-K72 -> 0 | M72: =L72/J72 -> #DIV/0! | T72: =R72-S72 -> 0 | U72: =T72/R72 -> #DIV/0! | X72: =V72-W72 -> 0 | Y72: =X72/V72 -> #DIV/0! | AA72: =(E72-K72-S72)/W72 -> #DIV/0! | AB72: =(D72-J72-R72)/V72 -> #DIV/0! | AC72: =(E72-K72-S72)/E72 -> #DIV/0! | AD72: =SUM(D72-H72)/D72 -> #DIV/0! | AK72: =SUM(AK67,AK68,AK69,AK70,AK71) -> -350 | AL72: =SUM(AL67,AL68,AL69,AL70,AL71) -> -37733.03
A74: ='Main Sheet'!A24 -> 9259 | B74: ='Main Sheet'!B24 -> Andrew Reeve Stage 2 | C74: Start of month | D74: 210242.4 | E74: 14860.85 | F74: =D74-E74 -> 195381.55 | G74: =F74/D74 -> 0.92931564 | H74: 188013.59 | I74: 33639.16 | J74: =SUM(H74-R74) -> 167291.62 | K74: =SUM(I74-S74) -> 33639.16 | L74: =J74-K74 -> 133652.46 | M74: =L74/J74 -> 0.79891904 | N74: 0 | R74: 20721.97 | S74: 0 | T74: =R74-S74 -> 20721.97 | U74: =T74/R74 -> 1 | V74: 416.73 | W74: 0 | X74: =V74-W74 -> 416.73 | Y74: =X74/V74 -> 1 | Z74: 0 | AA74: =(E74-K74-S74)/W74 -> #DIV/0! | AB74: =(D74-J74-R74)/V74 -> 53.341036 | AC74: =(E74-K74-S74)/E74 -> -1.2636094 | AD74: =SUM(D74-H74)/D74 -> 0.10572943 | AG74: Hours calc for monthly claims | AH74: =AK79 -> 0 | AK74: =SUM(W75-W74) -> 0 | AL74: =SUM(K75-K74) -> 16474.45
C75: Week 1 | D75: 210242.4 | E75: 67511.23 | F75: =D75-E75 -> 142731.17 | G75: =F75/D75 -> 0.67888861 | H75: 188013.59 | I75: 50113.61 | J75: =SUM(H75-R75) -> 167291.62 | K75: =SUM(I75-S75) -> 50113.61 | L75: =J75-K75 -> 117178.01 | M75: =L75/J75 -> 0.7004416 | N75: 0 | R75: 20721.97 | T75: =R75-S75 -> 20721.97 | U75: =T75/R75 -> 1 | V75: 416.73 | W75: 0 | X75: =V75-W75 -> 416.73 | Y75: =X75/V75 -> 1 | Z75: 0 | AA75: =(E75-K75-S75)/W75 -> #DIV/0! | AB75: =(D75-J75-R75)/V75 -> 53.341036 | AC75: =(E75-K75-S75)/E75 -> 0.25769964 | AD75: =SUM(D75-H75)/D75 -> 0.10572943 | AG75: Materials calc for monthly claims | AH75: =AL79 -> -33639.16 | AK75: =SUM(W76-W75) -> 0 | AL75: =SUM(K76-K75) -> 1067.7
C76: Week 2 | D76: 210242.4 | E76: 67511.23 | F76: =D76-E76 -> 142731.17 | G76: =F76/D76 -> 0.67888861 | H76: 188013.59 | I76: 51181.31 | J76: =SUM(H76-R76) -> 167216.61 | K76: =SUM(I76-S76) -> 51181.31 | L76: =J76-K76 -> 116035.3 | M76: =L76/J76 -> 0.69392209 | N76: 0 | R76: 20796.98 | T76: =R76-S76 -> 20796.98 | U76: =T76/R76 -> 1 | V76: 416.73 | W76: 0 | X76: =V76-W76 -> 416.73 | Y76: =X76/V76 -> 1 | Z76: 0 | AA76: =(E76-K76-S76)/W76 -> #DIV/0! | AB76: =(D76-J76-R76)/V76 -> 53.341036 | AC76: =(E76-K76-S76)/E76 -> 0.2418845 | AD76: =SUM(D76-H76)/D76 -> 0.10572943 | AK76: =SUM(W77-W76) -> 0 | AL76: =SUM(K77-K76) -> -51181.31
C77: Week 3 | F77: =D77-E77 -> 0 | G77: =F77/D77 -> #DIV/0! | J77: =SUM(H77-R77) -> 0 | K77: =SUM(I77-S77) -> 0 | L77: =J77-K77 -> 0 | M77: =L77/J77 -> #DIV/0! | N77: 0 | T77: =R77-S77 -> 0 | U77: =T77/R77 -> #DIV/0! | W77: 0 | X77: =V77-W77 -> 0 | Y77: =X77/V77 -> #DIV/0! | Z77: 0 | AA77: =(E77-K77-S77)/W77 -> #DIV/0! | AB77: =(D77-J77-R77)/V77 -> #DIV/0! | AC77: =(E77-K77-S77)/E77 -> #DIV/0! | AD77: =SUM(D77-H77)/D77 -> #DIV/0! | AG77: Estimated months claim | AH77: 0 | AK77: =SUM(W78-W77) -> 0 | AL77: =SUM(K78-K77) -> 0
C78: Week 4 | F78: =D78-E78 -> 0 | G78: =F78/D78 -> #DIV/0! | J78: =SUM(H78-R78) -> 0 | K78: =SUM(I78-S78) -> 0 | L78: =J78-K78 -> 0 | M78: =L78/J78 -> #DIV/0! | N78: 0 | S78: 0 | T78: =R78-S78 -> 0 | U78: =T78/R78 -> #DIV/0! | W78: 0 | X78: =V78-W78 -> 0 | Y78: =X78/V78 -> #DIV/0! | Z78: 0 | AA78: =(E78-K78-S78)/W78 -> #DIV/0! | AB78: =(D78-J78-R78)/V78 -> #DIV/0! | AC78: =(E78-K78-S78)/E78 -> #DIV/0! | AD78: =SUM(D78-H78)/D78 -> #DIV/0! | AK78: =SUM(W79-W78) -> 0 | AL78: =SUM(K79-K78) -> 0
C79: Week 5 | F79: =D79-E79 -> 0 | G79: =F79/D79 -> #DIV/0! | J79: =SUM(H79-R79) -> 0 | K79: =SUM(I79-S79) -> 0 | L79: =J79-K79 -> 0 | M79: =L79/J79 -> #DIV/0! | N79: 0 | S79: 0 | T79: =R79-S79 -> 0 | U79: =T79/R79 -> #DIV/0! | W79: 0 | X79: =V79-W79 -> 0 | Y79: =X79/V79 -> #DIV/0! | Z79: 0 | AA79: =(E79-K79-S79)/W79 -> #DIV/0! | AB79: =(D79-J79-R79)/V79 -> #DIV/0! | AC79: =(E79-K79-S79)/E79 -> #DIV/0! | AD79: =SUM(D79-H79)/D79 -> #DIV/0! | AK79: =SUM(AK74,AK75,AK76,AK77,AK78) -> 0 | AL79: =SUM(AL74,AL75,AL76,AL77,AL78) -> -33639.16
A81: ='Main Sheet'!A26 -> 8352 | B81: ='Main Sheet'!B26 -> 5 Sanscrit Place | C81: Start of month | D81: 43448.62 | E81: 19551.87 | F81: =D81-E81 -> 23896.75 | G81: =F81/D81 -> 0.55000021 | H81: 31063.54 | I81: 25863.55 | J81: =SUM(H81-R81) -> 16447.56 | K81: =SUM(I81-S81) -> 18255.63 | L81: =J81-K81 -> -1808.07 | M81: =L81/J81 -> -0.10992938 | N81: 0 | R81: 14615.98 | S81: 7607.92 | T81: =R81-S81 -> 7008.06 | U81: =T81/R81 -> 0.47947931 | V81: 292.93 | W81: 181.5 | X81: =V81-W81 -> 111.43 | Y81: =X81/V81 -> 0.38039805 | Z81: 0 | AA81: =(E81-K81-S81)/W81 -> -34.775096 | AB81: =(D81-J81-R81)/V81 -> 42.279999 | AC81: =(E81-K81-S81)/E81 -> -0.3228172 | AD81: =SUM(D81-H81)/D81 -> 0.28505117 | AG81: Hours calc for monthly claims | AH81: =AK86 -> -181.5 | AK81: =SUM(W82-W81) -> 0 | AL81: =SUM(K82-K81) -> 979.13
C82: Week 1 | D82: 43448.62 | E82: 34758.89 | F82: =D82-E82 -> 8689.73 | G82: =F82/D82 -> 0.20000014 | H82: 31063.54 | I82: 26842.68 | J82: =SUM(H82-R82) -> 16447.56 | K82: =SUM(I82-S82) -> 19234.76 | L82: =J82-K82 -> -2787.2 | M82: =L82/J82 -> -0.16945979 | N82: 0 | R82: 14615.98 | S82: 7607.92 | T82: =R82-S82 -> 7008.06 | U82: =T82/R82 -> 0.47947931 | V82: 292.93 | W82: 181.5 | X82: =V82-W82 -> 111.43 | Y82: =X82/V82 -> 0.38039805 | Z82: 0 | AA82: =(E82-K82-S82)/W82 -> 43.615482 | AB82: =(D82-J82-R82)/V82 -> 42.279999 | AC82: =(E82-K82-S82)/E82 -> 0.22774634 | AD82: =SUM(D82-H82)/D82 -> 0.28505117 | AG82: Materials calc for monthly claims | AH82: =AL86 -> -18255.63 | AK82: =SUM(W83-W82) -> -181.5 | AL82: =SUM(K83-K82) -> -19234.76
C83: Week 2 | D83: 0 | E83: 0 | F83: =D83-E83 -> 0 | G83: =F83/D83 -> #DIV/0! | H83: 0 | I83: 0 | J83: =SUM(H83-R83) -> 0 | K83: =SUM(I83-S83) -> 0 | L83: =J83-K83 -> 0 | M83: =L83/J83 -> #DIV/0! | R83: 0 | S83: 0 | T83: =R83-S83 -> 0 | U83: =T83/R83 -> #DIV/0! | V83: 0 | W83: 0 | X83: =V83-W83 -> 0 | Y83: =X83/V83 -> #DIV/0! | Z83: 0 | AA83: =(E83-K83-S83)/W83 -> #DIV/0! | AB83: =(D83-J83-R83)/V83 -> #DIV/0! | AC83: =(E83-K83-S83)/E83 -> #DIV/0! | AD83: =SUM(D83-H83)/D83 -> #DIV/0! | AK83: =SUM(W84-W83) -> 0 | AL83: =SUM(K84-K83) -> 0
C84: Week 3 | D84: 0 | E84: 0 | F84: =D84-E84 -> 0 | G84: =F84/D84 -> #DIV/0! | H84: 0 | I84: 0 | J84: =SUM(H84-R84) -> 0 | K84: =SUM(I84-S84) -> 0 | L84: =J84-K84 -> 0 | M84: =L84/J84 -> #DIV/0! | R84: 0 | S84: 0 | T84: =R84-S84 -> 0 | U84: =T84/R84 -> #DIV/0! | V84: 0 | W84: 0 | X84: =V84-W84 -> 0 | Y84: =X84/V84 -> #DIV/0! | Z84: 0 | AA84: =(E84-K84-S84)/W84 -> #DIV/0! | AB84: =(D84-J84-R84)/V84 -> #DIV/0! | AC84: =(E84-K84-S84)/E84 -> #DIV/0! | AD84: =SUM(D84-H84)/D84 -> #DIV/0! | AG84: Estimated months claim | AH84: 0 | AK84: =SUM(W85-W84) -> 0 | AL84: =SUM(K85-K84) -> 0
C85: Week 4 | D85: 0 | E85: 0 | F85: =D85-E85 -> 0 | G85: =F85/D85 -> #DIV/0! | H85: 0 | I85: 0 | J85: =SUM(H85-R85) -> 0 | K85: =SUM(I85-S85) -> 0 | L85: =J85-K85 -> 0 | M85: =L85/J85 -> #DIV/0! | R85: 0 | S85: 0 | T85: =R85-S85 -> 0 | U85: =T85/R85 -> #DIV/0! | V85: 0 | W85: 0 | X85: =V85-W85 -> 0 | Y85: =X85/V85 -> #DIV/0! | AA85: =(E85-K85-S85)/W85 -> #DIV/0! | AB85: =(D85-J85-R85)/V85 -> #DIV/0! | AC85: =(E85-K85-S85)/E85 -> #DIV/0! | AD85: =SUM(D85-H85)/D85 -> #DIV/0! | AK85: =SUM(W86-W85) -> 0 | AL85: =SUM(K86-K85) -> 0
C86: Week 5 | D86: 0 | E86: 0 | F86: =D86-E86 -> 0 | G86: =F86/D86 -> #DIV/0! | H86: 0 | I86: 0 | J86: =SUM(H86-R86) -> 0 | K86: =SUM(I86-S86) -> 0 | L86: =J86-K86 -> 0 | M86: =L86/J86 -> #DIV/0! | R86: 0 | S86: 0 | T86: =R86-S86 -> 0 | U86: =T86/R86 -> #DIV/0! | V86: 0 | W86: 0 | X86: =V86-W86 -> 0 | Y86: =X86/V86 -> #DIV/0! | AA86: =(E86-K86-S86)/W86 -> #DIV/0! | AB86: =(D86-J86-R86)/V86 -> #DIV/0! | AC86: =(E86-K86-S86)/E86 -> #DIV/0! | AD86: =SUM(D86-H86)/D86 -> #DIV/0! | AK86: =SUM(AK81,AK82,AK83,AK84,AK85) -> -181.5 | AL86: =SUM(AL81,AL82,AL83,AL84,AL85) -> -18255.63
A88: ='Main Sheet'!A28 -> 8234 | B88: ='Main Sheet'!B28 -> Melhuish House | C88: Start of month | D88: 49964.93 | E88: 25359.22 | F88: =D88-E88 -> 24605.71 | G88: =F88/D88 -> 0.49245961 | H88: 43768.91 | I88: 25556.81 | J88: =SUM(H88-R88) -> 37199.62 | K88: =SUM(I88-S88) -> 20554.23 | L88: =J88-K88 -> 16645.39 | M88: =L88/J88 -> 0.44746129 | N88: 0 | R88: 6569.29 | S88: 5002.58 | T88: =R88-S88 -> 1566.71 | U88: =T88/R88 -> 0.23849 | V88: 131.78 | W88: 113.75 | X88: =V88-W88 -> 18.03 | Y88: =X88/V88 -> 0.13681894 | Z88: 0 | AA88: =(E88-K88-S88)/W88 -> -1.7370549 | AB88: =(D88-J88-R88)/V88 -> 47.017909 | AC88: =(E88-K88-S88)/E88 -> -0.0077916434 | AD88: =SUM(D88-H88)/D88 -> 0.12400738 | AG88: Hours calc for monthly claims | AH88: =AK93 -> -113.75 | AK88: =SUM(W89-W88) -> 58 | AL88: =SUM(K89-K88) -> 7824.22
C89: Week 1 | D89: 49964.93 | E89: 45361.39 | F89: =D89-E89 -> 4603.54 | G89: =F89/D89 -> 0.092135424 | H89: 43768.91 | I89: 35776.29 | J89: =SUM(H89-R89) -> 37199.62 | K89: =SUM(I89-S89) -> 28378.45 | L89: =J89-K89 -> 8821.17 | M89: =L89/J89 -> 0.23713065 | R89: 6569.29 | S89: 7397.84 | T89: =R89-S89 -> -828.55 | U89: =T89/R89 -> -0.12612474 | V89: 131.78 | W89: 171.75 | X89: =V89-W89 -> -39.97 | Y89: =X89/V89 -> -0.30330854 | AA89: =(E89-K89-S89)/W89 -> 55.808443 | AB89: =(D89-J89-R89)/V89 -> 47.017909 | AC89: =(E89-K89-S89)/E89 -> 0.21130525 | AD89: =SUM(D89-H89)/D89 -> 0.12400738 | AG89: Materials calc for monthly claims | AH89: =AL93 -> -20554.23 | AK89: =SUM(W90-W89) -> -171.75 | AL89: =SUM(K90-K89) -> -28378.45
C90: Week 2 | D90: 0 | E90: 0 | F90: =D90-E90 -> 0 | G90: =F90/D90 -> #DIV/0! | H90: 0 | I90: 0 | J90: =SUM(H90-R90) -> 0 | K90: =SUM(I90-S90) -> 0 | L90: =J90-K90 -> 0 | M90: =L90/J90 -> #DIV/0! | R90: 0 | S90: 0 | T90: =R90-S90 -> 0 | U90: =T90/R90 -> #DIV/0! | V90: 0 | W90: 0 | X90: =V90-W90 -> 0 | Y90: =X90/V90 -> #DIV/0! | AA90: =(E90-K90-S90)/W90 -> #DIV/0! | AB90: =(D90-J90-R90)/V90 -> #DIV/0! | AC90: =(E90-K90-S90)/E90 -> #DIV/0! | AD90: =SUM(D90-H90)/D90 -> #DIV/0! | AK90: =SUM(W91-W90) -> 0 | AL90: =SUM(K91-K90) -> 0
C91: Week 3 | D91: 0 | E91: 0 | F91: =D91-E91 -> 0 | G91: =F91/D91 -> #DIV/0! | H91: 0 | I91: 0 | J91: =SUM(H91-R91) -> 0 | K91: =SUM(I91-S91) -> 0 | L91: =J91-K91 -> 0 | M91: =L91/J91 -> #DIV/0! | R91: 0 | S91: 0 | T91: =R91-S91 -> 0 | U91: =T91/R91 -> #DIV/0! | V91: 0 | W91: 0 | X91: =V91-W91 -> 0 | Y91: =X91/V91 -> #DIV/0! | AA91: =(E91-K91-S91)/W91 -> #DIV/0! | AB91: =(D91-J91-R91)/V91 -> #DIV/0! | AC91: =(E91-K91-S91)/E91 -> #DIV/0! | AD91: =SUM(D91-H91)/D91 -> #DIV/0! | AG91: Estimated months claim | AH91: 0 | AK91: =SUM(W92-W91) -> 0 | AL91: =SUM(K92-K91) -> 0
C92: Week 4 | D92: 0 | E92: 0 | F92: =D92-E92 -> 0 | G92: =F92/D92 -> #DIV/0! | H92: 0 | I92: 0 | J92: =SUM(H92-R92) -> 0 | K92: =SUM(I92-S92) -> 0 | L92: =J92-K92 -> 0 | M92: =L92/J92 -> #DIV/0! | R92: 0 | S92: 0 | T92: =R92-S92 -> 0 | U92: =T92/R92 -> #DIV/0! | V92: 0 | W92: 0 | X92: =V92-W92 -> 0 | Y92: =X92/V92 -> #DIV/0! | AA92: =(E92-K92-S92)/W92 -> #DIV/0! | AB92: =(D92-J92-R92)/V92 -> #DIV/0! | AC92: =(E92-K92-S92)/E92 -> #DIV/0! | AD92: =SUM(D92-H92)/D92 -> #DIV/0! | AK92: =SUM(W93-W92) -> 0 | AL92: =SUM(K93-K92) -> 0
C93: Week 5 | D93: 0 | E93: 0 | F93: =D93-E93 -> 0 | G93: =F93/D93 -> #DIV/0! | H93: 0 | I93: 0 | J93: =SUM(H93-R93) -> 0 | K93: =SUM(I93-S93) -> 0 | L93: =J93-K93 -> 0 | M93: =L93/J93 -> #DIV/0! | R93: 0 | S93: 0 | T93: =R93-S93 -> 0 | U93: =T93/R93 -> #DIV/0! | V93: 0 | W93: 0 | X93: =V93-W93 -> 0 | Y93: =X93/V93 -> #DIV/0! | AA93: =(E93-K93-S93)/W93 -> #DIV/0! | AB93: =(D93-J93-R93)/V93 -> #DIV/0! | AC93: =(E93-K93-S93)/E93 -> #DIV/0! | AD93: =SUM(D93-H93)/D93 -> #DIV/0! | AK93: =SUM(AK88,AK89,AK90,AK91,AK92) -> -113.75 | AL93: =SUM(AL88,AL89,AL90,AL91,AL92) -> -20554.23
A95: ='Main Sheet'!A30 -> 8214 | B95: ='Main Sheet'!B30 -> 6 Tiroroa Lane | C95: Start of month | D95: 109103.76 | E95: 51323.57 | F95: =D95-E95 -> 57780.19 | G95: =F95/D95 -> 0.52958936 | H95: 81158.83 | I95: 40300.16 | J95: =SUM(H95-R95) -> 52391.31 | K95: =SUM(I95-S95) -> 27621.5 | L95: =J95-K95 -> 24769.81 | M95: =L95/J95 -> 0.4727847 | N95: 0.2 | R95: 28767.52 | S95: 12678.66 | T95: =R95-S95 -> 16088.86 | U95: =T95/R95 -> 0.55927171 | V95: 577.33 | W95: 295.5 | X95: =V95-W95 -> 281.83 | Y95: =X95/V95 -> 0.48816102 | Z95: 0 | AA95: =(E95-K95-S95)/W95 -> 37.304264 | AB95: =(D95-J95-R95)/V95 -> 48.403738 | AC95: =(E95-K95-S95)/E95 -> 0.2147826 | AD95: =SUM(D95-H95)/D95 -> 0.25613169 | AG95: Hours calc for monthly claims | AH95: =AK100 -> -295.5 | AK95: =SUM(W96-W95) -> 19.25 | AL95: =SUM(K96-K95) -> 1.96
C96: Week 1 | D96: 109103.76 | E96: 77821.91 | F96: =D96-E96 -> 31281.85 | G96: =F96/D96 -> 0.28671652 | H96: 81158.83 | I96: 41214.74 | J96: =SUM(H96-R96) -> 52391.31 | K96: =SUM(I96-S96) -> 27623.46 | L96: =J96-K96 -> 24767.85 | M96: =L96/J96 -> 0.47274729 | N96: 0.2 | R96: 28767.52 | S96: 13591.28 | T96: =R96-S96 -> 15176.24 | U96: =T96/R96 -> 0.52754773 | V96: 577.33 | W96: 314.75 | X96: =V96-W96 -> 262.58 | Y96: =X96/V96 -> 0.45481787 | Z96: 0 | AA96: =(E96-K96-S96)/W96 -> 116.30554 | AB96: =(D96-J96-R96)/V96 -> 48.403738 | AC96: =(E96-K96-S96)/E96 -> 0.4703967 | AD96: =SUM(D96-H96)/D96 -> 0.25613169 | AG96: Materials calc for monthly claims | AH96: =AL100 -> -27621.5 | AK96: =SUM(W97-W96) -> -314.75 | AL96: =SUM(K97-K96) -> -27623.46
C97: Week 2 | D97: 0 | E97: 0 | F97: =D97-E97 -> 0 | G97: =F97/D97 -> #DIV/0! | H97: 0 | I97: 0 | J97: =SUM(H97-R97) -> 0 | K97: =SUM(I97-S97) -> 0 | L97: =J97-K97 -> 0 | M97: =L97/J97 -> #DIV/0! | N97: 0.2 | R97: 0 | S97: 0 | T97: =R97-S97 -> 0 | U97: =T97/R97 -> #DIV/0! | V97: 0 | W97: 0 | X97: =V97-W97 -> 0 | Y97: =X97/V97 -> #DIV/0! | Z97: 0.2 | AA97: =(E97-K97-S97)/W97 -> #DIV/0! | AB97: =(D97-J97-R97)/V97 -> #DIV/0! | AC97: =(E97-K97-S97)/E97 -> #DIV/0! | AD97: =SUM(D97-H97)/D97 -> #DIV/0! | AK97: =SUM(W98-W97) -> 0 | AL97: =SUM(K98-K97) -> 0
C98: Week 3 | D98: 0 | E98: 0 | F98: =D98-E98 -> 0 | G98: =F98/D98 -> #DIV/0! | H98: 0 | I98: 0 | J98: =SUM(H98-R98) -> 0 | K98: =SUM(I98-S98) -> 0 | L98: =J98-K98 -> 0 | M98: =L98/J98 -> #DIV/0! | N98: 0 | R98: 0 | S98: 0 | T98: =R98-S98 -> 0 | U98: =T98/R98 -> #DIV/0! | V98: 0 | W98: 0 | X98: =V98-W98 -> 0 | Y98: =X98/V98 -> #DIV/0! | Z98: 0.25 | AA98: =(E98-K98-S98)/W98 -> #DIV/0! | AB98: =(D98-J98-R98)/V98 -> #DIV/0! | AC98: =(E98-K98-S98)/E98 -> #DIV/0! | AD98: =SUM(D98-H98)/D98 -> #DIV/0! | AG98: Estimated months claim | AH98: 0 | AK98: =SUM(W99-W98) -> 0 | AL98: =SUM(K99-K98) -> 0
C99: Week 4 | D99: 0 | E99: 0 | F99: =D99-E99 -> 0 | G99: =F99/D99 -> #DIV/0! | H99: 0 | I99: 0 | J99: =SUM(H99-R99) -> 0 | K99: =SUM(I99-S99) -> 0 | L99: =J99-K99 -> 0 | M99: =L99/J99 -> #DIV/0! | N99: 0 | R99: 0 | S99: 0 | T99: =R99-S99 -> 0 | U99: =T99/R99 -> #DIV/0! | V99: 0 | W99: 0 | X99: =V99-W99 -> 0 | Y99: =X99/V99 -> #DIV/0! | AA99: =(E99-K99-S99)/W99 -> #DIV/0! | AB99: =(D99-J99-R99)/V99 -> #DIV/0! | AC99: =(E99-K99-S99)/E99 -> #DIV/0! | AD99: =SUM(D99-H99)/D99 -> #DIV/0! | AK99: =SUM(W100-W99) -> 0 | AL99: =SUM(K100-K99) -> 0
C100: Week 5 | D100: 0 | E100: 0 | F100: =D100-E100 -> 0 | G100: =F100/D100 -> #DIV/0! | H100: 0 | I100: 0 | J100: =SUM(H100-R100) -> 0 | K100: =SUM(I100-S100) -> 0 | L100: =J100-K100 -> 0 | M100: =L100/J100 -> #DIV/0! | N100: 0 | R100: 0 | S100: 0 | T100: =R100-S100 -> 0 | U100: =T100/R100 -> #DIV/0! | V100: 0 | W100: 0 | X100: =V100-W100 -> 0 | Y100: =X100/V100 -> #DIV/0! | AA100: =(E100-K100-S100)/W100 -> #DIV/0! | AB100: =(D100-J100-R100)/V100 -> #DIV/0! | AC100: =(E100-K100-S100)/E100 -> #DIV/0! | AD100: =SUM(D100-H100)/D100 -> #DIV/0! | AK100: =SUM(AK95,AK96,AK97,AK98,AK99) -> -295.5 | AL100: =SUM(AL95,AL96,AL97,AL98,AL99) -> -27621.5
A102: ='Main Sheet'!A32 -> 6792 | B102: ='Main Sheet'!B32 -> Major Hornbrook | C102: Start of month | D102: 27742.44 | E102: 0 | F102: =D102-E102 -> 27742.44 | G102: =F102/D102 -> 1 | H102: 20094.24 | I102: 405.4 | J102: =SUM(H102-R102) -> 11429.46 | K102: =SUM(I102-S102) -> 73.74 | L102: =J102-K102 -> 11355.72 | M102: =L102/J102 -> 0.99354825 | N102: 0 | R102: 8664.78 | S102: 331.66 | T102: =R102-S102 -> 8333.12 | U102: =T102/R102 -> 0.96172321 | V102: 173.8 | W102: 7.75 | X102: =V102-W102 -> 166.05 | Y102: =X102/V102 -> 0.95540852 | AA102: =(E102-K102-S102)/W102 -> -52.309677 | AB102: =(D102-J102-R102)/V102 -> 44.005754 | AC102: =(E102-K102-S102)/E102 -> #DIV/0! | AD102: =SUM(D102-H102)/D102 -> 0.27568592 | AG102: Hours calc for monthly claims | AH102: =AK107 -> -7.75 | AK102: =SUM(W103-W102) -> 0 | AL102: =SUM(K103-K102) -> -13.89
C103: Week 1 | D103: 27861.41 | E103: 0 | F103: =D103-E103 -> 27861.41 | G103: =F103/D103 -> 1 | H103: 20162.08 | I103: 392.27 | J103: =SUM(H103-R103) -> 11464.04 | K103: =SUM(I103-S103) -> 59.85 | L103: =J103-K103 -> 11404.19 | M103: =L103/J103 -> 0.99477933 | N103: 0 | R103: 8698.04 | S103: 332.42 | T103: =R103-S103 -> 8365.62 | U103: =T103/R103 -> 0.96178219 | V103: 174.46 | W103: 7.75 | X103: =V103-W103 -> 166.71 | Y103: =X103/V103 -> 0.95557721 | AA103: =(E103-K103-S103)/W103 -> -50.615484 | AB103: =(D103-J103-R103)/V103 -> 44.132351 | AC103: =(E103-K103-S103)/E103 -> #DIV/0! | AD103: =SUM(D103-H103)/D103 -> 0.27634387 | AG103: Materials calc for monthly claims | AH103: =AL107 -> -73.74 | AK103: =SUM(W104-W103) -> -7.75 | AL103: =SUM(K104-K103) -> -59.85
C104: Week 2 | D104: 0 | E104: 0 | F104: =D104-E104 -> 0 | G104: =F104/D104 -> #DIV/0! | H104: 0 | I104: 0 | J104: =SUM(H104-R104) -> 0 | K104: =SUM(I104-S104) -> 0 | L104: =J104-K104 -> 0 | M104: =L104/J104 -> #DIV/0! | N104: 0 | R104: 0 | S104: 0 | T104: =R104-S104 -> 0 | U104: =T104/R104 -> #DIV/0! | V104: 0 | W104: 0 | X104: =V104-W104 -> 0 | Y104: =X104/V104 -> #DIV/0! | AA104: =(E104-K104-S104)/W104 -> #DIV/0! | AB104: =(D104-J104-R104)/V104 -> #DIV/0! | AC104: =(E104-K104-S104)/E104 -> #DIV/0! | AD104: =SUM(D104-H104)/D104 -> #DIV/0! | AK104: =SUM(W105-W104) -> 0 | AL104: =SUM(K105-K104) -> 0
C105: Week 3 | D105: 0 | E105: 0 | F105: =D105-E105 -> 0 | G105: =F105/D105 -> #DIV/0! | H105: 0 | I105: 0 | J105: =SUM(H105-R105) -> 0 | K105: =SUM(I105-S105) -> 0 | L105: =J105-K105 -> 0 | M105: =L105/J105 -> #DIV/0! | N105: 0 | R105: 0 | S105: 0 | T105: =R105-S105 -> 0 | U105: =T105/R105 -> #DIV/0! | V105: 0 | W105: 0 | X105: =V105-W105 -> 0 | Y105: =X105/V105 -> #DIV/0! | AA105: =(E105-K105-S105)/W105 -> #DIV/0! | AB105: =(D105-J105-R105)/V105 -> #DIV/0! | AC105: =(E105-K105-S105)/E105 -> #DIV/0! | AD105: =SUM(D105-H105)/D105 -> #DIV/0! | AG105: Estimated months claim | AH105: 0 | AK105: =SUM(W106-W105) -> 0 | AL105: =SUM(K106-K105) -> 0
C106: Week 4 | D106: 0 | E106: 0 | F106: =D106-E106 -> 0 | G106: =F106/D106 -> #DIV/0! | H106: 0 | I106: 0 | J106: =SUM(H106-R106) -> 0 | K106: =SUM(I106-S106) -> 0 | L106: =J106-K106 -> 0 | M106: =L106/J106 -> #DIV/0! | N106: 0 | R106: 0 | S106: 0 | T106: =R106-S106 -> 0 | U106: =T106/R106 -> #DIV/0! | V106: 0 | W106: 0 | X106: =V106-W106 -> 0 | Y106: =X106/V106 -> #DIV/0! | AA106: =(E106-K106-S106)/W106 -> #DIV/0! | AB106: =(D106-J106-R106)/V106 -> #DIV/0! | AC106: =(E106-K106-S106)/E106 -> #DIV/0! | AD106: =SUM(D106-H106)/D106 -> #DIV/0! | AK106: =SUM(W107-W106) -> 0 | AL106: =SUM(K107-K106) -> 0
C107: Week 5 | D107: 0 | E107: 0 | F107: =D107-E107 -> 0 | G107: =F107/D107 -> #DIV/0! | H107: 0 | I107: 0 | J107: =SUM(H107-R107) -> 0 | K107: =SUM(I107-S107) -> 0 | L107: =J107-K107 -> 0 | M107: =L107/J107 -> #DIV/0! | N107: 0 | R107: 0 | S107: 0 | T107: =R107-S107 -> 0 | U107: =T107/R107 -> #DIV/0! | V107: 0 | W107: 0 | X107: =V107-W107 -> 0 | Y107: =X107/V107 -> #DIV/0! | AA107: =(E107-K107-S107)/W107 -> #DIV/0! | AB107: =(D107-J107-R107)/V107 -> #DIV/0! | AC107: =(E107-K107-S107)/E107 -> #DIV/0! | AD107: =SUM(D107-H107)/D107 -> #DIV/0! | AK107: =SUM(AK102,AK103,AK104,AK105,AK106) -> -7.75 | AL107: =SUM(AL102,AL103,AL104,AL105,AL106) -> -73.74
A109: ='Main Sheet'!A34 -> 8840 | B109: ='Main Sheet'!B34 -> Inline Architecture | C109: Start of month | D109: 21300.45 | E109: 5515.31 | F109: =D109-E109 -> 15785.14 | G109: =F109/D109 -> 0.74107073 | H109: 11275.69 | I109: 5128.09 | J109: =SUM(H109-R109) -> 4165.39 | K109: 815.93 | L109: =J109-K109 -> 3349.46 | M109: =L109/J109 -> 0.80411678 | N109: 1 | R109: 7110.3 | S109: 1880.39 | T109: =R109-S109 -> 5229.91 | U109: =T109/R109 -> 0.73553999 | V109: 142.36 | W109: 42.25 | X109: =V109-W109 -> 100.11 | Y109: =X109/V109 -> 0.7032172 | Z109: 1 | AA109: =(E109-K109-S109)/W109 -> 66.721657 | AB109: =(D109-J109-R109)/V109 -> 70.418376 | AC109: =(E109-K109-S109)/E109 -> 0.51112086 | AD109: =SUM(D109-H109)/D109 -> 0.47063607 | AG109: Hours calc for monthly claims | AH109: =AK114 -> -42.25 | AK109: =SUM(W110-W109) -> 14.25 | AL109: =SUM(K110-K109) -> 2844.83
C110: Week 1 | D110: 21300.45 | E110: 10143.09 | F110: =D110-E110 -> 11157.36 | G110: =F110/D110 -> 0.52380865 | H110: 11275.69 | I110: 6237.89 | J110: =SUM(H110-R110) -> 4165.39 | K110: =SUM(I110-S110) -> 3660.76 | L110: =J110-K110 -> 504.63 | M110: =L110/J110 -> 0.12114832 | N110: 1 | R110: 7110.3 | S110: 2577.13 | T110: =R110-S110 -> 4533.17 | U110: =T110/R110 -> 0.63754975 | V110: 142.36 | W110: 56.5 | X110: =V110-W110 -> 85.86 | Y110: =X110/V110 -> 0.60311885 | Z110: 1 | AA110: =(E110-K110-S110)/W110 -> 69.118584 | AB110: =(D110-J110-R110)/V110 -> 70.418376 | AC110: =(E110-K110-S110)/E110 -> 0.38501088 | AD110: =SUM(D110-H110)/D110 -> 0.47063607 | AG110: Materials calc for monthly claims | AH110: =AL114 -> -815.93 | AK110: =SUM(W111-W110) -> -56.5 | AL110: =SUM(K111-K110) -> -3660.76
C111: Week 2 | D111: 0 | E111: 0 | F111: =D111-E111 -> 0 | G111: =F111/D111 -> #DIV/0! | H111: 0 | I111: 0 | J111: =SUM(H111-R111) -> 0 | K111: =SUM(I111-S111) -> 0 | L111: =J111-K111 -> 0 | M111: =L111/J111 -> #DIV/0! | N111: 1 | R111: 0 | S111: 0 | T111: =R111-S111 -> 0 | U111: =T111/R111 -> #DIV/0! | V111: 0 | W111: 0 | X111: =V111-W111 -> 0 | Y111: =X111/V111 -> #DIV/0! | Z111: 1 | AA111: =(E111-K111-S111)/W111 -> #DIV/0! | AB111: =(D111-J111-R111)/V111 -> #DIV/0! | AC111: =(E111-K111-S111)/E111 -> #DIV/0! | AD111: =SUM(D111-H111)/D111 -> #DIV/0! | AK111: =SUM(W112-W111) -> 0 | AL111: =SUM(K112-K111) -> 0
C112: Week 3 | D112: 0 | E112: 0 | F112: =D112-E112 -> 0 | G112: =F112/D112 -> #DIV/0! | H112: 0 | I112: 0 | J112: =SUM(H112-R112) -> 0 | K112: =SUM(I112-S112) -> 0 | L112: =J112-K112 -> 0 | M112: =L112/J112 -> #DIV/0! | N112: 0 | R112: 0 | S112: 0 | T112: =R112-S112 -> 0 | U112: =T112/R112 -> #DIV/0! | V112: 0 | W112: 0 | X112: =V112-W112 -> 0 | Y112: =X112/V112 -> #DIV/0! | Z112: 0 | AA112: =(E112-K112-S112)/W112 -> #DIV/0! | AB112: =(D112-J112-R112)/V112 -> #DIV/0! | AC112: =(E112-K112-S112)/E112 -> #DIV/0! | AD112: =SUM(D112-H112)/D112 -> #DIV/0! | AG112: Estimated months claim | AH112: 0 | AK112: =SUM(W113-W112) -> 0 | AL112: =SUM(K113-K112) -> 0
C113: Week 4 | D113: 0 | E113: 0 | F113: =D113-E113 -> 0 | G113: =F113/D113 -> #DIV/0! | H113: 0 | I113: 0 | J113: =SUM(H113-R113) -> 0 | K113: =SUM(I113-S113) -> 0 | L113: =J113-K113 -> 0 | M113: =L113/J113 -> #DIV/0! | N113: 0 | R113: 0 | S113: 0 | T113: =R113-S113 -> 0 | U113: =T113/R113 -> #DIV/0! | V113: 0 | W113: 0 | X113: =V113-W113 -> 0 | Y113: =X113/V113 -> #DIV/0! | Z113: 0 | AA113: =(E113-K113-S113)/W113 -> #DIV/0! | AB113: =(D113-J113-R113)/V113 -> #DIV/0! | AC113: =(E113-K113-S113)/E113 -> #DIV/0! | AD113: =SUM(D113-H113)/D113 -> #DIV/0! | AK113: =SUM(W114-W113) -> 0 | AL113: =SUM(K114-K113) -> 0
C114: Week 5 | D114: 0 | E114: 0 | F114: =D114-E114 -> 0 | G114: =F114/D114 -> #DIV/0! | H114: 0 | I114: 0 | J114: =SUM(H114-R114) -> 0 | K114: =SUM(I114-S114) -> 0 | L114: =J114-K114 -> 0 | M114: =L114/J114 -> #DIV/0! | N114: 0 | R114: 0 | S114: 0 | T114: =R114-S114 -> 0 | U114: =T114/R114 -> #DIV/0! | V114: 0 | W114: 0 | X114: =V114-W114 -> 0 | Y114: =X114/V114 -> #DIV/0! | Z114: 0 | AA114: =(E114-K114-S114)/W114 -> #DIV/0! | AB114: =(D114-J114-R114)/V114 -> #DIV/0! | AC114: =(E114-K114-S114)/E114 -> #DIV/0! | AD114: =SUM(D114-H114)/D114 -> #DIV/0! | AK114: =SUM(AK109,AK110,AK111,AK112,AK113) -> -42.25 | AL114: =SUM(AL109,AL110,AL111,AL112,AL113) -> -815.93
A116: ='Main Sheet'!A36 -> 8769 | B116: ='Main Sheet'!B36 -> Percival Bach | C116: Start of month | D116: 63405.46 | E116: 0 | F116: =D116-E116 -> 63405.46 | G116: =F116/D116 -> 1 | H116: 43553.81 | I116: 9012.69 | J116: =SUM(H116-R116) -> 29573.66 | K116: =SUM(I116-S116) -> 8270.88 | L116: =J116-K116 -> 21302.78 | M116: =L116/J116 -> 0.72032951 | N116: 0 | R116: 13980.15 | S116: 741.81 | T116: =R116-S116 -> 13238.34 | U116: =T116/R116 -> 0.94693834 | V116: 279.87 | W116: 52 | X116: =V116-W116 -> 227.87 | Y116: =X116/V116 -> 0.81419945 | Z116: 0 | AA116: =(E116-K116-S116)/W116 -> -173.32096 | AB116: =(D116-J116-R116)/V116 -> 70.931683 | AC116: =(E116-K116-S116)/E116 -> #DIV/0! | AD116: =SUM(D116-H116)/D116 -> 0.31309054 | AG116: Hours calc for monthly claims | AH116: =AK121 -> -52 | AK116: =SUM(W117-W116) -> 36.5 | AL116: =SUM(K117-K116) -> 3381.04
...

Sheet Sheet1
A3: 340 | B3: Allowed | C3: Actual | D3: % of job
A4: Box out | B4: 30 | D4: =SUM(B4/A3) -> 0.088235294
A5: pre-wire | B5: 60 | P5: 95.35
A6: cut out | B6: 100 | P6: 102.69
A7: fit off lights | B7: 150 | P7: 134.82
P8: 324.19
P9: 415
