Workbook

Sheet Main Sheet
A1: Updated Job Spreadsheet
A2: Job Number | B2: Job Name | C2: Job Owner | D2: Contract Signed & Returned. Retention % loaded correctly into Katipolt | E2: Warranty Signed & Returned | F2: Construction Programme Received | G2: Into Work Calculator 2 Weekly | H2: Temp Application Done | I2: Mains Connection Application | J2: POs Sent to Sub contractors | K2: Switchboard Drawing Sent for Approval | L2: Email Sent to QS/Builder to Confirm Order Gear | M2: Long Lead Time Materials Ordered | O2: Client Walk Through | P2: Pre Job Meeting Completed with Staff Job Pack Made | Q2: O&M Manual underway (notes for what's needed) | R2: QA Completed By Others | T2: Job Completion Paperwork Completed | U2: All V.Os captured | W2: Last toolbox date
M3: Ordered | N3: Lead Times Comm. | R3: 1st Fix | S3: 2nd Fix
A4: 7658 | B4: Charity Hospital | C4: Cameron | D4: Yes | F4: Yes | G4: Yes | H4: N/A | I4: N/A | J4: Yes | K4: Yes | L4: Yes | M4: Yes | P4: Yes
A6: 8142 | B6: Fisher Developements | C6: Cameron | D6: Yes | F6: Yes | G6: yes | H6: Yes | I6: Yes | J6: Yes | K6: Yes | M6: Yes
A8: 8824 | B8: 3 Innovation Road | C8: Cameron
A10: 8127 | B10: Rolly Autowash | C10: Cameron | D10: Yes | F10: Yes | G10: No | H10: Yes | I10: Yes | J10: N/A | K10: Yes | M10: Yes
A12: 8183 | B12: Murney - 1 Freight Drive + 109 Iport | C12: Cameron | D12: Yes | F12: Yes | G12: Yes | H12: Yes | I12: Yes | J12: Yes | K12: Yes | M12: Yes
A14: 8886 | B14: Monkey Toe - Fisher fit out | C14: Cameron | F14: Yes | G14: No | H14: N/A | I14: Yes | J14: Yes | K14: Yes
A16: 8887 | B16: Tenancy 2 - Fisher Fit out | C16: Cameron | F16: Yes | G16: No | H16: N/A | I16: Yes | J16: Yes | K16: Yes
A18: 8670 | B18: Studio DB - tautara fit out | C18: Cameron | D18: Yes
A20: 8907 | B20: 35 Mania | C20: Cameron | D20: Yes
A22: 9065 | B22: Cooltranz stage 4 | C22: Cameron
A24: 9259 | B24: Andrew Reeve Stage 2 | C24: Cameron
A26: 8352 | B26: 5 Sanscrit Place | C26: Tom | D26: Yes | E26: N/A | F26: Yes | H26: N/A | I26: N/A | K26: N/A | L26: Yes | O26: Yes
A28: 8234 | B28: Melhuish House | C28: Tom
A30: 8214 | B30: 6 Tiroroa Lane | C30: Tom | D30: Yes | E30: N/A | K30: N/A
A32: 6792 | B32: Major Hornbrook | C32: Tom | D32: Yes | E32: N/A | F32: Yes | G32: 45979 | H32: Yes | I32: Yes | J32: N/A | K32: N/A | L32: N/A | O32: No | Q32: NA
A34: 8840 | B34: Inline Architecture | C34: Tom
A36: 8769 | B36: Percival Bach
A38: 7901 | B38: St Albans Street
A40: 8923 | B40: 4 Perry St
A42: 7864 | B42: Ryans House
A44: 7912 | B44: 71A Fendalton Road | C44: Tom | D44: Yes | E44: N/A | G44: 45979 | J44: N/A | K44: N/A | O44: No
A46: 8360 | B46: Dixon House | C46: Tom | D46: Yes | E46: N/A | F46: Yes | G46: 45979 | H46: N/A | I46: Yes | J46: N/A | K46: N/A | L46: N/A | M46: N/A | O46: Yes
A48: 8337 | B48: Waimak Dairys
A50: 9240 | B50: Daves Twizel Shack
A52: 7428 | B52: FAB Pegasus Lakeside | C52: Tom | D52: Yes | E52: N/A | F52: Yes | G52: 45979 | H52: Yes | J52: N/A | K52: N/A | L52: N/A | O52: No
A54: 9351 | B54: Harewood Golf Club | C54: Tom
A56: 7429 | B56: Taggart House | C56: Tom | D56: Yes | E56: N/A | F56: Yes | G56: 45979 | H56: N/A | I56: N/A | J56: N/A | K56: N/A | L56: N/A | O56: No
A58: 9508 | B58: St Barnabas Church | C58: Tom | E58: N/A | F58: Yes | G58: 45979 | H58: N/A | I58: N/A | J58: N/A | K58: N/A | L58: N/A | O58: No
E60: N/A | F60: Yes | H60: N/A | J60: N/A
B62: Contracting
A64: 8946 | B64: Westcoast Vaults | C64: Cameron
A66: 8308 | B66: Roydvale | C66: Tom | E66: N/A | F66: Yes | H66: N/A | J66: N/A

Sheet Deliverables Sheet
A1: Updated Job Spreadsheet
A2: Job Number | B2: Job Name | C2: Week | D2: Quoted Price | E2: Claim to date | F2: Remaining to claim | G2: % Claim remaining | H2: Total quoted cost | I2: Total actual cost | J2: Quoted material cost | K2: Actual material cost | L2: Material cost remaining | M2: Material % remaining | N2: Estimated % of materials recieved | O2: Quoted labour cost | P2: Actual labour cost | Q2: Labour cost remaining | R2: Labour cost % remaining | S2: Quoted labour hours | T2: Actual labour hours | U2: Labour hours remaining | V2: Labour hour % remaining | W2: Estimated % of job complete | X2: GP $ Per Hour | Y2: Quoted GP $ Per Hour | Z2: Margin to date | AA2: Quoted margin
AH3: Hours calcs | AI3: Materials calcs
A4: 7658 | B4: Charity Hospital | C4: Start of month | D4: 215046.91 | E4: 205915.9 | F4: 9131.01 | G4: 0.04246055 | H4: 181293.63 | I4: 113522.99 | J4: 155024.75 | K4: 92952.56 | L4: 62072.19 | M4: 0.40040181 | N4: 0.9 | O4: 26268.88 | P4: 20570.43 | Q4: 5698.45 | R4: 0.21692779 | S4: 530.95 | T4: 418 | U4: 112.95 | V4: 0.2127319 | X4: 221.03567 | Y4: 63.571485 | Z4: 0.44869245 | AA4: 0.15695775 | AD4: Hours calc for monthly claims | AE4: -418 | AH4: -418 | AI4: -92952.56
C5: Week 1 | D5: 233882.27 | E5: 205915.9 | F5: 27966.37 | G5: 0.11957456 | H5: 199128.99 | I5: 161636.57 | J5: 172860.11 | K5: 136958.29 | L5: 35901.82 | M5: 0.20769291 | O5: 26268.88 | P5: 24678.28 | Q5: 1590.6 | R5: 0.060550735 | S5: 530.95 | T5: 498.25 | U5: 32.7 | V5: 0.06158772 | X5: 88.869704 | Y5: 65.454902 | Z5: 0.215 | AA5: 0.1486 | AD5: Materials calc for monthly claims | AE5: -92952.56
C6: Week 2
C7: Week 3 | D7: 233882.27 | E7: 205915.9 | F7: 27966.37 | G7: 0.11957456 | H7: 199128.99 | I7: 165210.04 | J7: 172860.11 | K7: 137410.69 | L7: 35449.42 | M7: 0.20507577 | O7: 26268.88 | P7: 27799.35 | Q7: -1530.47 | R7: -0.058261715 | S7: 530.95 | T7: 556.5 | U7: -25.55 | V7: -0.048121292 | X7: 73.146199 | Y7: 65.454902 | Z7: 0.1977 | AA7: 0.1486 | AD7: Estimated months claim | AE7: 0
C8: Week 4
C9: Week 5 | AH9: -418 | AI9: -92952.56
A11: 8142 | B11: Fisher Developements | C11: Start of month | D11: 95023.47 | E11: 51156.11 | F11: 43867.36 | G11: 0.46164763 | H11: 72292.47 | I11: 48296.81 | J11: 56719.74 | K11: 45701.86 | L11: 11017.88 | M11: 0.19425124 | O11: 15572.73 | P11: 2594.95 | Q11: 12977.78 | R11: 0.83336576 | S11: 311.89 | T11: 52.5 | U11: 259.39 | V11: 0.83167142 | W11: 0.3 | X11: 54.462857 | Y11: 72.881465 | Z11: 0.055893617 | AA11: 0.23921459 | AD11: Hours calc for monthly claims | AE11: -52.5 | AH11: -52.5 | AI11: -45701.86
C12: Week 1 | D12: 129074.86 | E12: 55068.11 | F12: 74006.75 | G12: 0.57336301 | H12: 101420.72 | I12: 54810.2 | J12: 83645.65 | K12: 51716.87 | L12: 31928.78 | M12: 0.38171477 | O12: 17775.07 | P12: 3093.33 | Q12: 14681.74 | R12: 0.82597368 | S12: 356.07 | T12: 63 | U12: 293.07 | V12: 0.8230685 | X12: 4.0938095 | Y12: 77.66491 | Z12: 0.0047 | AA12: 0.2142 | AD12: Materials calc for monthly claims | AE12: -45701.86
C13: Week 2
C14: Week 3 | AD14: Estimated months claim | AE14: 0
C15: Week 4
C16: Week 5 | AH16: -52.5 | AI16: -45701.86
A18: 8824 | B18: 3 Innovation Road | C18: Start of month | D18: 27500.32 | E18: 6999.08 | F18: 20501.24 | G18: 0.74549096 | H18: 19565.83 | I18: 7621.92 | J18: 13767.34 | K18: 5911.24 | L18: 7856.1 | M18: 0.57063311 | O18: 5798.49 | P18: 1710.68 | Q18: 4087.81 | R18: 0.70497837 | S18: 125.39 | T18: 34.75 | U18: 90.64 | V18: 0.72286466 | W18: 0.25 | X18: -17.923453 | Y18: 63.278491 | Z18: -0.088988839 | AA18: 0.28852355 | AD18: Hours calc for monthly claims | AE18: -34.75 | AH18: -34.75 | AI18: -5911.24
C19: Week 1 | AD19: Materials calc for monthly claims | AE19: -5911.24
C20: Week 2
C21: Week 3 | AD21: Estimated months claim | AE21: 0
C22: Week 4
C23: Week 5 | AH23: -34.75 | AI23: -5911.24
A25: 8127 | B25: Rolly Autowash | C25: Start of month | D25: 150850.82 | E25: 111983.72 | F25: 38867.1 | G25: 0.25765256 | H25: 102178.42 | I25: 75718.13 | J25: 62464.86 | K25: 56964.81 | L25: 5500.05 | M25: 0.088050305 | N25: 0.9 | O25: 39713.56 | P25: 18753.32 | Q25: 20960.24 | R25: 0.52778547 | S25: 795.22 | T25: 388.25 | U25: 406.97 | V25: 0.51177033 | W25: 0.6 | X25: 93.40783 | Y25: 61.206207 | Z25: 0.32384698 | AA25: 0.32265254 | AD25: Hours calc for monthly claims | AE25: -388.25 | AH25: -388.25 | AI25: -56964.81
C26: Week 1 | D26: 150850.82 | E26: 111983.72 | F26: 38867.1 | G26: 0.25765256 | H26: 102178.42 | I26: 81033.37 | J26: 62464.86 | K26: 58088.59 | L26: 4376.27 | M26: 0.07005971 | O26: 39713.56 | P26: 22944.78 | Q26: 16768.78 | R26: 0.42224318 | S26: 795.22 | T26: 472.75 | U26: 322.47 | V26: 0.40551042 | X26: 65.468747 | Y26: 61.206215 | Z26: 0.2764 | AA26: 0.3227 | AD26: Materials calc for monthly claims | AE26: -56964.81
C27: Week 2
C28: Week 3 | AD28: Estimated months claim | AE28: 0
C29: Week 4
C30: Week 5 | AH30: -388.25 | AI30: -56964.81
A32: 8183 | B32: Murney - 1 Freight Drive + 109 Iport | C32: Start of month | D32: 389022.03 | E32: 176161.65 | F32: 212860.38 | G32: 0.54716793 | H32: 320431.12 | I32: 148939.51 | J32: 264519.78 | K32: 132316.71 | L32: 132203.07 | M32: 0.4997852 | O32: 55911.34 | P32: 16622.8 | Q32: 39288.54 | R32: 0.70269359 | S32: 1120.27 | T32: 387.5 | U32: 732.77 | V32: 0.65410124 | W32: 0.4 | X32: 70.250684 | Y32: 61.227124 | Z32: 0.15452932 | AA32: 0.17631626 | AD32: Hours calc for monthly claims | AE32: -387.5 | AH32: -387.5 | AI32: -132316.71
C33: Week 1 | D33: 396422.03 | E33: 176161.65 | F33: 220260.38 | G33: 0.55562094 | H33: 327431.12 | I33: 150094.16 | J33: 271519.78 | K33: 132259.14 | L33: 139260.64 | M33: 0.51289317 | O33: 55911.34 | P33: 17835.02 | Q33: 38076.32 | R33: 0.68101247 | S33: 1120.27 | T33: 416.25 | U33: 704.02 | V33: 0.62843779 | X33: 62.624601 | Y33: 61.584182 | Z33: 0.148 | AA33: 0.174 | AD33: Materials calc for monthly claims | AE33: -132316.71
C34: Week 2
C35: Week 3 | AD35: Estimated months claim | AE35: 0
C36: Week 4
C37: Week 5 | AH37: -387.5 | AI37: -132316.71
A39: 8886 | B39: Monkey Toe - Fisher fit out | C39: Start of month | D39: 128258.5 | E39: 36398.39 | F39: 91860.11 | G39: 0.7162107 | H39: 94098.32 | I39: 32521.46 | J39: 69042.09 | K39: 26847.46 | L39: 42194.63 | M39: 0.61114358 | O39: 25056.23 | P39: 5674 | Q39: 19382.23 | R39: 0.77354933 | S39: 501 | T39: 112 | U39: 389 | V39: 0.77644711 | W39: 0.4 | X39: 34.615446 | Y39: 68.183992 | Z39: 0.10651378 | AA39: 0.26633853 | AD39: Hours calc for monthly claims | AE39: -112 | AH39: -112 | AI39: -26847.46
C40: Week 1 | D40: 128258.5 | E40: 36398.39 | F40: 91860.11 | G40: 0.7162107 | H40: 94098.32 | I40: 35395.54 | J40: 69042.09 | K40: 29132.06 | L40: 39910.03 | M40: 0.57805362 | O40: 25056.23 | P40: 6263.48 | Q40: 18792.75 | R40: 0.75002305 | S40: 501.83 | T40: 122.75 | U40: 379.08 | V40: 0.75539525 | X40: 8.1698574 | Y40: 68.071224 | Z40: 0.0276 | AA40: 0.2663 | AD40: Materials calc for monthly claims | AE40: -26847.46
C41: Week 2 | D41: 128258.5 | E41: 36398.39 | F41: 91860.11 | G41: 0.7162107 | H41: 94098.32 | I41: 34659.62 | J41: 69042.09 | K41: 28340.06 | L41: 40702.03 | M41: 0.58952488 | O41: 25056.23 | P41: 6319.56 | Q41: 18736.67 | R41: 0.74778488 | S41: 501.83 | T41: 123.75 | U41: 378.08 | V41: 0.75340255 | X41: 14.050667 | Y41: 68.071224 | Z41: 0.0478 | AA41: 0.2663
C42: Week 3 | AD42: Estimated months claim | AE42: 0
C43: Week 4
C44: Week 5 | AH44: -112 | AI44: -26847.46
A46: 8887 | B46: Tenancy 2 - Fisher Fit out | C46: Start of month | D46: 64305.21 | E46: 25322.07 | F46: 38983.14 | G46: 0.60622055 | H46: 49749.48 | I46: 19566.87 | J46: 39151.4 | K46: 15639.05 | L46: 23512.35 | M46: 0.60054941 | N46: 0 | O46: 10598.08 | P46: 3927.82 | Q46: 6670.26 | R46: 0.62938381 | S46: 212.3 | T46: 86.75 | U46: 125.55 | V46: 0.59138012 | W46: 0.4 | X46: 66.342363 | Y46: 68.562082 | Z46: 0.22728 | AA46: 0.22635382 | AD46: Hours calc for monthly claims | AE46: -86.75 | AH46: -86.75 | AI46: -15639.05
C47: Week 1 | D47: 65693.36 | E47: 25322.07 | F47: 40371.29 | G47: 0.61454141 | H47: 50582.37 | I47: 21491.46 | J47: 39438.99 | K47: 16895.88 | L47: 22543.11 | M47: 0.57159451 | O47: 11143.38 | P47: 4595.58 | Q47: 6547.8 | R47: 0.58759551 | S47: 223.22 | T47: 100.25 | U47: 122.97 | V47: 0.5508915 | X47: 38.210574 | Y47: 67.695505 | Z47: 0.1513 | AA47: 0.23 | AD47: Materials calc for monthly claims | AE47: -15639.05
C48: Week 2 | D48: 65693.36 | E48: 25322.07 | F48: 40371.29 | G48: 0.61454141 | H48: 50582.37 | I48: 25131.9 | J48: 39438.99 | K48: 20456.64 | L48: 18982.35 | M48: 0.48130923 | O48: 11143.38 | P48: 4675.26 | Q48: 6468.12 | R48: 0.58044507 | S48: 223.22 | T48: 102.25 | U48: 120.97 | V48: 0.54193173 | X48: 1.8598533 | Y48: 67.695505 | Z48: 0.0075 | AA48: 0.23
C49: Week 3 | AD49: Estimated months claim | AE49: 0
C50: Week 4
C51: Week 5 | AH51: -86.75 | AI51: -15639.05
A53: 8670 | B53: Studio DB - tautara fit out | C53: Start of month | D53: 150152.16 | E53: 98562.5 | F53: 51589.66 | G53: 0.34358254 | H53: 105626.39 | I53: 79936.19 | J53: 72224.17 | K53: 66399.88 | L53: 5824.29 | M53: 0.080641841 | O53: 33402.22 | P53: 13536.31 | Q53: 19865.91 | R53: 0.59474819 | S53: 668.92 | T53: 269 | U53: 399.92 | V53: 0.59785924 | W53: 0.3 | X53: 69.242788 | Y53: 66.56367 | Z53: 0.18897968 | AA53: 0.29653766 | AD53: Hours calc for monthly claims | AE53: -269 | AH53: -269 | AI53: -66399.88
C54: Week 1 | D54: 154527.79 | E54: 98562.5 | F54: 55965.29 | G54: 0.36216974 | H54: 108880.28 | I54: 91409.03 | J54: 74953.01 | K54: 72957.27 | L54: 1995.74 | M54: 0.026626549 | O54: 33927.27 | P54: 18451.76 | Q54: 15475.51 | R54: 0.45613779 | S54: 679.42 | T54: 386.5 | U54: 292.92 | V54: 0.43113244 | X54: 18.508331 | Y54: 67.186001 | Z54: 0.0726 | AA54: 0.2954 | AD54: Materials calc for monthly claims | AE54: -66399.88
C55: Week 2 | D55: 154527.79 | E55: 98562.5 | F55: 55965.29 | G55: 0.36216974 | H55: 108880.28 | I55: 90918.83 | J55: 74953.01 | K55: 71302.07 | L55: 3650.94 | M55: 0.048709718 | O55: 33927.27 | P55: 19616.76 | Q55: 14310.51 | R55: 0.42179963 | S55: 679.42 | T55: 413 | U55: 266.42 | V55: 0.39212858 | X55: 18.507676 | Y55: 67.186001 | Z55: 0.0776 | AA55: 0.2954
C56: Week 3 | AD56: Estimated months claim | AE56: 0
C57: Week 4
C58: Week 5 | AH58: -269 | AI58: -66399.88
A60: 8907 | B60: 35 Mania | C60: Start of month | D60: 20420.56 | E60: 16358.37 | F60: 4062.19 | G60: 0.19892647 | H60: 15859.68 | I60: 12193.17 | J60: 12689.1 | K60: 11159.14 | L60: 1529.96 | M60: 0.12057278 | O60: 3170.58 | P60: 1034.03 | Q60: 2136.55 | R60: 0.67386724 | S60: 63.5 | T60: 26.75 | U60: 36.75 | V60: 0.57874016 | W60: 0.4 | X60: 155.70841 | Y60: 71.824882 | Z60: 0.25462195 | AA60: 0.22334745 | AD60: Hours calc for monthly claims | AE60: -26.75 | AH60: -26.75 | AI60: -11159.14
C61: Week 1 | D61: 20420.56 | E61: 16358.37 | F61: 4062.19 | G61: 0.19892647 | H61: 15859.68 | I61: 12992.52 | J61: 12689.1 | K61: 11685.13 | L61: 1003.97 | M61: 0.079120663 | O61: 3170.58 | P61: 1307.39 | Q61: 1863.19 | R61: 0.58764958 | S61: 63.5 | T61: 33.25 | U61: 30.25 | V61: 0.47637795 | X61: 101.22857 | Y61: 71.824956 | Z61: 0.2058 | AA61: 0.2233 | AD61: Materials calc for monthly claims | AE61: -11159.14
C62: Week 2 | D62: 20420.56 | E62: 16358.37 | F62: 4062.19 | G62: 0.19892647 | H62: 15859.68 | I62: 13601.05 | J62: 12689.1 | K62: 11685.13 | L62: 1003.97 | M62: 0.079120663 | O62: 3170.58 | P62: 1915.92 | Q62: 1254.66 | R62: 0.3957194 | S62: 63.5 | T62: 47.5 | U62: 16 | V62: 0.2519685 | X62: 58.048842 | Y62: 71.824956 | Z62: 0.1686 | AA62: 0.2233
C63: Week 3 | AD63: Estimated months claim | AE63: 0
C64: Week 4
C65: Week 5 | AH65: -26.75 | AI65: -11159.14
A67: 9065 | B67: Cooltranz stage 4 | C67: Start of month | D67: 46303.5 | E67: 6131.46 | F67: 40172.04 | G67: 0.86758107 | H67: 34612.41 | I67: 5397.27 | J67: 26584.53 | K67: 5397.27 | L67: 21187.26 | M67: 0.79697704 | O67: 8027.88 | P67: 0 | Q67: 8027.88 | R67: 1 | S67: 160.82 | T67: 0 | U67: 160.82 | V67: 1 | Y67: 72.696742 | Z67: 0.11974146 | AA67: 0.25248826 | AD67: Hours calc for monthly claims | AI67: -5397.27
C68: Week 1 | D68: 46303.5 | E68: 6131.46 | F68: 40172.04 | G68: 0.86758107 | H68: 34612.41 | I68: 9981.43 | J68: 26584.53 | K68: 9832.65 | L68: 16751.88 | M68: 0.6301364 | O68: 8027.88 | P68: 148.78 | Q68: 7879.1 | R68: 0.98146709 | S68: 160.82 | T68: 2.75 | U68: 158.07 | V68: 0.98290014 | X68: -1399.9891 | Y68: 72.696763 | Z68: -0.6279 | AA68: 0.2525 | AD68: Materials calc for monthly claims | AE68: -5397.27
C69: Week 2
C70: Week 3 | AD70: Estimated months claim | AE70: 0
C71: Week 4
C72: Week 5 | AI72: -5397.27
A74: 9259 | B74: Andrew Reeve Stage 2 | C74: Start of month | W74: 0 | AD74: Hours calc for monthly claims
C75: Week 1 | D75: 77166.16 | E75: 0 | F75: 77166.16 | G75: 1 | H75: 54302.66 | I75: 12474.95 | J75: 31383.39 | K75: 12474.95 | L75: 18908.44 | M75: 0.60249833 | O75: 22919.27 | P75: 0 | Q75: 22919.27 | R75: 1 | S75: 470.62 | T75: 0 | U75: 470.62 | V75: 1 | X75: 0 | Y75: 48.58166 | Z75: 0 | AA75: 0.2963 | AD75: Materials calc for monthly claims
C76: Week 2 | D76: 77166.16 | E76: 0 | F76: 77166.16 | G76: 1 | H76: 54302.66 | I76: 22353.17 | J76: 31383.39 | K76: 22353.17 | L76: 9030.22 | M76: 0.28773883 | O76: 22919.27 | P76: 0 | Q76: 22919.27 | R76: 1 | S76: 470.62 | T76: 0 | U76: 470.62 | V76: 1 | X76: 0 | Y76: 48.58166 | Z76: 0 | AA76: 0.2963
C77: Week 3 | AD77: Estimated months claim | AE77: 0
C78: Week 4
C79: Week 5
A81: 8352 | B81: 5 Sanscrit Place | C81: Start of month | D81: 25467.84 | E81: 19598.41 | F81: 5869.43 | G81: 0.23046438 | H81: 16606.83 | I81: 12921.64 | J81: 9659.99 | K81: 5569.48 | L81: 4090.51 | M81: 0.42344868 | N81: 0 | O81: 6946.84 | P81: 7352.16 | Q81: -405.32 | R81: -0.058345953 | S81: 139.07 | T81: 143.25 | U81: -4.18 | V81: -0.030056806 | X81: 46.609215 | Y81: 63.716186 | Z81: 0.34067917 | AA81: 0.34792939 | AD81: Hours calc for monthly claims | AE81: -143.25 | AH81: -143.25 | AI81: -5569.48
C82: Week 1 | D82: 25467.84 | E82: 19598.41 | F82: 5869.43 | G82: 0.23046438 | H82: 16606.83 | I82: 12729.14 | J82: 9659.99 | K82: 5354.12 | L82: 4305.87 | M82: 0.4457427 | O82: 6946.84 | P82: 7375.02 | Q82: -428.18 | R82: -0.061636658 | S82: 139.07 | T82: 143.25 | U82: -4.18 | V82: -0.030056806 | X82: 47.953019 | Y82: 63.716216 | Z82: 0.3505 | AA82: 0.3479 | AD82: Materials calc for monthly claims | AE82: -5569.48
C83: Week 2
C84: Week 3 | AD84: Estimated months claim | AE84: 0
C85: Week 4
C86: Week 5 | AH86: -143.25 | AI86: -5569.48
A88: 8234 | B88: Melhuish House | C88: Start of month | D88: 37083.03 | E88: 33023.07 | F88: 4059.96 | G88: 0.10948296 | H88: 27002.93 | I88: 21520.62 | J88: 15440.32 | K88: 14143.19 | L88: 1297.13 | M88: 0.084009269 | N88: 0 | O88: 11562.61 | P88: 7377.43 | Q88: 4185.18 | R88: 0.36195807 | S88: 231.75 | T88: 148.5 | U88: 83.25 | V88: 0.3592233 | X88: 77.457576 | Y88: 43.495577 | Z88: 0.34831559 | AA88: 0.27182514 | AD88: Hours calc for monthly claims | AE88: -148.5 | AH88: -148.5 | AI88: -14143.19
C89: Week 1 | D89: 37083.03 | E89: 33023.07 | F89: 4059.96 | G89: 0.10948296 | H89: 27002.93 | I89: 25023.81 | J89: 15440.32 | K89: 15309.99 | L89: 130.33 | M89: 0.0084408872 | O89: 11562.61 | P89: 9713.82 | Q89: 1848.79 | R89: 0.15989383 | S89: 231.75 | T89: 198.75 | U89: 33 | V89: 0.14239482 | X89: 40.247849 | Y89: 43.495571 | Z89: 0.2422 | AA89: 0.2718 | AD89: Materials calc for monthly claims | AE89: -14143.19
C90: Week 2 | D90: 37083.03 | E90: 33023.07 | F90: 4059.96 | G90: 0.10948296 | H90: 27002.93 | I90: 25996.77 | J90: 15440.32 | K90: 15990.78 | L90: -550.46 | M90: -0.035650816 | O90: 11562.61 | P90: 10005.99 | Q90: 1556.62 | R90: 0.13462531 | S90: 231.75 | T90: 204.75 | U90: 27 | V90: 0.11650485 | X90: 34.316484 | Y90: 43.495571 | Z90: 0.2128 | AA90: 0.2718
C91: Week 3 | AD91: Estimated months claim | AE91: 0
C92: Week 4
C93: Week 5 | AH93: -148.5 | AI93: -14143.19
A95: 8214 | B95: 6 Tiroroa Lane | C95: Start of month | D95: 26186.14 | E95: 5762.27 | F95: 20423.87 | G95: 0.77994962 | H95: 19428.98 | I95: 7925.81 | J95: 12051.32 | K95: 7679.91 | L95: 4371.41 | M95: 0.36273288 | N95: 0 | O95: 7377.66 | P95: 245.9 | Q95: 7131.76 | R95: 0.96666965 | S95: 147.9 | T95: 5 | U95: 142.9 | V95: 0.96619337 | X95: -432.708 | Y95: 45.687356 | Z95: -0.37546661 | AA95: 0.25804338 | AD95: Hours calc for monthly claims | AE95: -5 | AH95: -5 | AI95: -7679.91
C96: Week 1 | AD96: Materials calc for monthly claims | AE96: -7679.91
C97: Week 2
C98: Week 3 | AD98: Estimated months claim | AE98: 0
C99: Week 4
C100: Week 5 | AH100: -5 | AI100: -7679.91
A102: 6792 | B102: Major Hornbrook | C102: Start of month | D102: 33188.02 | E102: 33188.03 | F102: -0.01 | G102: -3.0131355e-07 | H102: 23790.07 | I102: 32303.46 | J102: 13406.21 | K102: 16562.52 | L102: -3156.31 | M102: -0.23543641 | N102: 0 | O102: 10383.86 | P102: 15740.94 | Q102: -5357.08 | R102: -0.51590449 | S102: 208.2 | T102: 317.25 | U102: -109.05 | V102: -0.52377522 | X102: 2.7882427 | Y102: 45.139049 | Z102: 0.026653284 | AA102: 0.28317296 | AD102: Hours calc for monthly claims | AE102: -317.25 | AH102: -317.25 | AI102: -16562.52
C103: Week 1 | D103: 32473.02 | E103: 33188.03 | F103: -715.01 | G103: -0.022018587 | H103: 23075.07 | I103: 30946.57 | J103: 12691.21 | K103: 15205.63 | L103: -2514.42 | M103: -0.19812295 | O103: 10383.86 | P103: 15740.94 | Q103: -5357.08 | R103: -0.51590449 | S103: 208.2 | T103: 317.25 | U103: -109.05 | V103: -0.52377522 | X103: 7.0652797 | Y103: 45.139085 | Z103: 0.0675 | AA103: 0.2894 | AD103: Materials calc for monthly claims | AE103: -16562.52
C104: Week 2 | D104: 32473.02 | E104: 33188.03 | F104: -715.01 | G104: -0.022018587 | H104: 23075.07 | I104: 31131.57 | J104: 12691.21 | K104: 15390.63 | L104: -2699.42 | M104: -0.21269997 | O104: 10383.86 | P104: 15740.94 | Q104: -5357.08 | R104: -0.51590449 | S104: 208.2 | T104: 317.25 | U104: -109.05 | V104: -0.52377522 | X104: 6.4821434 | Y104: 45.139085 | Z104: 0.062 | AA104: 0.2894
C105: Week 3 | AD105: Estimated months claim | AE105: 0
C106: Week 4
C107: Week 5 | AH107: -317.25 | AI107: -16562.52
A109: 8840 | B109: Inline Architecture | C109: Start of month | D109: 56556.55 | E109: 35454.43 | F109: 21102.12 | G109: 0.3731154 | H109: 35959.67 | I109: 21861.72 | J109: 20162.34 | K109: 12155.27 | L109: 8007.07 | M109: 0.39713 | N109: 0 | O109: 15797.33 | P109: 9706.45 | Q109: 6090.88 | R109: 0.38556389 | S109: 316.34 | T109: 204.75 | U109: 111.59 | V109: 0.35275337 | W109: 0 | X109: 66.386862 | Y109: 65.109945 | Z109: 0.38338538 | AA109: 0.36418204 | AD109: Hours calc for monthly claims | AE109: -204.75 | AH109: -204.75 | AI109: -12155.27
C110: Week 1 | D110: 58902.56 | E110: 0 | F110: 58902.56 | G110: 1 | H110: 37601.88 | I110: 34106.92 | J110: 21415.85 | K110: 18299.73 | L110: 3116.12 | M110: 0.14550531 | O110: 16186.03 | P110: 15807.19 | Q110: 378.84 | R110: 0.023405369 | S110: 324.19 | T110: 342.25 | U110: -18.06 | V110: -0.055708072 | X110: 3.9372096 | Y110: 65.704314 | Z110: 0.038 | AA110: 0.3616 | AD110: Materials calc for monthly claims | AE110: -12155.27
C111: Week 2 | D111: 58902.56 | E111: 0 | F111: 58902.56 | G111: 1 | H111: 37601.88 | I111: 38195.76 | J111: 21415.85 | K111: 19158.27 | L111: 2257.58 | M111: 0.10541632 | O111: 16186.03 | P111: 19037.49 | Q111: -2851.46 | R111: -0.17616797 | S111: 324.19 | T111: 412.5 | U111: -88.31 | V111: -0.27240199 | X111: -6.6456485 | Y111: 65.704314 | Z111: -0.0773 | AA111: 0.3616
C112: Week 3 | AD112: Estimated months claim | AE112: 0
C113: Week 4
C114: Week 5 | AH114: -204.75 | AI114: -12155.27
A116: 8769 | B116: Percival Bach | C116: Start of month | D116: 0 | E116: 0 | F116: 0 | H116: 0 | I116: 0 | N116: 0 | O116: 0 | P116: 0 | S116: 0 | T116: 0 | W116: 0 | AD116: Hours calc for monthly claims
...

Sheet Claim Calculator By Month
A1: Updated Job Spreadsheet
A2: Job Number | B2: Job Name | C2: Claim | D2: Costs | E2: Profit | F2: Retention | G2: Margin | H2: Quoted Margin | I2: Hours to complete before E.O.M | J2: Costs to come before E.O.M | K2: Total cost to come before E.O.M | L2: Estimated margin E.O.M | M2: GP End of month | N2: Hours this month | O2: GP $ per hour this month
A4: ='Main Sheet'!A4 -> 7658 | B4: ='Main Sheet'!B4 -> Charity Hospital | C4: 0 | D4: 51687.05 | E4: =C4-D4 -> 9727.83 | F4: 0 | G4: =(E4+F4)/C4 -> 0.4863915 | H4: 0.2149 | I4: 0 | J4: 90 | K4: =(I4*40)+J4 -> 90 | L4: =((E4-K4)+F4)/C4 -> 0.4818915 | M4: =SUM(E4:F4)-K4 -> 9637.83 | N4: 20 | O4: =SUM(M4/(N4+I4)) -> 481.8915
A6: ='Main Sheet'!A6 -> 8142 | B6: ='Main Sheet'!B6 -> Fisher Developements | C6: 3912 | D6: 6513.39 | E6: =C6-D6 -> -3968.93 | F6: 0 | G6: =(E6+F6)/C6 -> #DIV/0! | H6: ='Deliverables Sheet'!AA11 -> 0.23921459 | I6: 16 | J6: 272.6 | K6: =(I6*40)+J6 -> 912.6 | L6: =((E6-K6)+F6)/C6 -> #DIV/0! | M6: =SUM(E6:F6)-K6 -> -4881.53 | N6: ='Deliverables Sheet'!AE11 -> -52.5 | O6: =SUM(M6/(N6+I6)) -> 133.74055 | Q6: 14 Mirrors and 49 Downlights have been ordered
A8: ='Main Sheet'!A8 -> 8824 | B8: ='Main Sheet'!B8 -> 3 Innovation Road | C8: 0 | D8: 0 | E8: =C8-D8 -> 2227.16 | G8: =(E8+F8)/C8 -> 0.31820754 | H8: ='Deliverables Sheet'!AA18 -> 0.28852355 | I8: 16 | K8: =(I8*40)+J8 -> 640 | L8: =((E8-K8)+F8)/C8 -> 0.22676695 | M8: =SUM(E8:F8)-K8 -> 1587.16 | N8: ='Deliverables Sheet'!AE18 -> -34.75 | O8: =SUM(M8/(N8+I8)) -> -84.648533
A10: ='Main Sheet'!A10 -> 8127 | B10: ='Main Sheet'!B10 -> Rolly Autowash | C10: 0 | D10: 5315.24 | E10: =C10-D10 -> 19246.78 | F10: 0 | G10: =(E10+F10)/C10 -> 0.36157089 | H10: ='Deliverables Sheet'!AA25 -> 0.32265254 | I10: 48 | J10: 3000 | K10: 1000 | L10: =((E10-K10)+F10)/C10 -> 0.34278484 | M10: =SUM(E10:F10)-K10 -> 18246.78 | N10: ='Deliverables Sheet'!AE25 -> -388.25 | O10: =SUM(M10/(N10+I10)) -> -53.627568
A12: 8183 | B12: Murney Custodian - 1 Freight Drive | C12: 0 | D12: 1154.65 | E12: =C12-D12 -> 7144.34 | G12: =(E12+F12)/C12 -> 0.35107322 | H12: ='Deliverables Sheet'!AA32 -> 0.17631626 | I12: 16 | J12: 2000 | K12: =(I12*40)+J12 -> 2640 | L12: =((E12-K12)+F12)/C12 -> 0.22134349 | M12: =SUM(E12:F12)-K12 -> 4504.34 | N12: 53 | O12: =SUM(M12/(N12+I12)) -> 65.28029 | Q12: Couldnt get this rite because of ers but they re claiming 30%
A14: ='Main Sheet'!A14 -> 8886 | B14: ='Main Sheet'!B14 -> Monkey Toe - Fisher fit out | C14: 0 | D14: 2138.16 | E14: =C14-D14 -> 3415.11 | F14: 0 | G14: =(E14+F14)/C14 -> 0.3381297 | H14: ='Deliverables Sheet'!AA39 -> 0.26633853 | I14: 0 | J14: 3000 | K14: 0 | L14: =((E14-K14)+F14)/C14 -> 0.3381297 | M14: =SUM(E14:F14)-K14 -> 3415.11 | N14: ='Deliverables Sheet'!AE39 -> -112 | O14: =SUM(M14/(N14+I14)) -> -30.492054
A16: ='Main Sheet'!A16 -> 8887 | B16: ='Main Sheet'!B16 -> Tenancy 2 - Fisher Fit out | C16: 0 | D16: 5565.03 | E16: =C16-D16 -> 5660 | G16: =(E16+F16)/C16 -> 0.53904762 | H16: ='Deliverables Sheet'!AA46 -> 0.22635382 | I16: 0 | J16: 3000 | K16: =(I16*40)+J16 -> 3000 | L16: =((E16-K16)+F16)/C16 -> 0.25333333 | M16: =SUM(E16:F16)-K16 -> 2660 | N16: ='Deliverables Sheet'!AE46 -> -86.75 | O16: =SUM(M16/(N16+I16)) -> -30.662824
A18: ='Main Sheet'!A18 -> 8670 | B18: ='Main Sheet'!B18 -> Studio DB - tautara fit out | C18: 0 | D18: 10982.64 | E18: =C18-D18 -> 16075.1 | F18: 0 | G18: =(E18+F18)/C18 -> 0.43257869 | H18: ='Deliverables Sheet'!AA53 -> 0.29653766 | I18: 80 | J18: 5000 | K18: =(I18*40)+J18 -> 8200 | L18: =((E18-K18)+F18)/C18 -> 0.21191784 | M18: =SUM(E18:F18)-K18 -> 7875.1 | N18: ='Deliverables Sheet'!AE53 -> -269 | O18: =SUM(M18/(N18+I18)) -> -41.667196 | Q18: 48 Hours need to be made non Billable
A20: ='Main Sheet'!A20 -> 8907 | B20: ='Main Sheet'!B20 -> 35 Mania | C20: 0 | D20: 1407.88 | E20: =C20-D20 -> 0 | G20: =(E20+F20)/C20 -> #DIV/0! | H20: ='Deliverables Sheet'!AA60 -> 0.22334745 | K20: =(I20*40)+J20 -> 0 | L20: =((E20-K20)+F20)/C20 -> #DIV/0! | M20: =SUM(E20:F20)-K20 -> 0 | O20: =SUM(M20/(N20+I20)) -> #DIV/0!
A22: ='Main Sheet'!A22 -> 9065 | B22: ='Main Sheet'!B22 -> Cooltranz stage 4 | C22: 0 | D22: 4584.16 | E22: =C22-D22 -> 0 | F22: 0 | G22: =(E22+F22)/C22 -> #DIV/0! | H22: ='Deliverables Sheet'!AA67 -> 0.25248826 | K22: =(I22*40)+J22 -> 0 | L22: =((E22-K22)+F22)/C22 -> #DIV/0! | M22: =SUM(E22:F22)-K22 -> 0 | N22: ='Deliverables Sheet'!AE67 -> 0 | O22: =SUM(M22/(N22+I22)) -> #DIV/0!
A24: ='Main Sheet'!A24 -> 9259 | B24: ='Main Sheet'!B24 -> Andrew Reeve Stage 2 | C24: 0 | D24: 22353.17 | E24: =C24-D24 -> 0 | G24: =(E24+F24)/C24 -> #DIV/0! | H24: ='Deliverables Sheet'!AA74 -> #DIV/0! | K24: =(I24*40)+J24 -> 0 | L24: =((E24-K24)+F24)/C24 -> #DIV/0! | M24: =SUM(E24:F24)-K24 -> 0 | N24: ='Deliverables Sheet'!AE74 -> 0 | O24: =SUM(M24/(N24+I24)) -> #DIV/0!
A26: ='Main Sheet'!A26 -> 8352 | B26: ='Main Sheet'!B26 -> 5 Sanscrit Place | C26: 0 | D26: -192.5 | E26: =C26-D26 -> 0 | F26: 0 | G26: =(E26+F26)/C26 -> #DIV/0! | H26: ='Deliverables Sheet'!AA81 -> 0.34792939 | J26: 0 | K26: =(I26*40)+J26 -> 0 | L26: =((E26-K26)+F26)/C26 -> #DIV/0! | M26: =SUM(E26:F26)-K26 -> 0 | N26: ='Deliverables Sheet'!AE81 -> -143.25 | O26: =SUM(M26/(N26+I26)) -> 0
A28: ='Main Sheet'!A28 -> 8234 | B28: ='Main Sheet'!B28 -> Melhuish House | C28: 0 | D28: 4476.15 | E28: =C28-D28 -> 2313.69 | F28: 0 | G28: =(E28+F28)/C28 -> 0.34629131 | H28: ='Deliverables Sheet'!AA88 -> 0.27182514 | K28: =(I28*40)+J28 -> 0 | L28: =((E28-K28)+F28)/C28 -> 0.34629131 | M28: =SUM(E28:F28)-K28 -> 2313.69 | N28: ='Deliverables Sheet'!AE88 -> -148.5 | O28: =SUM(M28/(N28+I28)) -> -15.580404
A30: ='Main Sheet'!A30 -> 8214 | B30: ='Main Sheet'!B30 -> 6 Tiroroa Lane | C30: 0 | D30: 0 | E30: =C30-D30 -> 0 | F30: 0 | G30: =(E30+F30)/C30 -> #DIV/0! | H30: ='Deliverables Sheet'!AA95 -> 0.25804338 | K30: =(I30*40)+J30 -> 0 | L30: =((E30-K30)+F30)/C30 -> #DIV/0! | M30: =SUM(E30:F30)-K30 -> 0 | N30: ='Deliverables Sheet'!AE95 -> -5 | O30: =SUM(M30/(N30+I30)) -> 0
A32: ='Main Sheet'!A32 -> 6792 | B32: ='Main Sheet'!B32 -> Major Hornbrook | C32: 0 | D32: -1171.89 | E32: =C32-D32 -> 4327.53 | F32: 0 | G32: =(E32+F32)/C32 -> 0.6924048 | H32: ='Deliverables Sheet'!AA102 -> 0.28317296 | I32: 64 | J32: 0 | K32: =(I32*40)+J32 -> 2560 | L32: =((E32-K32)+F32)/C32 -> 0.2828048 | M32: =SUM(E32:F32)-K32 -> 1767.53 | N32: ='Deliverables Sheet'!AE102 -> -317.25 | O32: =SUM(M32/(N32+I32)) -> -6.979388
A34: ='Main Sheet'!A34 -> 8840 | B34: ='Main Sheet'!B34 -> Inline Architecture | C34: -35454.43 | D34: 16334.04 | E34: =C34-D34 -> 0 | F34: 0 | G34: =(E34+F34)/C34 -> #DIV/0! | H34: ='Deliverables Sheet'!AA109 -> 0.36418204 | J34: 0 | K34: =(I34*40)+J34 -> 0 | L34: =((E34-K34)+F34)/C34 -> #DIV/0! | M34: =SUM(E34:F34)-K34 -> 0 | N34: ='Deliverables Sheet'!AE109 -> -204.75 | O34: =SUM(M34/(N34+I34)) -> 0
A36: ='Main Sheet'!A36 -> 8769 | B36: ='Main Sheet'!B36 -> Percival Bach | C36: 0 | D36: 0 | E36: =C36-D36 -> 10702.1 | F36: 0 | G36: =(E36+F36)/C36 -> 0.49473237 | H36: ='Deliverables Sheet'!AA116 -> #DIV/0! | I36: 80 | J36: 0 | K36: =(I36*40)+J36 -> 3200 | L36: =((E36-K36)+F36)/C36 -> 0.34680406 | M36: =SUM(E36:F36)-K36 -> 7502.1 | N36: ='Deliverables Sheet'!AE116 -> 0 | O36: =SUM(M36/(N36+I36)) -> 93.77625
A38: ='Main Sheet'!A38 -> 7901 | B38: ='Main Sheet'!B38 -> St Albans Street | C38: 0 | D38: 6365.78 | E38: =C38-D38 -> 0 | F38: 0 | G38: =(E38+F38)/C38 -> #DIV/0! | H38: ='Deliverables Sheet'!AA123 -> 0.17509217 | K38: =(I38*40)+J38 -> 0 | L38: =((E38-K38)+F38)/C38 -> #DIV/0! | M38: =SUM(E38:F38)-K38 -> 0 | N38: ='Deliverables Sheet'!AE123 -> 0 | O38: =SUM(M38/(N38+I38)) -> #DIV/0!
A40: ='Main Sheet'!A40 -> 8923 | B40: ='Main Sheet'!B40 -> 4 Perry St | C40: 0 | D40: 0 | E40: =C40-D40 -> 0 | F40: 0 | G40: =(E40+F40)/C40 -> #DIV/0! | H40: ='Deliverables Sheet'!AA130 -> 0.26269298 | J40: 0 | K40: =(I40*40)+J40 -> 0 | L40: =((E40-K40)+F40)/C40 -> #DIV/0! | M40: =SUM(E40:F40)-K40 -> 0 | N40: ='Deliverables Sheet'!AE130 -> -2 | O40: =SUM(M40/(N40+I40)) -> 0
A42: ='Main Sheet'!A42 -> 7864 | B42: ='Main Sheet'!B42 -> Ryans House | C42: 3554.3 | D42: 584.89 | E42: =C42-D42 -> -106.2 | G42: =(E42+F42)/C42 -> -0.015830191 | H42: ='Deliverables Sheet'!AA137 -> 0.25724571 | I42: 0 | K42: =(I42*40)+J42 -> 0 | L42: =((E42-K42)+F42)/C42 -> -0.015830191 | M42: =SUM(E42:F42)-K42 -> -106.2 | N42: ='Deliverables Sheet'!AE137 -> -266.75 | O42: =SUM(M42/(N42+I42)) -> 0.39812559
A44: ='Main Sheet'!A44 -> 7912 | B44: ='Main Sheet'!B44 -> 71A Fendalton Road | C44: 9034.53 | D44: 6362.08 | E44: =C44-D44 -> 1991.31 | G44: =(E44+F44)/C44 -> 0.31224921 | H44: ='Deliverables Sheet'!AA144 -> #DIV/0! | K44: =(I44*40)+J44 -> 0 | L44: =((E44-K44)+F44)/C44 -> 0.31224921 | M44: =SUM(E44:F44)-K44 -> 1991.31 | N44: ='Deliverables Sheet'!AE144 -> 0 | O44: =SUM(M44/(N44+I44)) -> #DIV/0!
A46: ='Main Sheet'!A46 -> 8360 | B46: ='Main Sheet'!B46 -> Dixon House | C46: 0 | D46: 15.49 | E46: =C46-D46 -> 651.41 | G46: =(E46+F46)/C46 -> 0.12799574 | H46: ='Deliverables Sheet'!AA151 -> 0.3058095 | K46: =(I46*40)+J46 -> 0 | L46: =((E46-K46)+F46)/C46 -> 0.12799574 | M46: =SUM(E46:F46)-K46 -> 651.41 | N46: ='Deliverables Sheet'!AE151 -> -260.75 | O46: =SUM(M46/(N46+I46)) -> -2.4982167
A48: ='Main Sheet'!A48 -> 8337 | B48: ='Main Sheet'!B48 -> Waimak Dairys | C48: 13424.5 | D48: 2862.01 | E48: =C48-D48 -> 5862.4 | G48: =(E48+F48)/C48 -> 0.4366941 | H48: ='Deliverables Sheet'!AA158 -> 0.22235078 | J48: 2530 | K48: =(I48*40)+J48 -> 2530 | L48: =((E48-K48)+F48)/C48 -> 0.24823271 | M48: =SUM(E48:F48)-K48 -> 3332.4 | N48: ='Deliverables Sheet'!AE158 -> -44.75 | O48: =SUM(M48/(N48+I48)) -> -74.467039
A50: ='Main Sheet'!A50 -> 9240 | B50: ='Main Sheet'!B50 -> Daves Twizel Shack | C50: 0 | D50: 0 | E50: =C50-D50 -> 0 | G50: =(E50+F50)/C50 -> #DIV/0! | H50: ='Deliverables Sheet'!AA165 -> #DIV/0! | I50: 0 | K50: =(I50*40)+J50 -> 0 | L50: =((E50-K50)+F50)/C50 -> #DIV/0! | M50: =SUM(E50:F50)-K50 -> 0 | N50: ='Deliverables Sheet'!AE165 -> 0 | O50: =SUM(M50/(N50+I50)) -> #DIV/0! | Q50: $18627.12 from Sharp Electrical
A52: ='Main Sheet'!A52 -> 7428 | B52: ='Main Sheet'!B52 -> FAB Pegasus Lakeside | C52: 0 | D52: 20350.28 | E52: =C52-D52 -> 2683.58 | G52: =(E52+F52)/C52 -> 0.5707134 | H52: ='Deliverables Sheet'!AA172 -> 0.21598649 | I52: 32 | J52: 0 | K52: =(I52*40)+J52 -> 1280 | L52: =((E52-K52)+F52)/C52 -> 0.2984975 | M52: =SUM(E52:F52)-K52 -> 1403.58 | N52: ='Deliverables Sheet'!AE172 -> -304.75 | O52: =SUM(M52/(N52+I52)) -> -5.1460312
A54: ='Main Sheet'!A54 -> 9351 | B54: ='Main Sheet'!B54 -> Harewood Golf Club | C54: 5491.7 | D54: 756.63 | E54: =C54-D54 -> 2545.55 | G54: =(E54+F54)/C54 -> 0.46352678 | H54: ='Deliverables Sheet'!AA179 -> 0.45398706 | I54: 16 | J54: 0 | K54: =(I54*40)+J54 -> 640 | L54: =((E54-K54)+F54)/C54 -> 0.34698727 | M54: =SUM(E54:F54)-K54 -> 1905.55 | N54: ='Deliverables Sheet'!AE179 -> -11.25 | O54: =SUM(M54/(N54+I54)) -> 401.16842
A56: ='Main Sheet'!A56 -> 7429 | B56: ='Main Sheet'!B56 -> Taggart House | C56: 12937.1 | D56: 4850.19 | E56: =C56-D56 -> 9059.83 | G56: =(E56+F56)/C56 -> 0.70029837 | H56: ='Deliverables Sheet'!AA186 -> 0.22356151 | I56: 10 | J56: 5000 | K56: =(I56*40)+J56 -> 5400 | L56: =((E56-K56)+F56)/C56 -> 0.28289416 | M56: =SUM(E56:F56)-K56 -> 3659.83 | N56: ='Deliverables Sheet'!AE186 -> -32.25 | O56: =SUM(M56/(N56+I56)) -> -164.48674
A58: ='Main Sheet'!A58 -> 9508 | B58: ='Main Sheet'!B58 -> St Barnabas Church | C58: 0 | D58: 7180.07 | E58: =C58-D58 -> 0 | G58: =(E58+F58)/C58 -> #DIV/0! | H58: ='Deliverables Sheet'!AA193 -> #DIV/0! | K58: =(I58*40)+J58 -> 0 | L58: =((E58-K58)+F58)/C58 -> #DIV/0! | M58: =SUM(E58:F58)-K58 -> 0 | N58: ='Deliverables Sheet'!AE193 -> 0 | O58: =SUM(M58/(N58+I58)) -> #DIV/0!
A60: ='Main Sheet'!A60 -> 0 | B60: ='Main Sheet'!B60 -> 0 | E60: =C60-D60 -> 0 | G60: =(E60+F60)/C60 -> #DIV/0! | H60: ='Deliverables Sheet'!AA200 -> #DIV/0! | K60: =(I60*40)+J60 -> 0 | L60: =((E60-K60)+F60)/C60 -> #DIV/0! | M60: =SUM(E60:F60)-K60 -> 0 | N60: ='Deliverables Sheet'!AE200 -> 0 | O60: =SUM(M60/(N60+I60)) -> #DIV/0!
A62: ='Main Sheet'!A62 -> 0 | B62: ='Main Sheet'!B62 -> Contracting | E62: =C62-D62 -> 0 | G62: =(E62+F62)/C62 -> #DIV/0! | H62: ='Deliverables Sheet'!AA207 -> #DIV/0! | I62: 0 | K62: =(I62*40)+J62 -> 0 | L62: =((E62-K62)+F62)/C62 -> #DIV/0! | M62: =SUM(E62:F62)-K62 -> 0 | N62: ='Deliverables Sheet'!AE207 -> 0 | O62: =SUM(M62/(N62+I62)) -> #DIV/0!
A64: ='Main Sheet'!A64 -> 8946 | B64: ='Main Sheet'!B64 -> Westcoast Vaults | C64: 0 | D64: 1749.8 | E64: =C64-D64 -> 0 | G64: =(E64+F64)/C64 -> #DIV/0! | H64: ='Deliverables Sheet'!AA214 -> 0.14379005 | J64: 1750 | K64: =(I64*40)+J64 -> 1750 | L64: =((E64-K64)+F64)/C64 -> #DIV/0! | M64: =SUM(E64:F64)-K64 -> -1750 | N64: ='Deliverables Sheet'!AE214 -> 0 | O64: =SUM(M64/(N64+I64)) -> #DIV/0!
A66: 8308 | B66: ='Main Sheet'!B66 -> Roydvale | C66: 0 | D66: 3855.08 | E66: =C66-D66 -> 11482 | G66: =(E66+F66)/C66 -> 0.37645902 | H66: ='Deliverables Sheet'!AA221 -> 0.25626552 | I66: 80 | J66: 0 | K66: =(I66*40)+J66 -> 3200 | L66: =((E66-K66)+F66)/C66 -> 0.27154098 | M66: =SUM(E66:F66)-K66 -> 8282 | N66: ='Deliverables Sheet'!AE221 -> -1014.25 | O66: =SUM(M66/(N66+I66)) -> -8.8648649
A69: Totals | B69: Commercial | C69: =SUM(C4,C6,C8,C10,C12,C14,C16,C18,C20,C22,C24) -> 158341.18 | D69: =SUM(D4,D6,D8,D10,D12,D14,D16,D18,D20,D22,D24) -> 98813.79 | E69: =SUM(E4,E6,E8,E10,E12,E14,E16,E18,E20,E22,E24) -> 59527.39 | F69: GP% | G69: =SUM(E69/C69) -> 0.37594383 | H69: E.O.M GP% | I69: =(E69-(K4+K6+K8+K10+K12+K14+K16+K18+K20+K22+K24))/C69 -> 0.27184836
B70: Residential | C70: =SUM(C26,C28,C30,C32,C34,C36,C38,C40,C42,C44,C46) -> 52738.76 | D70: =SUM(D26,D28,D30,D32,D34,D36,D38,D40,D42,D44,D46) -> 32858.92 | E70: =SUM(E26,E28,E30,E32,E34,E36,E38,E40,E42,E44,E46) -> 19879.84 | F70: GP% | G70: =SUM(E70/C70) -> 0.37694933 | H70: E.O.M GP% | I70: =(E70-(K26+K28+K30+K32+K34+K36+K38+K40+K42+K44+K46))/C70 -> 0.26773174

Sheet Upcoming Work Calculator
A1: Updated Job Spreadsheet
B2: Job | C2: Quoted Hours | D2: Hours Used | E2: Hours Remaining | F2: January | G2: February | H2: March | I2: April | J2: May | K2: June | L2: July | M2: August | N2: September | O2: October | P2: November | Q2: December
A3: Servicing | B3: Servicing work any job under 30 hours | F3: 500 | G3: 700 | H3: 700 | I3: 700 | J3: 700 | K3: 700 | L3: 700 | M3: 700 | N3: 700 | O3: 700 | P3: 700 | Q3: 500
A4: ='Main Sheet'!A4 -> 7658 | B4: ='Main Sheet'!B4 -> Charity Hospital | C4: {=LOOKUP(2,1/('Deliverables Sheet'!S4:S9<>0),'Deliverables Sheet'!S4:S9)} -> 530.95 | D4: {=LOOKUP(2,1/('Deliverables Sheet'!T4:T9<>0),'Deliverables Sheet'!T4:T9)} -> 418 | E4: {=LOOKUP(2,1/('Deliverables Sheet'!U4:U9<>0),'Deliverables Sheet'!U4:U9)} -> 112.95 | M4: 80 | S4: Programme Checked 24/03/26
A6: ='Main Sheet'!A6 -> 8142 | B6: ='Main Sheet'!B6 -> Fisher Developements | C6: {=LOOKUP(2,1/('Deliverables Sheet'!S11:S16<>0),'Deliverables Sheet'!S11:S16)} -> 311.89 | D6: {=LOOKUP(2,1/('Deliverables Sheet'!T11:T16<>0),'Deliverables Sheet'!T11:T16)} -> 52.5 | E6: {=LOOKUP(2,1/('Deliverables Sheet'!U11:U16<>0),'Deliverables Sheet'!U11:U16)} -> 259.39 | N6: 80 | S6: Cant find a Programme for this.
A8: ='Main Sheet'!A8 -> 8824 | B8: ='Main Sheet'!B8 -> 3 Innovation Road | C8: {=LOOKUP(2,1/('Deliverables Sheet'!S18:S23<>0),'Deliverables Sheet'!S18:S23)} -> 125.39 | D8: {=LOOKUP(2,1/('Deliverables Sheet'!T18:T23<>0),'Deliverables Sheet'!T18:T23)} -> 34.75 | E8: {=LOOKUP(2,1/('Deliverables Sheet'!U18:U23<>0),'Deliverables Sheet'!U18:U23)} -> 90.64 | N8: 90 | S8: Programme Checked 24/03/26
A10: ='Main Sheet'!A10 -> 8127 | B10: ='Main Sheet'!B10 -> Rolly Autowash | C10: {=LOOKUP(2,1/('Deliverables Sheet'!S25:S30<>0),'Deliverables Sheet'!S25:S30)} -> 795.22 | D10: {=LOOKUP(2,1/('Deliverables Sheet'!T25:T30<>0),'Deliverables Sheet'!T25:T30)} -> 388.25 | E10: {=LOOKUP(2,1/('Deliverables Sheet'!U25:U30<>0),'Deliverables Sheet'!U25:U30)} -> 406.97 | M10: 200 | N10: 80 | S10: Programme Checked 24/03/26
A12: 8183 | B12: Murney Custodian - 1 Freight Drive | C12: ='Deliverables Sheet'!S32 -> 1120.27 | D12: ='Deliverables Sheet'!T32 -> 387.5 | E12: {=LOOKUP(2,1/('Deliverables Sheet'!U32:U37<>0),'Deliverables Sheet'!U32:U37)} -> 732.77 | M12: 160 | N12: 320 | O12: 80 | S12: Programme Checked 24/03/26
A14: ='Main Sheet'!A14 -> 8886 | B14: ='Main Sheet'!B14 -> Monkey Toe - Fisher fit out | C14: ='Deliverables Sheet'!S39 -> 501 | D14: ='Deliverables Sheet'!T39 -> 112 | E14: {=LOOKUP(2,1/('Deliverables Sheet'!U39:U44<>0),'Deliverables Sheet'!U39:U44)} -> 389 | L14: 0 | M14: 80 | N14: 300 | S14: Programme Checked 24/03/26
A16: ='Main Sheet'!A16 -> 8887 | B16: ='Main Sheet'!B16 -> Tenancy 2 - Fisher Fit out | C16: {=LOOKUP(2,1/('Deliverables Sheet'!S46:S51<>0),'Deliverables Sheet'!S46:S51)} -> 212.3 | D16: {=LOOKUP(2,1/('Deliverables Sheet'!T46:T51<>0),'Deliverables Sheet'!T46:T51)} -> 86.75 | E16: {=LOOKUP(2,1/('Deliverables Sheet'!U46:U51<>0),'Deliverables Sheet'!U46:U51)} -> 125.55 | M16: 16 | N16: 110
A18: ='Main Sheet'!A18 -> 8670 | B18: ='Main Sheet'!B18 -> Studio DB - tautara fit out | C18: {=LOOKUP(2,1/('Deliverables Sheet'!S53:S58<>0),'Deliverables Sheet'!S53:S58)} -> 668.92 | D18: {=LOOKUP(2,1/('Deliverables Sheet'!T53:T58<>0),'Deliverables Sheet'!T53:T58)} -> 269 | E18: {=LOOKUP(2,1/('Deliverables Sheet'!U53:U58<>0),'Deliverables Sheet'!U53:U58)} -> 399.92 | M18: 240 | N18: 160
A20: ='Main Sheet'!A20 -> 8907 | B20: ='Main Sheet'!B20 -> 35 Mania | C20: {=LOOKUP(2,1/('Deliverables Sheet'!S60:S65<>0),'Deliverables Sheet'!S60:S65)} -> 63.5 | D20: {=LOOKUP(2,1/('Deliverables Sheet'!T60:T65<>0),'Deliverables Sheet'!T60:T65)} -> 26.75 | E20: {=LOOKUP(2,1/('Deliverables Sheet'!U60:U65<>0),'Deliverables Sheet'!U60:U65)} -> 36.75 | M20: 36
A22: ='Main Sheet'!A22 -> 9065 | B22: ='Main Sheet'!B22 -> Cooltranz stage 4 | C22: {=LOOKUP(2,1/('Deliverables Sheet'!S67:S72<>0),'Deliverables Sheet'!S67:S72)} -> 160.82 | D22: {=LOOKUP(2,1/('Deliverables Sheet'!T67:T72<>0),'Deliverables Sheet'!T67:T72)} -> #N/A | E22: {=LOOKUP(2,1/('Deliverables Sheet'!U67:U72<>0),'Deliverables Sheet'!U67:U72)} -> 160.82 | M22: 20 | N22: 80 | O22: 60
A24: ='Main Sheet'!A24 -> 9259 | B24: ='Main Sheet'!B24 -> Andrew Reeve Stage 2 | E24: {=LOOKUP(2,1/('Deliverables Sheet'!U69:U74<>0),'Deliverables Sheet'!U69:U74)} -> #N/A | M24: 188 | N24: 282
A26: ='Main Sheet'!A26 -> 8352 | B26: ='Main Sheet'!B26 -> 5 Sanscrit Place | C26: {=LOOKUP(2,1/('Deliverables Sheet'!S81:S86<>0),'Deliverables Sheet'!S81:S86)} -> 139.07 | D26: {=LOOKUP(2,1/('Deliverables Sheet'!T81:T86<>0),'Deliverables Sheet'!T81:T86)} -> 143.25 | E26: {=LOOKUP(2,1/('Deliverables Sheet'!U81:U86<>0),'Deliverables Sheet'!U81:U86)} -> -4.18 | M26: 48
A28: ='Main Sheet'!A28 -> 8234 | B28: ='Main Sheet'!B28 -> Melhuish House | C28: {=LOOKUP(2,1/('Deliverables Sheet'!S88:S93<>0),'Deliverables Sheet'!S88:S93)} -> 231.75 | D28: {=LOOKUP(2,1/('Deliverables Sheet'!T88:T93<>0),'Deliverables Sheet'!T88:T93)} -> 148.5 | E28: {=LOOKUP(2,1/('Deliverables Sheet'!U88:U93<>0),'Deliverables Sheet'!U88:U93)} -> 83.25 | M28: 32
A30: ='Main Sheet'!A30 -> 8214 | B30: ='Main Sheet'!B30 -> 6 Tiroroa Lane | C30: {=LOOKUP(2,1/('Deliverables Sheet'!S95:S100<>0),'Deliverables Sheet'!S95:S100)} -> 147.9 | D30: {=LOOKUP(2,1/('Deliverables Sheet'!T95:T100<>0),'Deliverables Sheet'!T95:T100)} -> 5 | E30: {=LOOKUP(2,1/('Deliverables Sheet'!U95:U100<>0),'Deliverables Sheet'!U95:U100)} -> 142.9 | N30: 48 | O30: 16 | P30: 64
A32: ='Main Sheet'!A32 -> 6792 | B32: ='Main Sheet'!B32 -> Major Hornbrook | C32: {=LOOKUP(2,1/('Deliverables Sheet'!S102:S107<>0),'Deliverables Sheet'!S102:S107)} -> 208.2 | D32: {=LOOKUP(2,1/('Deliverables Sheet'!T102:T107<>0),'Deliverables Sheet'!T102:T107)} -> 317.25 | E32: {=LOOKUP(2,1/('Deliverables Sheet'!U102:U107<>0),'Deliverables Sheet'!U102:U107)} -> -109.05
A34: ='Main Sheet'!A34 -> 8840 | B34: ='Main Sheet'!B34 -> Inline Architecture | C34: {=LOOKUP(2,1/('Deliverables Sheet'!S109:S114<>0),'Deliverables Sheet'!S109:S114)} -> 316.34 | D34: {=LOOKUP(2,1/('Deliverables Sheet'!T109:T114<>0),'Deliverables Sheet'!T109:T114)} -> 204.75 | E34: {=LOOKUP(2,1/('Deliverables Sheet'!U109:U114<>0),'Deliverables Sheet'!U109:U114)} -> 111.59 | M34: 130
A36: ='Main Sheet'!A36 -> 8769 | B36: ='Main Sheet'!B36 -> Percival Bach | C36: {=LOOKUP(2,1/('Deliverables Sheet'!S116:S121<>0),'Deliverables Sheet'!S116:S121)} -> #N/A | D36: {=LOOKUP(2,1/('Deliverables Sheet'!T116:T121<>0),'Deliverables Sheet'!T116:T121)} -> #N/A | E36: {=LOOKUP(2,1/('Deliverables Sheet'!U116:U121<>0),'Deliverables Sheet'!U116:U121)} -> #N/A | M36: 30 | N36: 50
A38: ='Main Sheet'!A38 -> 7901 | B38: ='Main Sheet'!B38 -> St Albans Street | C38: {=LOOKUP(2,1/('Deliverables Sheet'!S123:S128<>0),'Deliverables Sheet'!S123:S128)} -> 273.37 | D38: {=LOOKUP(2,1/('Deliverables Sheet'!T123:T128<>0),'Deliverables Sheet'!T123:T128)} -> #N/A | E38: {=LOOKUP(2,1/('Deliverables Sheet'!U123:U128<>0),'Deliverables Sheet'!U123:U128)} -> 273.37 | M38: 80 | N38: 40 | O38: 160
A40: ='Main Sheet'!A40 -> 8923 | B40: ='Main Sheet'!B40 -> 4 Perry St | C40: {=LOOKUP(2,1/('Deliverables Sheet'!S130:S135<>0),'Deliverables Sheet'!S130:S135)} -> 157 | D40: {=LOOKUP(2,1/('Deliverables Sheet'!T130:T135<>0),'Deliverables Sheet'!T130:T135)} -> 2 | E40: {=LOOKUP(2,1/('Deliverables Sheet'!U130:U135<>0),'Deliverables Sheet'!U130:U135)} -> 155 | F40: 60 | G40: 15 | H40: 90
A42: ='Main Sheet'!A42 -> 7864 | B42: ='Main Sheet'!B42 -> Ryans House | C42: {=LOOKUP(2,1/('Deliverables Sheet'!S137:S142<>0),'Deliverables Sheet'!S137:S142)} -> 193.82 | D42: {=LOOKUP(2,1/('Deliverables Sheet'!T137:T142<>0),'Deliverables Sheet'!T137:T142)} -> 266.75 | E42: {=LOOKUP(2,1/('Deliverables Sheet'!U137:U142<>0),'Deliverables Sheet'!U137:U142)} -> -72.93
A44: ='Main Sheet'!A44 -> 7912 | B44: ='Main Sheet'!B44 -> 71A Fendalton Road | C44: {=LOOKUP(2,1/('Deliverables Sheet'!S144:S149<>0),'Deliverables Sheet'!S144:S149)} -> #N/A | D44: {=LOOKUP(2,1/('Deliverables Sheet'!T144:T149<>0),'Deliverables Sheet'!T144:T149)} -> #N/A | E44: {=LOOKUP(2,1/('Deliverables Sheet'!U144:U149<>0),'Deliverables Sheet'!U144:U149)} -> #N/A | F44: 80 | N44: 40 | O44: 300 | P44: 150 | Q44: 150
A46: ='Main Sheet'!A46 -> 8360 | B46: ='Main Sheet'!B46 -> Dixon House | C46: {=LOOKUP(2,1/('Deliverables Sheet'!S151:S156<>0),'Deliverables Sheet'!S151:S156)} -> 210.6 | D46: {=LOOKUP(2,1/('Deliverables Sheet'!T151:T156<>0),'Deliverables Sheet'!T151:T156)} -> 260.75 | E46: {=LOOKUP(2,1/('Deliverables Sheet'!U151:U156<>0),'Deliverables Sheet'!U151:U156)} -> -50.15
A48: ='Main Sheet'!A48 -> 8337 | B48: ='Main Sheet'!B48 -> Waimak Dairys | C48: {=LOOKUP(2,1/('Deliverables Sheet'!S158:S163<>0),'Deliverables Sheet'!S158:S163)} -> 110.44 | D48: {=LOOKUP(2,1/('Deliverables Sheet'!T158:T163<>0),'Deliverables Sheet'!T158:T163)} -> 44.75 | E48: {=LOOKUP(2,1/('Deliverables Sheet'!U158:U163<>0),'Deliverables Sheet'!U158:U163)} -> 65.69 | M48: 16 | N48: 32
A50: ='Main Sheet'!A50 -> 9240 | B50: ='Main Sheet'!B50 -> Daves Twizel Shack | C50: {=LOOKUP(2,1/('Deliverables Sheet'!S165:S170<>0),'Deliverables Sheet'!S165:S170)} -> #N/A | D50: {=LOOKUP(2,1/('Deliverables Sheet'!T165:T170<>0),'Deliverables Sheet'!T165:T170)} -> #N/A | E50: {=LOOKUP(2,1/('Deliverables Sheet'!U165:U170<>0),'Deliverables Sheet'!U165:U170)} -> #N/A | M50: 16 | N50: 40
A52: ='Main Sheet'!A52 -> 7428 | B52: ='Main Sheet'!B52 -> FAB Pegasus Lakeside | C52: {=LOOKUP(2,1/('Deliverables Sheet'!S172:S177<>0),'Deliverables Sheet'!S172:S177)} -> 659.73 | D52: {=LOOKUP(2,1/('Deliverables Sheet'!T172:T177<>0),'Deliverables Sheet'!T172:T177)} -> 304.75 | E52: {=LOOKUP(2,1/('Deliverables Sheet'!U172:U177<>0),'Deliverables Sheet'!U172:U177)} -> 354.98 | M52: 80 | N52: 80 | O52: 180
A54: ='Main Sheet'!A54 -> 9351 | B54: ='Main Sheet'!B54 -> Harewood Golf Club | C54: {=LOOKUP(2,1/('Deliverables Sheet'!S179:S184<>0),'Deliverables Sheet'!S179:S184)} -> 125.17 | D54: {=LOOKUP(2,1/('Deliverables Sheet'!T179:T184<>0),'Deliverables Sheet'!T179:T184)} -> 11.25 | E54: {=LOOKUP(2,1/('Deliverables Sheet'!U179:U184<>0),'Deliverables Sheet'!U179:U184)} -> 113.92 | L54: 16 | M54: 32 | N54: 65
A56: ='Main Sheet'!A56 -> 7429 | B56: ='Main Sheet'!B56 -> Taggart House | C56: {=LOOKUP(2,1/('Deliverables Sheet'!S186:S191<>0),'Deliverables Sheet'!S186:S191)} -> 130.62 | D56: {=LOOKUP(2,1/('Deliverables Sheet'!T186:T191<>0),'Deliverables Sheet'!T186:T191)} -> 32.25 | E56: {=LOOKUP(2,1/('Deliverables Sheet'!U186:U191<>0),'Deliverables Sheet'!U186:U191)} -> 98.37 | M56: 16 | N56: 70
A58: ='Main Sheet'!A58 -> 9508 | B58: ='Main Sheet'!B58 -> St Barnabas Church | C58: {=LOOKUP(2,1/('Deliverables Sheet'!S193:S198<>0),'Deliverables Sheet'!S193:S198)} -> #N/A | D58: {=LOOKUP(2,1/('Deliverables Sheet'!T193:T198<>0),'Deliverables Sheet'!T193:T198)} -> #N/A | E58: {=LOOKUP(2,1/('Deliverables Sheet'!U193:U198<>0),'Deliverables Sheet'!U193:U198)} -> #N/A | O58: 52 | P58: 13 | Q58: 69
A60: ='Main Sheet'!A60 -> 0 | B60: ='Main Sheet'!B60 -> 0 | C60: {=LOOKUP(2,1/('Deliverables Sheet'!S200:S205<>0),'Deliverables Sheet'!S200:S205)} -> #N/A | D60: {=LOOKUP(2,1/('Deliverables Sheet'!T200:T205<>0),'Deliverables Sheet'!T200:T205)} -> #N/A | E60: {=LOOKUP(2,1/('Deliverables Sheet'!U200:U205<>0),'Deliverables Sheet'!U200:U205)} -> #N/A
A62: ='Main Sheet'!A62 -> 0 | B62: ='Main Sheet'!B62 -> Contracting | C62: {=LOOKUP(2,1/('Deliverables Sheet'!S207:S212<>0),'Deliverables Sheet'!S207:S212)} -> #N/A | D62: {=LOOKUP(2,1/('Deliverables Sheet'!T207:T212<>0),'Deliverables Sheet'!T207:T212)} -> #N/A | E62: {=LOOKUP(2,1/('Deliverables Sheet'!U207:U212<>0),'Deliverables Sheet'!U207:U212)} -> #N/A
A64: ='Main Sheet'!A64 -> 8946 | B64: ='Main Sheet'!B64 -> Westcoast Vaults | C64: {=LOOKUP(2,1/('Deliverables Sheet'!S214:S219<>0),'Deliverables Sheet'!S214:S219)} -> 358.86 | D64: {=LOOKUP(2,1/('Deliverables Sheet'!T214:T219<>0),'Deliverables Sheet'!T214:T219)} -> #N/A | E64: {=LOOKUP(2,1/('Deliverables Sheet'!U214:U219<>0),'Deliverables Sheet'!U214:U219)} -> 358.86 | N64: 143 | P64: 215
A66: ='Main Sheet'!A66 -> 8308 | B66: ='Main Sheet'!B66 -> Roydvale | C66: {=LOOKUP(2,1/('Deliverables Sheet'!S221:S226<>0),'Deliverables Sheet'!S221:S226)} -> 2312.68 | D66: {=LOOKUP(2,1/('Deliverables Sheet'!T221:T226<>0),'Deliverables Sheet'!T221:T226)} -> 1014.25 | E66: {=LOOKUP(2,1/('Deliverables Sheet'!U221:U226<>0),'Deliverables Sheet'!U221:U226)} -> 1298.43 | M66: 320 | N66: 250 | O66: 250 | P66: 240 | Q66: 80
B70: Total Hours | C70: =C3+C71+C72 -> #N/A | D70: =D3+D71+D72 -> #N/A | E70: =E3+E71+E72 -> #N/A | F70: =F3+F71+F72 -> 640 | G70: =G3+G71+G72 -> 715 | H70: =H3+H71+H72 -> 790 | I70: =I3+I71+I72 -> 700 | J70: =J3+J71+J72 -> 700 | ... Q70: =Q3+Q71+Q72 -> 650
B71: Residential Hours | C71: =SUM(C26:C46) -> #N/A | D71: =SUM(D26:D46) -> #N/A | E71: =SUM(E26:E46) -> #N/A | F71: =SUM(F26:F46) -> 140 | G71: =SUM(G26:G46) -> 15 | H71: =SUM(H26:H46) -> 90 | I71: =SUM(I26:I66) -> 0 | J71: =SUM(J26:J66) -> 0 | K71: =SUM(K26:K66) -> 0 | L71: =SUM(L26:L66) -> 16 | M71: =SUM(M26:M66) -> 800 | N71: =SUM(N26:N66) -> 858 | O71: =SUM(O26:O46) -> 476 | P71: =SUM(P26:P46) -> 214 | Q71: =SUM(Q26:Q46) -> 150
B72: Commercial Hours | C72: =SUM(C4:C24) -> 4490.26 | D72: =SUM(D4:D24) -> #N/A | E72: =SUM(E4:E24) -> #N/A | F72: =SUM(F4:F24) -> 0 | G72: =SUM(G4:G24) -> 0 | H72: =SUM(H4:H24) -> 0 | I72: =SUM(I4:I24) -> 0 | J72: =SUM(J4:J24) -> 0 | ... Q72: =SUM(Q4:Q24) -> 0
B73: Hours Available | F73: =F77*F76*8*0.8 -> 1488 | G73: =G77*G76*8*0.8 -> 2112 | H73: =H77*H76*8*0.8 -> 1984 | I73: =I77*I76*8*0.8 -> 1884.8 | J73: =J77*J76*8*0.8 -> 1948.8 | K73: =K77*K76*8*0.8 -> 2083.2 | L73: =L77*L76*8*0.8 -> 2604.8 | M73: =M77*M76*8*0.8 -> 2486.4 | ... Q73: =Q77*Q76*8*0.8 -> 1478.4
B74: Balance Hours | F74: =F70-F73 -> -848 | G74: =G70-G73 -> -1397 | H74: =H70-H73 -> -1194 | I74: =I70-I73 -> -1184.8 | J74: =J70-J73 -> -1248.8 | K74: =K70-K73 -> -1383.2 | L74: =L70-L73 -> -1888.8 | M74: =M70-M73 -> 33.6 | ... Q74: =Q70-Q73 -> -828.4
B76: Working Days In Month | C76: Check Staff Numbers | F76: 15 | G76: 20 | H76: 20 | I76: 19 | J76: 21 | K76: 21 | L76: 22 | M76: 21 | N76: 22 | O76: 21 | P76: 20 | Q76: 14
B77: No - Staff On Tools | F77: 15.5 | G77: 16.5 | H77: 15.5 | I77: 15.5 | J77: 14.5 | K77: 15.5 | L77: 18.5 | M77: 18.5 | N77: 18.5 | O77: 16.5 | P77: 16.5 | Q77: 16.5
B79: Staff | L79: 2 x PPLguys here for July and August
B80: Turbo | C80: 1
B81: Sean | C81: 1
B82: Jacob | C82: 1
B83: Hayden | C83: 1
B84: Doug | C84: 1
B85: Kyle | C85: 0.5
B86: Jack | C86: 1
B87: Andy | C87: 1
B88: Ben Ruffles | C88: 1
B89: Ben Dyer | C89: 0
B90: Jake | C90: 1
C91: 0
C92: 0
C93: 0
C94: 0
C95: 0
C96: 0
C97: 0
B98: Ethan | C98: 1
B99: Rhod | C99: 1
B100: George | C100: 1
B101: Jasper | C101: 1
B102: Logan | C102: 1
B103: Quin | C103: 1
B104: Regan | C104: 1
B109: Total Staff (enter in above spreadsheet) | C109: =SUM(C80:C108) -> 16.5

Sheet Note Cam (To Do)
A2: Cams Notes
A3: Koawa:
A4: New job meeting set up for 8am wednesday - Tim, Dylan, VD, Cam - Perhaps bring in Jacob once back from leave??
A5: Tray shop drawings into engineers - waiting on geoff to send back multidraw drawings.
A6: DB dates for sites (livening 11 July)
A7: Confirm Warrenties agreement
A8: Go to tech submissions meeting on Wednesday 12th March
A9: Start getting orders in, (so far PDL gear ordered through rads) need to look at lights beign ordered that we can - confirm process.
A12: Tru Hire:
A13: Temp should be on Monday morning 14.04.25
A14: Craig would like an export/list for me please mate that captures all of the costs to date from you guys and ILS?
A15: Riccarton High:
... A50: Comes up with hours tracking solution

Sheet Note Tom (To Do) 
A2: Tom's Notes:
A38: Other:
A39: Comes up with hours tracking solution

Sheet Deliverables_RR_Test_Sheet (2)
A1: Updated Job Spreadsheet
A2: Job Number | B2: Job Name | C2: Week | D2: Quoted Price | E2: Claim to date | F2: Remaining to claim | G2: % Claim remaining | H2: Total quoted cost | I2: Total actual cost | J2: Quoted material cost | K2: Actual material cost | L2: Material cost remaining | M2: Material % remaining | N2: Estimated % of materials recieved | O2: Contractor Quoted Cost | P2: Contractor Actual Cost | Q2: Contractor Balance | R2: Quoted labour cost | S2: Actual labour cost | T2: Labour cost remaining | U2: Labour cost % remaining | V2: Quoted labour hours | W2: Actual labour hours | X2: Labour hours remaining | Y2: Labour hour % remaining | Z2: Estimated % of job complete | AA2: GP $ Per Hour | AB2: Quoted GP $ Per Hour | AC2: Margin to date | AD2: Quoted margin
AK3: Hours calcs | AL3: Materials calcs
A4: ='Main Sheet'!A4 -> 7658 | B4: ='Main Sheet'!B4 -> Charity Hospital | C4: Start of month | D4: 1914143.5 | E4: 1667392.4 | F4: =D4-E4 -> 246751.12 | G4: =F4/D4 -> 0.12890941 | H4: 1675578 | I4: 1406264.8 | J4: =SUM(H4-(R4+O4)) -> 1511021.4 | K4: =SUM(I4-(S4+P4)) -> 1215391.4 | L4: =J4-K4 -> 295630 | M4: =L4/J4 -> 0.19564911 | O4: 5 | P4: 4 | Q4: =O4-P4 -> 1 | R4: 164551.54 | S4: 190869.33 | T4: =R4-S4 -> -26317.79 | U4: =T4/R4 -> -0.15993646 | V4: 3296.1 | W4: 4599 | X4: =V4-W4 -> -1302.9 | Y4: =X4/V4 -> -0.39528534 | AA4: =(E4-K4-S4)/W4 -> 56.780087 | AB4: =(D4-J4-R4)/V4 -> 72.37964 | AC4: =(E4-K4-S4)/E4 -> 0.15661078 | AD4: =SUM(D4-H4)/D4 -> 0.12463304 | AG4: Hours calc for monthly claims | AH4: =AK9 -> -4599 | AK4: =SUM(W5-W4) -> 415.49 | AL4: =SUM(K5-K4) -> 48650.89
C5: Week 1 | D5: 1922479.9 | E5: 1667392.4 | F5: =D5-E5 -> 255087.52 | G5: =F5/D5 -> 0.1326867 | H5: 1681960.6 | I5: 1474477.1 | J5: =SUM(H5-R5) -> 1516687.4 | K5: =SUM(I5-S5) -> 1264042.3 | L5: =J5-K5 -> 252645.09 | M5: =L5/J5 -> 0.1665769 | R5: 165273.18 | S5: 210434.8 | T5: =R5-S5 -> -45161.62 | U5: =T5/R5 -> -0.27325438 | V5: 3312.1 | W5: 5014.49 | X5: =V5-W5 -> -1702.39 | Y5: =X5/V5 -> -0.51399112 | AA5: =(E5-K5-S5)/W5 -> 38.471561 | AB5: =(D5-J5-R5)/V5 -> 72.618372 | AC5: =(E5-K5-S5)/E5 -> 0.11569878 | AD5: =SUM(D5-H5)/D5 -> 0.12510888 | AG5: Materials calc for monthly claims | AH5: =AL9 -> -1215391.4 | AK5: =SUM(W6-W5) -> 134.5 | AL5: =SUM(K6-K5) -> 24752.67
C6: Week 2 | D6: 1922479.9 | E6: 1667392.4 | F6: =D6-E6 -> 255087.52 | G6: =F6/D6 -> 0.1326867 | H6: 1681960.6 | I6: 1505572.2 | J6: =SUM(H6-R6) -> 1516687.4 | K6: =SUM(I6-S6) -> 1288795 | L6: =J6-K6 -> 227892.42 | M6: =L6/J6 -> 0.15025668 | N6: 0.9 | R6: 165273.18 | S6: 216777.2 | T6: =R6-S6 -> -51504.02 | U6: =T6/R6 -> -0.31162963 | V6: 3312.1 | W6: 5148.99 | X6: =V6-W6 -> -1836.89 | Y6: =X6/V6 -> -0.5545998 | Z6: 0.9 | AA6: =(E6-K6-S6)/W6 -> 31.42756 | AB6: =(D6-J6-R6)/V6 -> 72.618372 | AC6: =(E6-K6-S6)/E6 -> 0.097049855 | AD6: =SUM(D6-H6)/D6 -> 0.12510888 | AK6: =SUM(W7-W6) -> -5148.99 | AL6: =SUM(K7-K6) -> -1288795
C7: Week 3 | F7: =D7-E7 -> 0 | G7: =F7/D7 -> #DIV/0! | J7: =SUM(H7-R7) -> 0 | K7: =SUM(I7-S7) -> 0 | L7: =J7-K7 -> 0 | M7: =L7/J7 -> #DIV/0! | T7: =R7-S7 -> 0 | U7: =T7/R7 -> #DIV/0! | X7: =V7-W7 -> 0 | Y7: =X7/V7 -> #DIV/0! | AA7: =(E7-K7-S7)/W7 -> #DIV/0! | AB7: =(D7-J7-R7)/V7 -> #DIV/0! | AC7: =(E7-K7-S7)/E7 -> #DIV/0! | AD7: =SUM(D7-H7)/D7 -> #DIV/0! | AG7: Estimated months claim | AH7: 0 | AK7: =SUM(W8-W7) -> 0 | AL7: =SUM(K8-K7) -> 0
C8: Week 4 | F8: =D8-E8 -> 0 | G8: =F8/D8 -> #DIV/0! | J8: =SUM(H8-R8) -> 0 | K8: =SUM(I8-S8) -> 0 | L8: =J8-K8 -> 0 | M8: =L8/J8 -> #DIV/0! | T8: =R8-S8 -> 0 | U8: =T8/R8 -> #DIV/0! | X8: =V8-W8 -> 0 | Y8: =X8/V8 -> #DIV/0! | AA8: =(E8-K8-S8)/W8 -> #DIV/0! | AB8: =(D8-J8-R8)/V8 -> #DIV/0! | AC8: =(E8-K8-S8)/E8 -> #DIV/0! | AD8: =SUM(D8-H8)/D8 -> #DIV/0! | AK8: =SUM(W9-W8) -> 0 | AL8: =SUM(K9-K8) -> 0
C9: Week 5 | F9: =D9-E9 -> 0 | G9: =F9/D9 -> #DIV/0! | J9: =SUM(H9-R9) -> 0 | K9: =SUM(I9-S9) -> 0 | L9: =J9-K9 -> 0 | M9: =L9/J9 -> #DIV/0! | T9: =R9-S9 -> 0 | U9: =T9/R9 -> #DIV/0! | X9: =V9-W9 -> 0 | Y9: =X9/V9 -> #DIV/0! | AA9: =(E9-K9-S9)/W9 -> #DIV/0! | AB9: =(D9-J9-R9)/V9 -> #DIV/0! | AC9: =(E9-K9-S9)/E9 -> #DIV/0! | AD9: =SUM(D9-H9)/D9 -> #DIV/0! | AK9: =SUM(AK4,AK5,AK6,AK7,AK8) -> -4599 | AL9: =SUM(AL4,AL5,AL6,AL7,AL8) -> -1215391.4
A11: ='Main Sheet'!A6 -> 8142 | B11: ='Main Sheet'!B6 -> Fisher Developements | C11: Start of month | D11: 381671.63 | E11: 144223.4 | F11: =D11-E11 -> 237448.23 | G11: =F11/D11 -> 0.62212701 | H11: 329257.09 | I11: 168819.17 | J11: =SUM(H11-R11) -> 288248.16 | K11: =SUM(I11-S11) -> 158648.53 | L11: =J11-K11 -> 129599.63 | M11: =L11/J11 -> 0.4496113 | R11: 41008.93 | S11: 10170.64 | T11: =R11-S11 -> 30838.29 | U11: =T11/R11 -> 0.75198963 | V11: 821.2 | W11: 241 | X11: =V11-W11 -> 580.2 | Y11: =X11/V11 -> 0.70652703 | AA11: =(E11-K11-S11)/W11 -> -102.05714 | AB11: =(D11-J11-R11)/V11 -> 63.826766 | AC11: =(E11-K11-S11)/E11 -> -0.17053939 | AD11: =SUM(D11-H11)/D11 -> 0.13732889 | AG11: Hours calc for monthly claims | AH11: =AK16 -> -241 | AK11: =SUM(W12-W11) -> 96.25 | AL11: =SUM(K12-K11) -> 30474.42
C12: Week 1 | D12: 382219.49 | E12: 240065.55 | F12: =D12-E12 -> 142153.94 | G12: =F12/D12 -> 0.37191704 | H12: 329585.81 | I12: 202828.2 | J12: =SUM(H12-R12) -> 288352.94 | K12: =SUM(I12-S12) -> 189122.95 | L12: =J12-K12 -> 99229.99 | M12: =L12/J12 -> 0.34412685 | R12: 41232.87 | S12: 13705.25 | T12: =R12-S12 -> 27527.62 | U12: =T12/R12 -> 0.66761348 | V12: 825.68 | W12: 337.25 | X12: =V12-W12 -> 488.43 | Y12: =X12/V12 -> 0.59154878 | AA12: =(E12-K12-S12)/W12 -> 110.41468 | AB12: =(D12-J12-R12)/V12 -> 63.745858 | AC12: =(E12-K12-S12)/E12 -> 0.15511326 | AD12: =SUM(D12-H12)/D12 -> 0.13770538 | AG12: Materials calc for monthly claims | AH12: =AL16 -> -158648.53 | AK12: =SUM(W13-W12) -> 101.75 | AL12: =SUM(K13-K12) -> 7119.32
C13: Week 2 | D13: 382219.49 | E13: 240065.55 | F13: =D13-E13 -> 142153.94 | G13: =F13/D13 -> 0.37191704 | H13: 329585.81 | I13: 213730.54 | J13: =SUM(H13-R13) -> 288352.94 | K13: =SUM(I13-S13) -> 196242.27 | L13: =J13-K13 -> 92110.67 | M13: =L13/J13 -> 0.31943725 | R13: 41232.87 | S13: 17488.27 | T13: =R13-S13 -> 23744.6 | U13: =T13/R13 -> 0.57586581 | V13: 825.68 | W13: 439 | X13: =V13-W13 -> 386.68 | Y13: =X13/V13 -> 0.46831702 | AA13: =(E13-K13-S13)/W13 -> 59.988633 | AB13: =(D13-J13-R13)/V13 -> 63.745858 | AC13: =(E13-K13-S13)/E13 -> 0.10969925 | AD13: =SUM(D13-H13)/D13 -> 0.13770538 | AK13: =SUM(W14-W13) -> -439 | AL13: =SUM(K14-K13) -> 23228
C14: Week 3 | D14: 383409.63 | E14: 240065.55 | F14: =D14-E14 -> 143344.08 | G14: =F14/D14 -> 0.37386667 | H14: 330537 | I14: 246817.11 | J14: 289155.03 | K14: 219470.27 | L14: =J14-K14 -> 69684.76 | M14: =L14/J14 -> 0.24099446 | N14: 0.75 | T14: =R14-S14 -> 0 | U14: =T14/R14 -> #DIV/0! | X14: =V14-W14 -> 0 | Y14: =X14/V14 -> #DIV/0! | AA14: =(E14-K14-S14)/W14 -> #DIV/0! | AB14: =(D16-J14-R14)/V14 -> #DIV/0! | AC14: =(E14-K14-S14)/E14 -> 0.085790235 | AD14: =SUM(D16-H14)/D16 -> 0.13790115 | AG14: Estimated months claim | AH14: 0 | AK14: =SUM(W15-W14) -> 0 | AL14: =SUM(K15-K14) -> -219470.27
C15: Week 4 | D15: 383409.63 | F15: =D15-E15 -> 383409.63 | G15: =F15/D15 -> 1 | J15: =SUM(H15-R15) -> 0 | K15: =SUM(I15-S15) -> 0 | L15: =J15-K15 -> 0 | M15: =L15/J15 -> #DIV/0! | T15: =R15-S15 -> 0 | U15: =T15/R15 -> #DIV/0! | X15: =V15-W15 -> 0 | Y15: =X15/V15 -> #DIV/0! | AA15: =(E15-K15-S15)/W15 -> #DIV/0! | AB15: =(D15-J15-R15)/V15 -> #DIV/0! | AC15: =(E15-K15-S15)/E15 -> #DIV/0! | AD15: =SUM(D15-H15)/D15 -> 1 | AK15: =SUM(W16-W15) -> 0 | AL15: =SUM(K16-K15) -> 0
C16: Week 5 | D16: 383409.63 | F16: =D16-E16 -> 383409.63 | G16: =F16/D16 -> 1 | J16: =SUM(H16-R16) -> 0 | K16: =SUM(I16-S16) -> 0 | L16: =J16-K16 -> 0 | M16: =L16/J16 -> #DIV/0! | N16: 0.55 | T16: =R16-S16 -> 0 | U16: =T16/R16 -> #DIV/0! | X16: =V16-W16 -> 0 | Y16: =X16/V16 -> #DIV/0! | Z16: 0.35 | AA16: =(E16-K16-S16)/W16 -> #DIV/0! | AB16: =(#REF!-J16-R16)/V16 -> #REF! | AC16: =(E16-K16-S16)/E16 -> #DIV/0! | AD16: =SUM(#REF!-H16)/#REF! -> #REF! | AK16: =SUM(AK11,AK12,AK13,AK14,AK15) -> -241 | AL16: =SUM(AL11,AL12,AL13,AL14,AL15) -> -158648.53
A18: 7104 | B18: ='Main Sheet'!B8 -> 3 Innovation Road | C18: Start of month | D18: 449818.08 | E18: 246538.95 | F18: =D18-E18 -> 203279.13 | G18: =F18/D18 -> 0.45191409 | H18: 329858.1 | I18: 251921.97 | J18: =SUM(H18-R18) -> 255282.19 | K18: =SUM(I18-S18) -> 219103.38 | L18: =J18-K18 -> 36178.81 | M18: =L18/J18 -> 0.14172085 | N18: 0 | R18: 74575.91 | S18: 32818.59 | T18: =R18-S18 -> 41757.32 | U18: =T18/R18 -> 0.55993041 | V18: 1493.36 | W18: 799.5 | X18: =V18-W18 -> 693.86 | Y18: =X18/V18 -> 0.4646301 | Z18: 0 | AA18: =(E18-K18-S18)/W18 -> -6.7329831 | AB18: =(D18-J18-R18)/V18 -> 80.328909 | AC18: =(E18-K18-S18)/E18 -> -0.021834359 | AD18: =SUM(D18-H18)/D18 -> 0.26668555 | AG18: Hours calc for monthly claims | AH18: =AK23 -> -799.5 | AK18: =SUM(W19-W18) -> 57.75 | AL18: =SUM(K19-K18) -> -918.26
C19: Week 1 | D19: 449818.08 | E19: 364039.73 | F19: =D19-E19 -> 85778.35 | G19: =F19/D19 -> 0.19069565 | H19: 329858.1 | I19: 253347.64 | J19: =SUM(H19-R19) -> 255282.19 | K19: =SUM(I19-S19) -> 218185.12 | L19: =J19-K19 -> 37097.07 | M19: =L19/J19 -> 0.14531789 | R19: 74575.91 | S19: 35162.52 | T19: =R19-S19 -> 39413.39 | U19: =T19/R19 -> 0.52850029 | V19: 1493.36 | W19: 857.25 | X19: =V19-W19 -> 636.11 | Y19: =X19/V19 -> 0.42595891 | Z19: 0.1 | AA19: =(E19-K19-S19)/W19 -> 129.12463 | AB19: =(D19-J19-R19)/V19 -> 80.328909 | AC19: =(E19-K19-S19)/E19 -> 0.30406596 | AD19: =SUM(D19-H19)/D19 -> 0.26668555 | AG19: Materials calc for monthly claims | AH19: =AL23 -> -219103.38 | AK19: =SUM(W20-W19) -> 93.75 | AL19: =SUM(K20-K19) -> 5813.69
C20: Week 2 | D20: 449818.08 | E20: 364039.73 | F20: =D20-E20 -> 85778.35 | G20: =F20/D20 -> 0.19069565 | H20: 329858.1 | I20: 262942.02 | J20: =SUM(H20-R20) -> 255282.19 | K20: =SUM(I20-S20) -> 223998.81 | L20: =J20-K20 -> 31283.38 | M20: =L20/J20 -> 0.12254431 | R20: 74575.91 | S20: 38943.21 | T20: =R20-S20 -> 35632.7 | U20: =T20/R20 -> 0.47780443 | V20: 1493.36 | W20: 951 | X20: =V20-W20 -> 542.36 | Y20: =X20/V20 -> 0.36318101 | Z20: 0.15 | AA20: =(E20-K20-S20)/W20 -> 106.30674 | AB20: =(D20-J20-R20)/V20 -> 80.328909 | AC20: =(E20-K20-S20)/E20 -> 0.27771065 | AD20: =SUM(D20-H20)/D20 -> 0.26668555 | AK20: =SUM(W21-W20) -> -951 | AL20: =SUM(K21-K20) -> -223998.81
C21: Week 3 | F21: =D21-E21 -> 0 | G21: =F21/D21 -> #DIV/0! | J21: =SUM(H21-R21) -> 0 | K21: =SUM(I21-S21) -> 0 | L21: =J21-K21 -> 0 | M21: =L21/J21 -> #DIV/0! | T21: =R21-S21 -> 0 | U21: =T21/R21 -> #DIV/0! | X21: =V21-W21 -> 0 | Y21: =X21/V21 -> #DIV/0! | Z21: 0.03 | AA21: =(E21-K21-S21)/W21 -> #DIV/0! | AB21: =(D21-J21-R21)/V21 -> #DIV/0! | AC21: =(E21-K21-S21)/E21 -> #DIV/0! | AD21: =SUM(D21-H21)/D21 -> #DIV/0! | AG21: Estimated months claim | AH21: 0 | AK21: =SUM(W22-W21) -> 0 | AL21: =SUM(K22-K21) -> 0
C22: Week 4 | F22: =D22-E22 -> 0 | G22: =F22/D22 -> #DIV/0! | J22: =SUM(H22-R22) -> 0 | K22: =SUM(I22-S22) -> 0 | L22: =J22-K22 -> 0 | M22: =L22/J22 -> #DIV/0! | T22: =R22-S22 -> 0 | U22: =T22/R22 -> #DIV/0! | X22: =V22-W22 -> 0 | Y22: =X22/V22 -> #DIV/0! | Z22: 0.03 | AA22: =(E22-K22-S22)/W22 -> #DIV/0! | AB22: =(D22-J22-R22)/V22 -> #DIV/0! | AC22: =(E22-K22-S22)/E22 -> #DIV/0! | AD22: =SUM(D22-H22)/D22 -> #DIV/0! | AK22: =SUM(W23-W22) -> 0 | AL22: =SUM(K23-K22) -> 0
C23: Week 5 | F23: =D23-E23 -> 0 | G23: =F23/D23 -> #DIV/0! | J23: =SUM(H23-R23) -> 0 | K23: =SUM(I23-S23) -> 0 | L23: =J23-K23 -> 0 | M23: =L23/J23 -> #DIV/0! | N23: 0.9 | T23: =R23-S23 -> 0 | U23: =T23/R23 -> #DIV/0! | X23: =V23-W23 -> 0 | Y23: =X23/V23 -> #DIV/0! | Z23: 0.65 | AA23: =(E23-K23-S23)/W23 -> #DIV/0! | AB23: =(D23-J23-R23)/V23 -> #DIV/0! | AC23: =(E23-K23-S23)/E23 -> #DIV/0! | AD23: =SUM(D23-H23)/D23 -> #DIV/0! | AK23: =SUM(AK18,AK19,AK20,AK21,AK22) -> -799.5 | AL23: =SUM(AL18,AL19,AL20,AL21,AL22) -> -219103.38
A25: ='Main Sheet'!A10 -> 8127 | B25: ='Main Sheet'!B10 -> Rolly Autowash | C25: Start of month | D25: 38856.96 | E25: 0 | F25: =D25-E25 -> 38856.96 | G25: =F25/D25 -> 1 | H25: 27050.88 | I25: 1129.12 | J25: =SUM(H25-R25) -> 16492.08 | K25: =SUM(I25-S25) -> 1129.12 | L25: =J25-K25 -> 15362.96 | M25: =L25/J25 -> 0.93153562 | N25: 0 | R25: 10558.8 | S25: 0 | T25: =R25-S25 -> 10558.8 | U25: =T25/R25 -> 1 | V25: 213 | W25: 0 | X25: =V25-W25 -> 213 | Y25: =X25/V25 -> 1 | Z25: 0 | AA25: =(E25-K25-S25)/W25 -> #DIV/0! | AB25: =(D25-J25-R25)/V25 -> 55.427606 | AC25: =(E25-K25-S25)/E25 -> #DIV/0! | AD25: =SUM(D25-H25)/D25 -> 0.30383437 | AG25: Hours calc for monthly claims | AH25: =AK30 -> 0 | AK25: =SUM(W26-W25) -> 9.25 | AL25: =SUM(K26-K25) -> 5779.58
C26: Week 1 | D26: 38856.96 | E26: 0 | F26: =D26-E26 -> 38856.96 | G26: =F26/D26 -> 1 | H26: 27050.88 | I26: 7293.59 | J26: =SUM(H26-R26) -> 16492.08 | K26: =SUM(I26-S26) -> 6908.7 | L26: =J26-K26 -> 9583.38 | M26: =L26/J26 -> 0.58108983 | N26: 0 | R26: 10558.8 | S26: 384.89 | T26: =R26-S26 -> 10173.91 | U26: =T26/R26 -> 0.96354794 | V26: 213.13 | W26: 9.25 | X26: =V26-W26 -> 203.88 | Y26: =X26/V26 -> 0.95659926 | Z26: 0 | AA26: =(E26-K26-S26)/W26 -> -788.49622 | AB26: =(D26-J26-R26)/V26 -> 55.393797 | AC26: =(E26-K26-S26)/E26 -> #DIV/0! | AD26: =SUM(D26-H26)/D26 -> 0.30383437 | AG26: Materials calc for monthly claims | AH26: =AL30 -> -1129.12 | AK26: =SUM(W27-W26) -> 101.75 | AL26: =SUM(K27-K26) -> 6796.13
C27: Week 2 | D27: 38856.96 | E27: 0 | F27: =D27-E27 -> 38856.96 | G27: =F27/D27 -> 1 | H27: 27050.88 | I27: 18431.21 | J27: =SUM(H27-R27) -> 16492.08 | K27: =SUM(I27-S27) -> 13704.83 | L27: =J27-K27 -> 2787.25 | M27: =L27/J27 -> 0.16900536 | N27: 0 | R27: 10558.8 | S27: 4726.38 | T27: =R27-S27 -> 5832.42 | U27: =T27/R27 -> 0.55237527 | V27: 213.13 | W27: 111 | X27: =V27-W27 -> 102.13 | Y27: =X27/V27 -> 0.4791911 | Z27: 0 | AA27: =(E27-K27-S27)/W27 -> -166.04694 | AB27: =(D27-J27-R27)/V27 -> 55.393797 | AC27: =(E27-K27-S27)/E27 -> #DIV/0! | AD27: =SUM(D27-H27)/D27 -> 0.30383437 | AK27: =SUM(W28-W27) -> -111 | AL27: =SUM(K28-K27) -> -13704.83
C28: Week 3 | E28: 0 | F28: =D28-E28 -> 0 | G28: =F28/D28 -> #DIV/0! | J28: =SUM(H28-R28) -> 0 | K28: =SUM(I28-S28) -> 0 | L28: =J28-K28 -> 0 | M28: =L28/J28 -> #DIV/0! | N28: 0 | S28: 0 | T28: =R28-S28 -> 0 | U28: =T28/R28 -> #DIV/0! | W28: 0 | X28: =V28-W28 -> 0 | Y28: =X28/V28 -> #DIV/0! | Z28: 0 | AA28: =(E28-K28-S28)/W28 -> #DIV/0! | AB28: =(D28-J28-R28)/V28 -> #DIV/0! | AC28: =(E28-K28-S28)/E28 -> #DIV/0! | AD28: =SUM(D28-H28)/D28 -> #DIV/0! | AG28: Estimated months claim | AH28: 0 | AK28: =SUM(W29-W28) -> 0 | AL28: =SUM(K29-K28) -> 0
C29: Week 4 | E29: 0 | F29: =D29-E29 -> 0 | G29: =F29/D29 -> #DIV/0! | J29: =SUM(H29-R29) -> 0 | K29: =SUM(I29-S29) -> 0 | L29: =J29-K29 -> 0 | M29: =L29/J29 -> #DIV/0! | N29: 0 | S29: 0 | T29: =R29-S29 -> 0 | U29: =T29/R29 -> #DIV/0! | W29: 0 | X29: =V29-W29 -> 0 | Y29: =X29/V29 -> #DIV/0! | Z29: 0 | AA29: =(E29-K29-S29)/W29 -> #DIV/0! | AB29: =(D29-J29-R29)/V29 -> #DIV/0! | AC29: =(E29-K29-S29)/E29 -> #DIV/0! | AD29: =SUM(D29-H29)/D29 -> #DIV/0! | AK29: =SUM(W30-W29) -> 0 | AL29: =SUM(K30-K29) -> 0
C30: Week 5 | E30: 0 | F30: =D30-E30 -> 0 | G30: =F30/D30 -> #DIV/0! | J30: =SUM(H30-R30) -> 0 | K30: =SUM(I30-S30) -> 0 | L30: =J30-K30 -> 0 | M30: =L30/J30 -> #DIV/0! | N30: 0 | S30: 0 | T30: =R30-S30 -> 0 | U30: =T30/R30 -> #DIV/0! | W30: 0 | X30: =V30-W30 -> 0 | Y30: =X30/V30 -> #DIV/0! | Z30: 0 | AA30: =(E30-K30-S30)/W30 -> #DIV/0! | AB30: =(D30-J30-R30)/V30 -> #DIV/0! | AC30: =(E30-K30-S30)/E30 -> #DIV/0! | AD30: =SUM(D30-H30)/D30 -> #DIV/0! | AK30: =SUM(AK25,AK26,AK27,AK28,AK29) -> 0 | AL30: =SUM(AL25,AL26,AL27,AL28,AL29) -> -1129.12
A32: ='Main Sheet'!A12 -> 8183 | B32: ='Main Sheet'!B12 -> Murney - 1 Freight Drive + 109 Iport | C32: Start of month | D32: 69191.71 | E32: 0 | F32: =D32-E32 -> 69191.71 | G32: =F32/D32 -> 1 | H32: 53243.87 | I32: 641.28 | J32: =SUM(H32-R32) -> 41588.94 | K32: =SUM(I32-S32) -> 171.84 | L32: =J32-K32 -> 41417.1 | M32: =L32/J32 -> 0.99586813 | R32: 11654.93 | S32: 469.44 | T32: =R32-S32 -> 11185.49 | U32: =T32/R32 -> 0.95972177 | V32: 233.59 | W32: 12.5 | X32: =V32-W32 -> 221.09 | Y32: =X32/V32 -> 0.94648744 | Z32: 0 | AA32: =(E32-K32-S32)/W32 -> -51.3024 | AB32: =(D32-J32-R32)/V32 -> 68.272786 | AC32: =(E32-K32-S32)/E32 -> #DIV/0! | AD32: =SUM(D32-H32)/D32 -> 0.23048773 | AG32: Hours calc for monthly claims | AH32: =AK37 -> -12.5 | AK32: =SUM(W33-W32) -> 4.5 | AL32: =SUM(K33-K32) -> 13.95
C33: Week 1 | D33: 69191.71 | E33: 1364.78 | F33: =D33-E33 -> 67826.93 | G33: =F33/D33 -> 0.98027538 | H33: 53243.87 | I33: 844.77 | J33: =SUM(H33-R33) -> 41588.94 | K33: =SUM(I33-S33) -> 185.79 | L33: =J33-K33 -> 41403.15 | M33: =L33/J33 -> 0.99553271 | R33: 11654.93 | S33: 658.98 | T33: =R33-S33 -> 10995.95 | U33: =T33/R33 -> 0.94345912 | V33: 233.59 | W33: 17 | X33: =V33-W33 -> 216.59 | Y33: =X33/V33 -> 0.92722291 | AA33: =(E33-K33-S33)/W33 -> 30.588824 | AB33: =(D33-J33-R33)/V33 -> 68.272786 | AC33: =(E33-K33-S33)/E33 -> 0.38102112 | AD33: =SUM(D33-H33)/D33 -> 0.23048773 | AG33: Materials calc for monthly claims | AH33: =AL37 -> -171.84 | AK33: =SUM(W34-W33) -> 3 | AL33: =SUM(K34-K33) -> 3907.37
C34: Week 2 | D34: 69191.71 | E34: 1364.78 | F34: =D34-E34 -> 67826.93 | G34: =F34/D34 -> 0.98027538 | H34: 53243.87 | I34: 4850.24 | J34: =SUM(H34-R34) -> 41588.94 | K34: =SUM(I34-S34) -> 4093.16 | L34: =J34-K34 -> 37495.78 | M34: =L34/J34 -> 0.90158056 | R34: 11654.93 | S34: 757.08 | T34: =R34-S34 -> 10897.85 | U34: =T34/R34 -> 0.93504208 | V34: 233.59 | W34: 20 | X34: =V34-W34 -> 213.59 | Y34: =X34/V34 -> 0.9143799 | AA34: =(E34-K34-S34)/W34 -> -174.273 | AB34: =(D34-J34-R34)/V34 -> 68.272786 | AC34: =(E34-K34-S34)/E34 -> -2.5538622 | AD34: =SUM(D34-H34)/D34 -> 0.23048773 | AK34: =SUM(W35-W34) -> -20 | AL34: =SUM(K35-K34) -> -4093.16
C35: Week 3 | F35: =D35-E35 -> 0 | G35: =F35/D35 -> #DIV/0! | J35: =SUM(H35-R35) -> 0 | K35: =SUM(I35-S35) -> 0 | L35: =J35-K35 -> 0 | M35: =L35/J35 -> #DIV/0! | T35: =R35-S35 -> 0 | U35: =T35/R35 -> #DIV/0! | X35: =V35-W35 -> 0 | Y35: =X35/V35 -> #DIV/0! | AA35: =(E35-K35-S35)/W35 -> #DIV/0! | AB35: =(D35-J35-R35)/V35 -> #DIV/0! | AC35: =(E35-K35-S35)/E35 -> #DIV/0! | AD35: =SUM(D35-H35)/D35 -> #DIV/0! | AG35: Estimated months claim | AH35: 0 | AK35: =SUM(W36-W35) -> 0 | AL35: =SUM(K36-K35) -> 0
C36: Week 4 | F36: =D36-E36 -> 0 | G36: =F36/D36 -> #DIV/0! | J36: =SUM(H36-R36) -> 0 | K36: =SUM(I36-S36) -> 0 | L36: =J36-K36 -> 0 | M36: =L36/J36 -> #DIV/0! | T36: =R36-S36 -> 0 | U36: =T36/R36 -> #DIV/0! | X36: =V36-W36 -> 0 | Y36: =X36/V36 -> #DIV/0! | AA36: =(E36-K36-S36)/W36 -> #DIV/0! | AB36: =(D36-J36-R36)/V36 -> #DIV/0! | AC36: =(E36-K36-S36)/E36 -> #DIV/0! | AD36: =SUM(D36-H36)/D36 -> #DIV/0! | AK36: =SUM(W37-W36) -> 0 | AL36: =SUM(K37-K36) -> 0
C37: Week 5 | F37: =D37-E37 -> 0 | G37: =F37/D37 -> #DIV/0! | J37: =SUM(H37-R37) -> 0 | K37: =SUM(I37-S37) -> 0 | L37: =J37-K37 -> 0 | M37: =L37/J37 -> #DIV/0! | T37: =R37-S37 -> 0 | U37: =T37/R37 -> #DIV/0! | X37: =V37-W37 -> 0 | Y37: =X37/V37 -> #DIV/0! | AA37: =(E37-K37-S37)/W37 -> #DIV/0! | AB37: =(D37-J37-R37)/V37 -> #DIV/0! | AC37: =(E37-K37-S37)/E37 -> #DIV/0! | AD37: =SUM(D37-H37)/D37 -> #DIV/0! | AK37: =SUM(AK32,AK33,AK34,AK35,AK36) -> -12.5 | AL37: =SUM(AL32,AL33,AL34,AL35,AL36) -> -171.84
A39: ='Main Sheet'!A14 -> 8886 | B39: ='Main Sheet'!B14 -> Monkey Toe - Fisher fit out | C39: Start of month | D39: 44956.29 | F39: =D39-E39 -> 44956.29 | G39: =F39/D39 -> 1 | H39: 30585.67 | I39: 0 | J39: =SUM(H39-R39) -> 19268.79 | K39: =SUM(I39-S39) -> 0 | L39: =J39-K39 -> 19268.79 | M39: =L39/J39 -> 1 | R39: 11316.88 | T39: =R39-S39 -> 11316.88 | U39: =T39/R39 -> 1 | V39: 234.28 | W39: 0 | X39: =V39-W39 -> 234.28 | Y39: =X39/V39 -> 1 | Z39: 0.8 | AA39: =(E39-K39-S39)/W39 -> #DIV/0! | AB39: =(D39-J39-R39)/V39 -> 61.339508 | AC39: =(E39-K39-S39)/E39 -> #DIV/0! | AD39: =SUM(D39-H39)/D39 -> 0.31965761 | AG39: Hours calc for monthly claims | AH39: =AK44 -> 0 | AK39: =SUM(W40-W39) -> 0 | AL39: =SUM(K40-K39) -> 0
C40: Week 1 | D40: 44956.29 | F40: =D40-E40 -> 44956.29 | G40: =F40/D40 -> 1 | H40: 30585.67 | J40: =SUM(H40-R40) -> 19268.79 | K40: =SUM(I40-S40) -> 0 | L40: =J40-K40 -> 19268.79 | M40: =L40/J40 -> 1 | R40: 11316.88 | T40: =R40-S40 -> 11316.88 | U40: =T40/R40 -> 1 | V40: 234.28 | W40: 0 | X40: =V40-W40 -> 234.28 | Y40: =X40/V40 -> 1 | Z40: 0.95 | AA40: =(E40-K40-S40)/W40 -> #DIV/0! | AB40: =(D40-J40-R40)/V40 -> 61.339508 | AC40: =(E40-K40-S40)/E40 -> #DIV/0! | AD40: =SUM(D40-H40)/D40 -> 0.31965761 | AG40: Materials calc for monthly claims | AH40: =AL44 -> 0 | AK40: =SUM(W41-W40) -> 2.5 | AL40: =SUM(K41-K40) -> 0
C41: Week 2 | D41: 44956.29 | F41: =D41-E41 -> 44956.29 | G41: =F41/D41 -> 1 | H41: 30585.67 | I41: 112.35 | J41: =SUM(H41-R41) -> 19268.79 | K41: =SUM(I41-S41) -> 0 | L41: =J41-K41 -> 19268.79 | M41: =L41/J41 -> 1 | R41: 11316.88 | S41: 112.35 | T41: =R41-S41 -> 11204.53 | U41: =T41/R41 -> 0.99007235 | V41: 234.28 | W41: 2.5 | X41: =V41-W41 -> 231.78 | Y41: =X41/V41 -> 0.98932901 | Z41: 0.98 | AA41: =(E41-K41-S41)/W41 -> -44.94 | AB41: =(D41-J41-R41)/V41 -> 61.339508 | AC41: =(E41-K41-S41)/E41 -> #DIV/0! | AD41: =SUM(D41-H41)/D41 -> 0.31965761 | AK41: =SUM(W42-W41) -> -2.5 | AL41: =SUM(K42-K41) -> 0
C42: Week 3 | F42: =D42-E42 -> 0 | G42: =F42/D42 -> #DIV/0! | J42: =SUM(H42-R42) -> 0 | K42: =SUM(I42-S42) -> 0 | L42: =J42-K42 -> 0 | M42: =L42/J42 -> #DIV/0! | T42: =R42-S42 -> 0 | U42: =T42/R42 -> #DIV/0! | W42: 0 | X42: =V42-W42 -> 0 | Y42: =X42/V41 -> 0 | Z42: 1 | AA42: =(E42-K42-S42)/W42 -> #DIV/0! | AB42: =(D42-J42-R42)/V41 -> 0 | AC42: =(E42-K42-S42)/E42 -> #DIV/0! | AD42: =SUM(D42-H42)/D42 -> #DIV/0! | AG42: Estimated months claim | AH42: 0 | AK42: =SUM(W43-W42) -> 0 | AL42: =SUM(K43-K42) -> 0
C43: Week 4 | F43: =D43-E43 -> 0 | G43: =F43/D43 -> #DIV/0! | J43: =SUM(H43-R43) -> 0 | K43: =SUM(I43-S43) -> 0 | L43: =J43-K43 -> 0 | M43: =L43/J43 -> #DIV/0! | T43: =R43-S43 -> 0 | U43: =T43/R43 -> #DIV/0! | W43: 0 | X43: =V43-W43 -> 0 | Y43: =X43/V43 -> #DIV/0! | Z43: 1 | AA43: =(E43-K43-S43)/W43 -> #DIV/0! | AB43: =(D43-J43-R43)/V43 -> #DIV/0! | AC43: =(E43-K43-S43)/E43 -> #DIV/0! | AD43: =SUM(D43-H43)/D43 -> #DIV/0! | AK43: =SUM(W44-W43) -> 0 | AL43: =SUM(K44-K43) -> 0
C44: Week 5 | F44: =D44-E44 -> 0 | G44: =F44/D44 -> #DIV/0! | J44: =SUM(H44-R44) -> 0 | K44: =SUM(I44-S44) -> 0 | L44: =J44-K44 -> 0 | M44: =L44/J44 -> #DIV/0! | T44: =R44-S44 -> 0 | U44: =T44/R44 -> #DIV/0! | W44: 0 | X44: =V44-W44 -> 0 | Y44: =X44/V44 -> #DIV/0! | Z44: 1 | AA44: =(E44-K44-S44)/W44 -> #DIV/0! | AB44: =(D44-J44-R44)/V44 -> #DIV/0! | AC44: =(E44-K44-S44)/E44 -> #DIV/0! | AD44: =SUM(D44-H44)/D44 -> #DIV/0! | AK44: =SUM(AK39,AK40,AK41,AK42,AK43) -> 0 | AL44: =SUM(AL39,AL40,AL41,AL42,AL43) -> 0
A46: ='Main Sheet'!A16 -> 8887 | B46: ='Main Sheet'!B16 -> Tenancy 2 - Fisher Fit out | C46: Start of month | D46: 7495.54 | E46: 0 | F46: =D46-E46 -> 7495.54 | G46: =F46/D46 -> 1 | H46: 5659.85 | I46: 0 | J46: =SUM(H46-R46) -> 3768.03 | K46: =SUM(I46-S46) -> 0 | L46: =J46-K46 -> 3768.03 | M46: =L46/J46 -> 1 | N46: 0 | R46: 1891.82 | S46: 0 | T46: =R46-S46 -> 1891.82 | U46: =T46/R46 -> 1 | V46: 37.84 | W46: 0 | X46: =V46-W46 -> 37.84 | Y46: =X46/V46 -> 1 | Z46: 0 | AA46: =(E46-K46-S46)/W46 -> #DIV/0! | AB46: =(D46-J46-R46)/V46 -> 48.511892 | AC46: =(E46-K46-S46)/E46 -> #DIV/0! | AD46: =SUM(D46-H46)/D46 -> 0.2449043 | AG46: Hours calc for monthly claims | AH46: =AK51 -> 0 | AK46: =SUM(W47-W46) -> 0 | AL46: =SUM(K47-K46) -> 0
C47: Week 1 | D47: 7495.54 | E47: 0 | F47: =D47-E47 -> 7495.54 | G47: =F47/D47 -> 1 | H47: 5659.85 | I47: 0 | J47: =SUM(H47-R47) -> 3768.03 | K47: =SUM(I47-S47) -> 0 | L47: =J47-K47 -> 3768.03 | M47: =L47/J47 -> 1 | N47: 0 | R47: 1891.82 | S47: 0 | T47: =R47-S47 -> 1891.82 | U47: =T47/R47 -> 1 | V47: 37.84 | W47: 0 | X47: =V47-W47 -> 37.84 | Y47: =X47/V47 -> 1 | Z47: 0 | AA47: =(E47-K47-S47)/W47 -> #DIV/0! | AB47: =(D47-J47-R47)/V47 -> 48.511892 | AC47: =(E47-K47-S47)/E47 -> #DIV/0! | AD47: =SUM(D47-H47)/D47 -> 0.2449043 | AG47: Materials calc for monthly claims | AH47: =AL51 -> 0 | AK47: =SUM(W48-W47) -> 0 | AL47: =SUM(K48-K47) -> 0
C48: Week 2 | D48: 7495.54 | E48: 0 | F48: =D48-E48 -> 7495.54 | G48: =F48/D48 -> 1 | H48: 5659.85 | I48: 0 | J48: =SUM(H48-R48) -> 3768.03 | K48: =SUM(I48-S48) -> 0 | L48: =J48-K48 -> 3768.03 | M48: =L48/J48 -> 1 | N48: 0 | R48: 1891.82 | S48: 0 | T48: =R48-S48 -> 1891.82 | U48: =T48/R48 -> 1 | V48: 37.84 | W48: 0 | X48: =V48-W48 -> 37.84 | Y48: =X48/V48 -> 1 | Z48: 0 | AA48: =(E48-K48-S48)/W48 -> #DIV/0! | AB48: =(D48-J48-R48)/V48 -> 48.511892 | AC48: =(E48-K48-S48)/E48 -> #DIV/0! | AD48: =SUM(D48-H48)/D48 -> 0.2449043 | AK48: =SUM(W49-W48) -> 0 | AL48: =SUM(K49-K48) -> 0
C49: Week 3 | E49: 0 | F49: =D49-E49 -> 0 | G49: =F49/D49 -> #DIV/0! | J49: =SUM(H49-R49) -> 0 | K49: =SUM(I49-S49) -> 0 | L49: =J49-K49 -> 0 | M49: =L49/J49 -> #DIV/0! | N49: 0 | S49: 0 | T49: =R49-S49 -> 0 | U49: =T49/R49 -> #DIV/0! | W49: 0 | X49: =V49-W49 -> 0 | Y49: =X49/V49 -> #DIV/0! | AA49: =(E49-K49-S49)/W49 -> #DIV/0! | AB49: =(D49-J49-R49)/V49 -> #DIV/0! | AC49: =(E49-K49-S49)/E49 -> #DIV/0! | AD49: =SUM(D49-H49)/D49 -> #DIV/0! | AG49: Estimated months claim | AH49: 0 | AK49: =SUM(W50-W49) -> 0 | AL49: =SUM(K50-K49) -> 0
C50: Week 4 | E50: 0 | F50: =D50-E50 -> 0 | G50: =F50/D50 -> #DIV/0! | J50: =SUM(H50-R50) -> 0 | K50: =SUM(I50-S50) -> 0 | L50: =J50-K50 -> 0 | M50: =L50/J50 -> #DIV/0! | N50: 0 | S50: 0 | T50: =R50-S50 -> 0 | U50: =T50/R50 -> #DIV/0! | W50: 0 | X50: =V50-W50 -> 0 | Y50: =X50/V50 -> #DIV/0! | AA50: =(E50-K50-S50)/W50 -> #DIV/0! | AB50: =(D50-J50-R50)/V50 -> #DIV/0! | AC50: =(E50-K50-S50)/E50 -> #DIV/0! | AD50: =SUM(D50-H50)/D50 -> #DIV/0! | AK50: =SUM(W51-W50) -> 0 | AL50: =SUM(K51-K50) -> 0
C51: Week 5 | E51: 0 | F51: =D51-E51 -> 0 | G51: =F51/D51 -> #DIV/0! | J51: =SUM(H51-R51) -> 0 | K51: =SUM(I51-S51) -> 0 | L51: =J51-K51 -> 0 | M51: =L51/J51 -> #DIV/0! | N51: 0 | S51: 0 | T51: =R51-S51 -> 0 | U51: =T51/R51 -> #DIV/0! | W51: 0 | X51: =V51-W51 -> 0 | Y51: =X51/V51 -> #DIV/0! | AA51: =(E51-K51-S51)/W51 -> #DIV/0! | AB51: =(D51-J51-R51)/V51 -> #DIV/0! | AC51: =(E51-K51-S51)/E51 -> #DIV/0! | AD51: =SUM(D51-H51)/D51 -> #DIV/0! | AK51: =SUM(AK46,AK47,AK48,AK49,AK50) -> 0 | AL51: =SUM(AL46,AL47,AL48,AL49,AL50) -> 0
A53: ='Main Sheet'!A18 -> 8670 | B53: ='Main Sheet'!B18 -> Studio DB - tautara fit out | C53: Start of month | D53: 100348.26 | E53: 91153 | F53: =D53-E53 -> 9195.26 | G53: =F53/D53 -> 0.091633477 | H53: 79103.46 | I53: 64224.89 | J53: =SUM(H53-R53) -> 62144.61 | K53: =SUM(I53-S53) -> 54357.06 | L53: =J53-K53 -> 7787.55 | M53: =L53/J53 -> 0.12531336 | N53: 0 | R53: 16958.85 | S53: 9867.83 | T53: =R53-S53 -> 7091.02 | U53: =T53/R53 -> 0.41813095 | V53: 340.12 | W53: 262 | X53: =V53-W53 -> 78.12 | Y53: =X53/V53 -> 0.22968364 | Z53: 0 | AA53: =(E53-K53-S53)/W53 -> 102.77905 | AB53: =(D53-J53-R53)/V53 -> 62.46266 | AC53: =(E53-K53-S53)/E53 -> 0.29541661 | AD53: =SUM(D53-H53)/D53 -> 0.2117107 | AG53: Hours calc for monthly claims | AH53: =AK58 -> -262 | AK53: =SUM(W54-W53) -> 10 | AL53: =SUM(K54-K53) -> 1582.92
C54: Week 1 | D54: 100348.26 | E54: 91153 | F54: =D54-E54 -> 9195.26 | G54: =F54/D54 -> 0.091633477 | H54: 79103.46 | I54: 66212.81 | J54: =SUM(H54-R54) -> 62144.61 | K54: =SUM(I54-S54) -> 55939.98 | L54: =J54-K54 -> 6204.63 | M54: =L54/J54 -> 0.099841804 | R54: 16958.85 | S54: 10272.83 | T54: =R54-S54 -> 6686.02 | U54: =T54/R54 -> 0.39424961 | V54: 340.12 | W54: 272 | X54: =V54-W54 -> 68.12 | Y54: =X54/V54 -> 0.20028225 | AA54: =(E54-K54-S54)/W54 -> 91.691875 | AB54: =(D54-J54-R54)/V54 -> 62.46266 | AC54: =(E54-K54-S54)/E54 -> 0.273608 | AD54: =SUM(D54-H54)/D54 -> 0.2117107 | AG54: Materials calc for monthly claims | AH54: =AL58 -> -54357.06 | AK54: =SUM(W55-W54) -> 44.25 | AL54: =SUM(K55-K54) -> 218.2
C55: Week 2 | D55: 100348.26 | E55: 91153 | F55: =D55-E55 -> 9195.26 | G55: =F55/D55 -> 0.091633477 | H55: 79103.46 | I55: 68039.14 | J55: =SUM(H55-R55) -> 62144.61 | K55: =SUM(I55-S55) -> 56158.18 | L55: =J55-K55 -> 5986.43 | M55: =L55/J55 -> 0.096330639 | R55: 16958.85 | S55: 11880.96 | T55: =R55-S55 -> 5077.89 | U55: =T55/R55 -> 0.29942419 | V55: 340.12 | W55: 316.25 | X55: =V55-W55 -> 23.87 | Y55: =X55/V55 -> 0.070181113 | AA55: =(E55-K55-S55)/W55 -> 73.087304 | AB55: =(D55-J55-R55)/V55 -> 62.46266 | AC55: =(E55-K55-S55)/E55 -> 0.25357213 | AD55: =SUM(D55-H55)/D55 -> 0.2117107 | AK55: =SUM(W56-W55) -> -316.25 | AL55: =SUM(K56-K55) -> -56158.18
C56: Week 3 | F56: =D56-E56 -> 0 | G56: =F56/D56 -> #DIV/0! | J56: =SUM(H56-R56) -> 0 | K56: =SUM(I56-S56) -> 0 | L56: =J56-K56 -> 0 | M56: =L56/J56 -> #DIV/0! | T56: =R56-S56 -> 0 | U56: =T56/R56 -> #DIV/0! | X56: =V56-W56 -> 0 | Y56: =X56/V56 -> #DIV/0! | AA56: =(E56-K56-S56)/W56 -> #DIV/0! | AB56: =(D56-J56-R56)/V56 -> #DIV/0! | AC56: =(E56-K56-S56)/E56 -> #DIV/0! | AD56: =SUM(D56-H56)/D56 -> #DIV/0! | AG56: Estimated months claim | AH56: 0 | AK56: =SUM(W57-W56) -> 0 | AL56: =SUM(K57-K56) -> 0
C57: Week 4 | F57: =D57-E57 -> 0 | G57: =F57/D57 -> #DIV/0! | J57: =SUM(H57-R57) -> 0 | K57: =SUM(I57-S57) -> 0 | L57: =J57-K57 -> 0 | M57: =L57/J57 -> #DIV/0! | T57: =R57-S57 -> 0 | U57: =T57/R57 -> #DIV/0! | X57: =V57-W57 -> 0 | Y57: =X57/V57 -> #DIV/0! | AA57: =(E57-K57-S57)/W57 -> #DIV/0! | AB57: =(D57-J57-R57)/V57 -> #DIV/0! | AC57: =(E57-K57-S57)/E57 -> #DIV/0! | AD57: =SUM(D57-H57)/D57 -> #DIV/0! | AK57: =SUM(W58-W57) -> 0 | AL57: =SUM(K58-K57) -> 0
C58: Week 5 | F58: =D58-E58 -> 0 | G58: =F58/D58 -> #DIV/0! | J58: =SUM(H58-R58) -> 0 | K58: =SUM(I58-S58) -> 0 | L58: =J58-K58 -> 0 | M58: =L58/J58 -> #DIV/0! | N58: 0.9 | T58: =R58-S58 -> 0 | U58: =T58/R58 -> #DIV/0! | X58: =V58-W58 -> 0 | Y58: =X58/V58 -> #DIV/0! | Z58: 0.9 | AA58: =(E58-K58-S58)/W58 -> #DIV/0! | AB58: =(D58-J58-R58)/V58 -> #DIV/0! | AC58: =(E58-K58-S58)/E58 -> #DIV/0! | AD58: =SUM(D58-H58)/D58 -> #DIV/0! | AK58: =SUM(AK53,AK54,AK55,AK56,AK57) -> -262 | AL58: =SUM(AL53,AL54,AL55,AL56,AL57) -> -54357.06
A60: ='Main Sheet'!A20 -> 8907 | B60: ='Main Sheet'!B20 -> 35 Mania | C60: Start of month | D60: 98524.85 | E60: 42682.56 | F60: =D60-E60 -> 55842.29 | G60: =F60/D60 -> 0.56678381 | H60: 82927.42 | I60: 59094.67 | J60: =SUM(H60-R60) -> 64755.29 | K60: =SUM(I60-S60) -> 50345.39 | L60: =J60-K60 -> 14409.9 | M60: =L60/J60 -> 0.22252854 | R60: 18172.13 | S60: 8749.28 | T60: =R60-S60 -> 9422.85 | U60: =T60/R60 -> 0.51853305 | V60: 363.99 | W60: 218.25 | X60: =V60-W60 -> 145.74 | Y60: =X60/V60 -> 0.40039562 | Z60: 0 | AA60: =(E60-K60-S60)/W60 -> -75.198671 | AB60: =(D60-J60-R60)/V60 -> 42.85126 | AC60: =(E60-K60-S60)/E60 -> -0.3845156 | AD60: =SUM(D60-H60)/D60 -> 0.1583096 | AG60: Hours calc for monthly claims | AH60: =AK65 -> -218.25 | AK60: =SUM(W61-W60) -> 163.25 | AL60: =SUM(K61-K60) -> 7441.38
C61: Week 1 | D61: 98524.85 | E61: 93329.71 | F61: =D61-E61 -> 5195.14 | G61: =F61/D61 -> 0.052729235 | H61: 82927.42 | I61: 73161.13 | J61: =SUM(H61-R61) -> 64755.29 | K61: =SUM(I61-S61) -> 57786.77 | L61: =J61-K61 -> 6968.52 | M61: =L61/J61 -> 0.10761314 | R61: 18172.13 | S61: 15374.36 | T61: =R61-S61 -> 2797.77 | U61: =T61/R61 -> 0.15395939 | V61: 363.99 | W61: 381.5 | X61: =V61-W61 -> -17.51 | Y61: =X61/V61 -> -0.048105717 | Z61: 0.2 | AA61: =(E61-K61-S61)/W61 -> 52.866527 | AB61: =(D61-J61-R61)/V61 -> 42.85126 | AC61: =(E61-K61-S61)/E61 -> 0.21610032 | AD61: =SUM(D61-H61)/D61 -> 0.1583096 | AG61: Materials calc for monthly claims | AH61: =AL65 -> -50345.39 | AK61: =SUM(W62-W61) -> 2 | AL61: =SUM(K62-K61) -> 728.1
C62: Week 2 | D62: 98524.85 | E62: 93329.71 | F62: =D62-E62 -> 5195.14 | G62: =F62/D62 -> 0.052729235 | H62: 82927.42 | I62: 73980.77 | J62: =SUM(H62-R62) -> 64755.29 | K62: =SUM(I62-S62) -> 58514.87 | L62: =J62-K62 -> 6240.42 | M62: =L62/J62 -> 0.09636927 | R62: 18172.13 | S62: 15465.9 | T62: =R62-S62 -> 2706.23 | U62: =T62/R62 -> 0.148922 | V62: 363.99 | W62: 383.5 | X62: =V62-W62 -> -19.51 | Y62: =X62/V62 -> -0.053600374 | Z62: 0.25 | AA62: =(E62-K62-S62)/W62 -> 50.453559 | AB62: =(D62-J62-R62)/V62 -> 42.85126 | AC62: =(E62-K62-S62)/E62 -> 0.20731812 | AD62: =SUM(D62-H62)/D62 -> 0.1583096 | AK62: =SUM(W63-W62) -> -383.5 | AL62: =SUM(K63-K62) -> -58514.87
C63: Week 3 | F63: =D63-E63 -> 0 | G63: =F63/D63 -> #DIV/0! | J63: =SUM(H63-R63) -> 0 | K63: =SUM(I63-S63) -> 0 | L63: =J63-K63 -> 0 | M63: =L63/J63 -> #DIV/0! | N63: 0.05 | T63: =R63-S63 -> 0 | U63: =T63/R63 -> #DIV/0! | X63: =V63-W63 -> 0 | Y63: =X63/V63 -> #DIV/0! | Z63: 0.02 | AA63: =(E63-K63-S63)/W63 -> #DIV/0! | AB63: =(D63-J63-R63)/V63 -> #DIV/0! | AC63: =(E63-K63-S63)/E63 -> #DIV/0! | AD63: =SUM(D63-H63)/D63 -> #DIV/0! | AG63: Estimated months claim | AH63: 0 | AK63: =SUM(W64-W63) -> 0 | AL63: =SUM(K64-K63) -> 0
C64: Week 4 | F64: =D64-E64 -> 0 | G64: =F64/D64 -> #DIV/0! | J64: =SUM(H64-R64) -> 0 | K64: =SUM(I64-S64) -> 0 | L64: =J64-K64 -> 0 | M64: =L64/J64 -> #DIV/0! | N64: 0.25 | T64: =R64-S64 -> 0 | U64: =T64/R64 -> #DIV/0! | X64: =V64-W64 -> 0 | Y64: =X64/V64 -> #DIV/0! | Z64: 0.1 | AA64: =(E64-K64-S64)/W64 -> #DIV/0! | AB64: =(D64-J64-R64)/V64 -> #DIV/0! | AC64: =(E64-K64-S64)/E64 -> #DIV/0! | AD64: =SUM(D64-H64)/D64 -> #DIV/0! | AK64: =SUM(W65-W64) -> 0 | AL64: =SUM(K65-K64) -> 0
C65: Week 5 | F65: =D65-E65 -> 0 | G65: =F65/D65 -> #DIV/0! | J65: =SUM(H65-R65) -> 0 | K65: =SUM(I65-S65) -> 0 | L65: =J65-K65 -> 0 | M65: =L65/J65 -> #DIV/0! | N65: 0.95 | T65: =R65-S65 -> 0 | U65: =T65/R65 -> #DIV/0! | X65: =V65-W65 -> 0 | Y65: =X65/V65 -> #DIV/0! | Z65: 0.1 | AA65: =(E65-K65-S65)/W65 -> #DIV/0! | AB65: =(D65-J65-R65)/V65 -> #DIV/0! | AC65: =(E65-K65-S65)/E65 -> #DIV/0! | AD65: =SUM(D65-H65)/D65 -> #DIV/0! | AK65: =SUM(AK60,AK61,AK62,AK63,AK64) -> -218.25 | AL65: =SUM(AL60,AL61,AL62,AL63,AL64) -> -50345.39
A67: ='Main Sheet'!A22 -> 9065 | B67: ='Main Sheet'!B22 -> Cooltranz stage 4 | C67: Start of month | D67: 87970.61 | E67: 48945.78 | F67: =D67-E67 -> 39024.83 | G67: =F67/D67 -> 0.44361213 | H67: 68471.73 | I67: 49900.98 | J67: =SUM(H67-R67) -> 52300.56 | K67: =SUM(I67-S67) -> 37733.03 | L67: =J67-K67 -> 14567.53 | M67: =L67/J67 -> 0.27853488 | R67: 16171.17 | S67: 12167.95 | T67: =R67-S67 -> 4003.22 | U67: =T67/R67 -> 0.2475529 | V67: 323.99 | W67: 350 | X67: =V67-W67 -> -26.01 | Y67: =X67/V67 -> -0.080280256 | AA67: =(E67-K67-S67)/W67 -> -2.7291429 | AB67: =(D67-J67-R67)/V67 -> 60.183586 | AC67: =(E67-K67-S67)/E67 -> -0.019515472 | AD67: =SUM(D67-H67)/D67 -> 0.22165221 | AG67: Hours calc for monthly claims | AH67: =AK72 -> -350 | AK67: =SUM(W68-W67) -> -39.5 | AL67: =SUM(K68-K67) -> 321.16
C68: Week 1 | D68: 87970.61 | E68: 85555.47 | F68: =D68-E68 -> 2415.14 | G68: =F68/D68 -> 0.027453942 | H68: 68471.73 | I68: 50194.4 | J68: =SUM(H68-R68) -> 52300.56 | K68: =SUM(I68-S68) -> 38054.19 | L68: =J68-K68 -> 14246.37 | M68: =L68/J68 -> 0.27239422 | R68: 16171.17 | S68: 12140.21 | T68: =R68-S68 -> 4030.96 | U68: =T68/R68 -> 0.2492683 | V68: 323.99 | W68: 310.5 | X68: =V68-W68 -> 13.49 | Y68: =X68/V68 -> 0.041637088 | Z68: 0.3 | AA68: =(E68-K68-S68)/W68 -> 113.88428 | AB68: =(D68-J68-R68)/V68 -> 60.183586 | AC68: =(E68-K68-S68)/E68 -> 0.41331162 | AD68: =SUM(D68-H68)/D68 -> 0.22165221 | AG68: Materials calc for monthly claims | AH68: =AL72 -> -37733.03 | AK68: =SUM(W69-W68) -> -310.5 | AL68: =SUM(K69-K68) -> -38054.19
C69: Week 2 | F69: =D69-E69 -> 0 | G69: =F69/D69 -> #DIV/0! | J69: =SUM(H69-R69) -> 0 | K69: =SUM(I69-S69) -> 0 | L69: =J69-K69 -> 0 | M69: =L69/J69 -> #DIV/0! | T69: =R69-S69 -> 0 | U69: =T69/R69 -> #DIV/0! | X69: =V69-W69 -> 0 | Y69: =X69/V69 -> #DIV/0! | Z69: 0.3 | AA69: =(E69-K69-S69)/W69 -> #DIV/0! | AB69: =(D69-J69-R69)/V69 -> #DIV/0! | AC69: =(E69-K69-S69)/E69 -> #DIV/0! | AD69: =SUM(D69-H69)/D69 -> #DIV/0! | AK69: =SUM(W70-W69) -> 0 | AL69: =SUM(K70-K69) -> 0
C70: Week 3 | F70: =D70-E70 -> 0 | G70: =F70/D70 -> #DIV/0! | J70: =SUM(H70-R70) -> 0 | K70: =SUM(I70-S70) -> 0 | L70: =J70-K70 -> 0 | M70: =L70/J70 -> #DIV/0! | T70: =R70-S70 -> 0 | U70: =T70/R70 -> #DIV/0! | X70: =V70-W70 -> 0 | Y70: =X70/V70 -> #DIV/0! | Z70: 0.1 | AA70: =(E70-K70-S70)/W70 -> #DIV/0! | AB70: =(D70-J70-R70)/V70 -> #DIV/0! | AC70: =(E70-K70-S70)/E70 -> #DIV/0! | AD70: =SUM(D70-H70)/D70 -> #DIV/0! | AG70: Estimated months claim | AH70: 0 | AK70: =SUM(W71-W70) -> 0 | AL70: =SUM(K71-K70) -> 0
C71: Week 4 | F71: =D71-E71 -> 0 | G71: =F71/D71 -> #DIV/0! | J71: =SUM(H71-R71) -> 0 | K71: =SUM(I71-S71) -> 0 | L71: =J71-K71 -> 0 | M71: =L71/J71 -> #DIV/0! | T71: =R71-S71 -> 0 | U71: =T71/R71 -> #DIV/0! | X71: =V71-W71 -> 0 | Y71: =X71/V71 -> #DIV/0! | Z71: 0.1 | AA71: =(E71-K71-S71)/W71 -> #DIV/0! | AB71: =(D71-J71-R71)/V71 -> #DIV/0! | AC71: =(E71-K71-S71)/E71 -> #DIV/0! | AD71: =SUM(D71-H71)/D71 -> #DIV/0! | AK71: =SUM(W72-W71) -> 0 | AL71: =SUM(K72-K71) -> 0
C72: Week 5 | F72: =D72-E72 -> 0 | G72: =F72/D72 -> #DIV/0! | J72: =SUM(H72-R72) -> 0 | K72: =SUM(I72-S72) -> 0 | L72: =J72-K72 -> 0 | M72: =L72/J72 -> #DIV/0! | T72: =R72-S72 -> 0 | U72: =T72/R72 -> #DIV/0! | X72: =V72-W72 -> 0 | Y72: =X72/V72 -> #DIV/0! | AA72: =(E72-K72-S72)/W72 -> #DIV/0! | AB72: =(D72-J72-R72)/V72 -> #DIV/0! | AC72: =(E72-K72-S72)/E72 -> #DIV/0! | AD72: =SUM(D72-H72)/D72 -> #DIV/0! | AK72: =SUM(AK67,AK68,AK69,AK70,AK71) -> -350 | AL72: =SUM(AL67,AL68,AL69,AL70,AL71) -> -37733.03
A74: ='Main Sheet'!A24 -> 9259 | B74: ='Main Sheet'!B24 -> Andrew Reeve Stage 2 | C74: Start of month | D74: 210242.4 | E74: 14860.85 | F74: =D74-E74 -> 195381.55 | G74: =F74/D74 -> 0.92931564 | H74: 188013.59 | I74: 33639.16 | J74: =SUM(H74-R74) -> 167291.62 | K74: =SUM(I74-S74) -> 33639.16 | L74: =J74-K74 -> 133652.46 | M74: =L74/J74 -> 0.79891904 | N74: 0 | R74: 20721.97 | S74: 0 | T74: =R74-S74 -> 20721.97 | U74: =T74/R74 -> 1 | V74: 416.73 | W74: 0 | X74: =V74-W74 -> 416.73 | Y74: =X74/V74 -> 1 | Z74: 0 | AA74: =(E74-K74-S74)/W74 -> #DIV/0! | AB74: =(D74-J74-R74)/V74 -> 53.341036 | AC74: =(E74-K74-S74)/E74 -> -1.2636094 | AD74: =SUM(D74-H74)/D74 -> 0.10572943 | AG74: Hours calc for monthly claims | AH74: =AK79 -> 0 | AK74: =SUM(W75-W74) -> 0 | AL74: =SUM(K75-K74) -> 16474.45
C75: Week 1 | D75: 210242.4 | E75: 67511.23 | F75: =D75-E75 -> 142731.17 | G75: =F75/D75 -> 0.67888861 | H75: 188013.59 | I75: 50113.61 | J75: =SUM(H75-R75) -> 167291.62 | K75: =SUM(I75-S75) -> 50113.61 | L75: =J75-K75 -> 117178.01 | M75: =L75/J75 -> 0.7004416 | N75: 0 | R75: 20721.97 | T75: =R75-S75 -> 20721.97 | U75: =T75/R75 -> 1 | V75: 416.73 | W75: 0 | X75: =V75-W75 -> 416.73 | Y75: =X75/V75 -> 1 | Z75: 0 | AA75: =(E75-K75-S75)/W75 -> #DIV/0! | AB75: =(D75-J75-R75)/V75 -> 53.341036 | AC75: =(E75-K75-S75)/E75 -> 0.25769964 | AD75: =SUM(D75-H75)/D75 -> 0.10572943 | AG75: Materials calc for monthly claims | AH75: =AL79 -> -33639.16 | AK75: =SUM(W76-W75) -> 0 | AL75: =SUM(K76-K75) -> 1067.7
C76: Week 2 | D76: 210242.4 | E76: 67511.23 | F76: =D76-E76 -> 142731.17 | G76: =F76/D76 -> 0.67888861 | H76: 188013.59 | I76: 51181.31 | J76: =SUM(H76-R76) -> 167216.61 | K76: =SUM(I76-S76) -> 51181.31 | L76: =J76-K76 -> 116035.3 | M76: =L76/J76 -> 0.69392209 | N76: 0 | R76: 20796.98 | T76: =R76-S76 -> 20796.98 | U76: =T76/R76 -> 1 | V76: 416.73 | W76: 0 | X76: =V76-W76 -> 416.73 | Y76: =X76/V76 -> 1 | Z76: 0 | AA76: =(E76-K76-S76)/W76 -> #DIV/0! | AB76: =(D76-J76-R76)/V76 -> 53.341036 | AC76: =(E76-K76-S76)/E76 -> 0.2418845 | AD76: =SUM(D76-H76)/D76 -> 0.10572943 | AK76: =SUM(W77-W76) -> 0 | AL76: =SUM(K77-K76) -> -51181.31
C77: Week 3 | F77: =D77-E77 -> 0 | G77: =F77/D77 -> #DIV/0! | J77: =SUM(H77-R77) -> 0 | K77: =SUM(I77-S77) -> 0 | L77: =J77-K77 -> 0 | M77: =L77/J77 -> #DIV/0! | N77: 0 | T77: =R77-S77 -> 0 | U77: =T77/R77 -> #DIV/0! | W77: 0 | X77: =V77-W77 -> 0 | Y77: =X77/V77 -> #DIV/0! | Z77: 0 | AA77: =(E77-K77-S77)/W77 -> #DIV/0! | AB77: =(D77-J77-R77)/V77 -> #DIV/0! | AC77: =(E77-K77-S77)/E77 -> #DIV/0! | AD77: =SUM(D77-H77)/D77 -> #DIV/0! | AG77: Estimated months claim | AH77: 0 | AK77: =SUM(W78-W77) -> 0 | AL77: =SUM(K78-K77) -> 0
C78: Week 4 | F78: =D78-E78 -> 0 | G78: =F78/D78 -> #DIV/0! | J78: =SUM(H78-R78) -> 0 | K78: =SUM(I78-S78) -> 0 | L78: =J78-K78 -> 0 | M78: =L78/J78 -> #DIV/0! | N78: 0 | S78: 0 | T78: =R78-S78 -> 0 | U78: =T78/R78 -> #DIV/0! | W78: 0 | X78: =V78-W78 -> 0 | Y78: =X78/V78 -> #DIV/0! | Z78: 0 | AA78: =(E78-K78-S78)/W78 -> #DIV/0! | AB78: =(D78-J78-R78)/V78 -> #DIV/0! | AC78: =(E78-K78-S78)/E78 -> #DIV/0! | AD78: =SUM(D78-H78)/D78 -> #DIV/0! | AK78: =SUM(W79-W78) -> 0 | AL78: =SUM(K79-K78) -> 0
C79: Week 5 | F79: =D79-E79 -> 0 | G79: =F79/D79 -> #DIV/0! | J79: =SUM(H79-R79) -> 0 | K79: =SUM(I79-S79) -> 0 | L79: =J79-K79 -> 0 | M79: =L79/J79 -> #DIV/0! | N79: 0 | S79: 0 | T79: =R79-S79 -> 0 | U79: =T79/R79 -> #DIV/0! | W79: 0 | X79: =V79-W79 -> 0 | Y79: =X79/V79 -> #DIV/0! | Z79: 0 | AA79: =(E79-K79-S79)/W79 -> #DIV/0! | AB79: =(D79-J79-R79)/V79 -> #DIV/0! | AC79: =(E79-K79-S79)/E79 -> #DIV/0! | AD79: =SUM(D79-H79)/D79 -> #DIV/0! | AK79: =SUM(AK74,AK75,AK76,AK77,AK78) -> 0 | AL79: =SUM(AL74,AL75,AL76,AL77,AL78) -> -33639.16
A81: ='Main Sheet'!A26 -> 8352 | B81: ='Main Sheet'!B26 -> 5 Sanscrit Place | C81: Start of month | D81: 43448.62 | E81: 19551.87 | F81: =D81-E81 -> 23896.75 | G81: =F81/D81 -> 0.55000021 | H81: 31063.54 | I81: 25863.55 | J81: =SUM(H81-R81) -> 16447.56 | K81: =SUM(I81-S81) -> 18255.63 | L81: =J81-K81 -> -1808.07 | M81: =L81/J81 -> -0.10992938 | N81: 0 | R81: 14615.98 | S81: 7607.92 | T81: =R81-S81 -> 7008.06 | U81: =T81/R81 -> 0.47947931 | V81: 292.93 | W81: 181.5 | X81: =V81-W81 -> 111.43 | Y81: =X81/V81 -> 0.38039805 | Z81: 0 | AA81: =(E81-K81-S81)/W81 -> -34.775096 | AB81: =(D81-J81-R81)/V81 -> 42.279999 | AC81: =(E81-K81-S81)/E81 -> -0.3228172 | AD81: =SUM(D81-H81)/D81 -> 0.28505117 | AG81: Hours calc for monthly claims | AH81: =AK86 -> -181.5 | AK81: =SUM(W82-W81) -> 0 | AL81: =SUM(K82-K81) -> 979.13
C82: Week 1 | D82: 43448.62 | E82: 34758.89 | F82: =D82-E82 -> 8689.73 | G82: =F82/D82 -> 0.20000014 | H82: 31063.54 | I82: 26842.68 | J82: =SUM(H82-R82) -> 16447.56 | K82: =SUM(I82-S82) -> 19234.76 | L82: =J82-K82 -> -2787.2 | M82: =L82/J82 -> -0.16945979 | N82: 0 | R82: 14615.98 | S82: 7607.92 | T82: =R82-S82 -> 7008.06 | U82: =T82/R82 -> 0.47947931 | V82: 292.93 | W82: 181.5 | X82: =V82-W82 -> 111.43 | Y82: =X82/V82 -> 0.38039805 | Z82: 0 | AA82: =(E82-K82-S82)/W82 -> 43.615482 | AB82: =(D82-J82-R82)/V82 -> 42.279999 | AC82: =(E82-K82-S82)/E82 -> 0.22774634 | AD82: =SUM(D82-H82)/D82 -> 0.28505117 | AG82: Materials calc for monthly claims | AH82: =AL86 -> -18255.63 | AK82: =SUM(W83-W82) -> -181.5 | AL82: =SUM(K83-K82) -> -19234.76
C83: Week 2 | D83: 0 | E83: 0 | F83: =D83-E83 -> 0 | G83: =F83/D83 -> #DIV/0! | H83: 0 | I83: 0 | J83: =SUM(H83-R83) -> 0 | K83: =SUM(I83-S83) -> 0 | L83: =J83-K83 -> 0 | M83: =L83/J83 -> #DIV/0! | R83: 0 | S83: 0 | T83: =R83-S83 -> 0 | U83: =T83/R83 -> #DIV/0! | V83: 0 | W83: 0 | X83: =V83-W83 -> 0 | Y83: =X83/V83 -> #DIV/0! | Z83: 0 | AA83: =(E83-K83-S83)/W83 -> #DIV/0! | AB83: =(D83-J83-R83)/V83 -> #DIV/0! | AC83: =(E83-K83-S83)/E83 -> #DIV/0! | AD83: =SUM(D83-H83)/D83 -> #DIV/0! | AK83: =SUM(W84-W83) -> 0 | AL83: =SUM(K84-K83) -> 0
C84: Week 3 | D84: 0 | E84: 0 | F84: =D84-E84 -> 0 | G84: =F84/D84 -> #DIV/0! | H84: 0 | I84: 0 | J84: =SUM(H84-R84) -> 0 | K84: =SUM(I84-S84) -> 0 | L84: =J84-K84 -> 0 | M84: =L84/J84 -> #DIV/0! | R84: 0 | S84: 0 | T84: =R84-S84 -> 0 | U84: =T84/R84 -> #DIV/0! | V84: 0 | W84: 0 | X84: =V84-W84 -> 0 | Y84: =X84/V84 -> #DIV/0! | Z84: 0 | AA84: =(E84-K84-S84)/W84 -> #DIV/0! | AB84: =(D84-J84-R84)/V84 -> #DIV/0! | AC84: =(E84-K84-S84)/E84 -> #DIV/0! | AD84: =SUM(D84-H84)/D84 -> #DIV/0! | AG84: Estimated months claim | AH84: 0 | AK84: =SUM(W85-W84) -> 0 | AL84: =SUM(K85-K84) -> 0
C85: Week 4 | D85: 0 | E85: 0 | F85: =D85-E85 -> 0 | G85: =F85/D85 -> #DIV/0! | H85: 0 | I85: 0 | J85: =SUM(H85-R85) -> 0 | K85: =SUM(I85-S85) -> 0 | L85: =J85-K85 -> 0 | M85: =L85/J85 -> #DIV/0! | R85: 0 | S85: 0 | T85: =R85-S85 -> 0 | U85: =T85/R85 -> #DIV/0! | V85: 0 | W85: 0 | X85: =V85-W85 -> 0 | Y85: =X85/V85 -> #DIV/0! | AA85: =(E85-K85-S85)/W85 -> #DIV/0! | AB85: =(D85-J85-R85)/V85 -> #DIV/0! | AC85: =(E85-K85-S85)/E85 -> #DIV/0! | AD85: =SUM(D85-H85)/D85 -> #DIV/0! | AK85: =SUM(W86-W85) -> 0 | AL85: =SUM(K86-K85) -> 0
C86: Week 5 | D86: 0 | E86: 0 | F86: =D86-E86 -> 0 | G86: =F86/D86 -> #DIV/0! | H86: 0 | I86: 0 | J86: =SUM(H86-R86) -> 0 | K86: =SUM(I86-S86) -> 0 | L86: =J86-K86 -> 0 | M86: =L86/J86 -> #DIV/0! | R86: 0 | S86: 0 | T86: =R86-S86 -> 0 | U86: =T86/R86 -> #DIV/0! | V86: 0 | W86: 0 | X86: =V86-W86 -> 0 | Y86: =X86/V86 -> #DIV/0! | AA86: =(E86-K86-S86)/W86 -> #DIV/0! | AB86: =(D86-J86-R86)/V86 -> #DIV/0! | AC86: =(E86-K86-S86)/E86 -> #DIV/0! | AD86: =SUM(D86-H86)/D86 -> #DIV/0! | AK86: =SUM(AK81,AK82,AK83,AK84,AK85) -> -181.5 | AL86: =SUM(AL81,AL82,AL83,AL84,AL85) -> -18255.63
A88: ='Main Sheet'!A28 -> 8234 | B88: ='Main Sheet'!B28 -> Melhuish House | C88: Start of month | D88: 49964.93 | E88: 25359.22 | F88: =D88-E88 -> 24605.71 | G88: =F88/D88 -> 0.49245961 | H88: 43768.91 | I88: 25556.81 | J88: =SUM(H88-R88) -> 37199.62 | K88: =SUM(I88-S88) -> 20554.23 | L88: =J88-K88 -> 16645.39 | M88: =L88/J88 -> 0.44746129 | N88: 0 | R88: 6569.29 | S88: 5002.58 | T88: =R88-S88 -> 1566.71 | U88: =T88/R88 -> 0.23849 | V88: 131.78 | W88: 113.75 | X88: =V88-W88 -> 18.03 | Y88: =X88/V88 -> 0.13681894 | Z88: 0 | AA88: =(E88-K88-S88)/W88 -> -1.7370549 | AB88: =(D88-J88-R88)/V88 -> 47.017909 | AC88: =(E88-K88-S88)/E88 -> -0.0077916434 | AD88: =SUM(D88-H88)/D88 -> 0.12400738 | AG88: Hours calc for monthly claims | AH88: =AK93 -> -113.75 | AK88: =SUM(W89-W88) -> 58 | AL88: =SUM(K89-K88) -> 7824.22
C89: Week 1 | D89: 49964.93 | E89: 45361.39 | F89: =D89-E89 -> 4603.54 | G89: =F89/D89 -> 0.092135424 | H89: 43768.91 | I89: 35776.29 | J89: =SUM(H89-R89) -> 37199.62 | K89: =SUM(I89-S89) -> 28378.45 | L89: =J89-K89 -> 8821.17 | M89: =L89/J89 -> 0.23713065 | R89: 6569.29 | S89: 7397.84 | T89: =R89-S89 -> -828.55 | U89: =T89/R89 -> -0.12612474 | V89: 131.78 | W89: 171.75 | X89: =V89-W89 -> -39.97 | Y89: =X89/V89 -> -0.30330854 | AA89: =(E89-K89-S89)/W89 -> 55.808443 | AB89: =(D89-J89-R89)/V89 -> 47.017909 | AC89: =(E89-K89-S89)/E89 -> 0.21130525 | AD89: =SUM(D89-H89)/D89 -> 0.12400738 | AG89: Materials calc for monthly claims | AH89: =AL93 -> -20554.23 | AK89: =SUM(W90-W89) -> -171.75 | AL89: =SUM(K90-K89) -> -28378.45
C90: Week 2 | D90: 0 | E90: 0 | F90: =D90-E90 -> 0 | G90: =F90/D90 -> #DIV/0! | H90: 0 | I90: 0 | J90: =SUM(H90-R90) -> 0 | K90: =SUM(I90-S90) -> 0 | L90: =J90-K90 -> 0 | M90: =L90/J90 -> #DIV/0! | R90: 0 | S90: 0 | T90: =R90-S90 -> 0 | U90: =T90/R90 -> #DIV/0! | V90: 0 | W90: 0 | X90: =V90-W90 -> 0 | Y90: =X90/V90 -> #DIV/0! | AA90: =(E90-K90-S90)/W90 -> #DIV/0! | AB90: =(D90-J90-R90)/V90 -> #DIV/0! | AC90: =(E90-K90-S90)/E90 -> #DIV/0! | AD90: =SUM(D90-H90)/D90 -> #DIV/0! | AK90: =SUM(W91-W90) -> 0 | AL90: =SUM(K91-K90) -> 0
C91: Week 3 | D91: 0 | E91: 0 | F91: =D91-E91 -> 0 | G91: =F91/D91 -> #DIV/0! | H91: 0 | I91: 0 | J91: =SUM(H91-R91) -> 0 | K91: =SUM(I91-S91) -> 0 | L91: =J91-K91 -> 0 | M91: =L91/J91 -> #DIV/0! | R91: 0 | S91: 0 | T91: =R91-S91 -> 0 | U91: =T91/R91 -> #DIV/0! | V91: 0 | W91: 0 | X91: =V91-W91 -> 0 | Y91: =X91/V91 -> #DIV/0! | AA91: =(E91-K91-S91)/W91 -> #DIV/0! | AB91: =(D91-J91-R91)/V91 -> #DIV/0! | AC91: =(E91-K91-S91)/E91 -> #DIV/0! | AD91: =SUM(D91-H91)/D91 -> #DIV/0! | AG91: Estimated months claim | AH91: 0 | AK91: =SUM(W92-W91) -> 0 | AL91: =SUM(K92-K91) -> 0
C92: Week 4 | D92: 0 | E92: 0 | F92: =D92-E92 -> 0 | G92: =F92/D92 -> #DIV/0! | H92: 0 | I92: 0 | J92: =SUM(H92-R92) -> 0 | K92: =SUM(I92-S92) -> 0 | L92: =J92-K92 -> 0 | M92: =L92/J92 -> #DIV/0! | R92: 0 | S92: 0 | T92: =R92-S92 -> 0 | U92: =T92/R92 -> #DIV/0! | V92: 0 | W92: 0 | X92: =V92-W92 -> 0 | Y92: =X92/V92 -> #DIV/0! | AA92: =(E92-K92-S92)/W92 -> #DIV/0! | AB92: =(D92-J92-R92)/V92 -> #DIV/0! | AC92: =(E92-K92-S92)/E92 -> #DIV/0! | AD92: =SUM(D92-H92)/D92 -> #DIV/0! | AK92: =SUM(W93-W92) -> 0 | AL92: =SUM(K93-K92) -> 0
C93: Week 5 | D93: 0 | E93: 0 | F93: =D93-E93 -> 0 | G93: =F93/D93 -> #DIV/0! | H93: 0 | I93: 0 | J93: =SUM(H93-R93) -> 0 | K93: =SUM(I93-S93) -> 0 | L93: =J93-K93 -> 0 | M93: =L93/J93 -> #DIV/0! | R93: 0 | S93: 0 | T93: =R93-S93 -> 0 | U93: =T93/R93 -> #DIV/0! | V93: 0 | W93: 0 | X93: =V93-W93 -> 0 | Y93: =X93/V93 -> #DIV/0! | AA93: =(E93-K93-S93)/W93 -> #DIV/0! | AB93: =(D93-J93-R93)/V93 -> #DIV/0! | AC93: =(E93-K93-S93)/E93 -> #DIV/0! | AD93: =SUM(D93-H93)/D93 -> #DIV/0! | AK93: =SUM(AK88,AK89,AK90,AK91,AK92) -> -113.75 | AL93: =SUM(AL88,AL89,AL90,AL91,AL92) -> -20554.23
A95: ='Main Sheet'!A30 -> 8214 | B95: ='Main Sheet'!B30 -> 6 Tiroroa Lane | C95: Start of month | D95: 109103.76 | E95: 51323.57 | F95: =D95-E95 -> 57780.19 | G95: =F95/D95 -> 0.52958936 | H95: 81158.83 | I95: 40300.16 | J95: =SUM(H95-R95) -> 52391.31 | K95: =SUM(I95-S95) -> 27621.5 | L95: =J95-K95 -> 24769.81 | M95: =L95/J95 -> 0.4727847 | N95: 0.2 | R95: 28767.52 | S95: 12678.66 | T95: =R95-S95 -> 16088.86 | U95: =T95/R95 -> 0.55927171 | V95: 577.33 | W95: 295.5 | X95: =V95-W95 -> 281.83 | Y95: =X95/V95 -> 0.48816102 | Z95: 0 | AA95: =(E95-K95-S95)/W95 -> 37.304264 | AB95: =(D95-J95-R95)/V95 -> 48.403738 | AC95: =(E95-K95-S95)/E95 -> 0.2147826 | AD95: =SUM(D95-H95)/D95 -> 0.25613169 | AG95: Hours calc for monthly claims | AH95: =AK100 -> -295.5 | AK95: =SUM(W96-W95) -> 19.25 | AL95: =SUM(K96-K95) -> 1.96
C96: Week 1 | D96: 109103.76 | E96: 77821.91 | F96: =D96-E96 -> 31281.85 | G96: =F96/D96 -> 0.28671652 | H96: 81158.83 | I96: 41214.74 | J96: =SUM(H96-R96) -> 52391.31 | K96: =SUM(I96-S96) -> 27623.46 | L96: =J96-K96 -> 24767.85 | M96: =L96/J96 -> 0.47274729 | N96: 0.2 | R96: 28767.52 | S96: 13591.28 | T96: =R96-S96 -> 15176.24 | U96: =T96/R96 -> 0.52754773 | V96: 577.33 | W96: 314.75 | X96: =V96-W96 -> 262.58 | Y96: =X96/V96 -> 0.45481787 | Z96: 0 | AA96: =(E96-K96-S96)/W96 -> 116.30554 | AB96: =(D96-J96-R96)/V96 -> 48.403738 | AC96: =(E96-K96-S96)/E96 -> 0.4703967 | AD96: =SUM(D96-H96)/D96 -> 0.25613169 | AG96: Materials calc for monthly claims | AH96: =AL100 -> -27621.5 | AK96: =SUM(W97-W96) -> -314.75 | AL96: =SUM(K97-K96) -> -27623.46
C97: Week 2 | D97: 0 | E97: 0 | F97: =D97-E97 -> 0 | G97: =F97/D97 -> #DIV/0! | H97: 0 | I97: 0 | J97: =SUM(H97-R97) -> 0 | K97: =SUM(I97-S97) -> 0 | L97: =J97-K97 -> 0 | M97: =L97/J97 -> #DIV/0! | N97: 0.2 | R97: 0 | S97: 0 | T97: =R97-S97 -> 0 | U97: =T97/R97 -> #DIV/0! | V97: 0 | W97: 0 | X97: =V97-W97 -> 0 | Y97: =X97/V97 -> #DIV/0! | Z97: 0.2 | AA97: =(E97-K97-S97)/W97 -> #DIV/0! | AB97: =(D97-J97-R97)/V97 -> #DIV/0! | AC97: =(E97-K97-S97)/E97 -> #DIV/0! | AD97: =SUM(D97-H97)/D97 -> #DIV/0! | AK97: =SUM(W98-W97) -> 0 | AL97: =SUM(K98-K97) -> 0
C98: Week 3 | D98: 0 | E98: 0 | F98: =D98-E98 -> 0 | G98: =F98/D98 -> #DIV/0! | H98: 0 | I98: 0 | J98: =SUM(H98-R98) -> 0 | K98: =SUM(I98-S98) -> 0 | L98: =J98-K98 -> 0 | M98: =L98/J98 -> #DIV/0! | N98: 0 | R98: 0 | S98: 0 | T98: =R98-S98 -> 0 | U98: =T98/R98 -> #DIV/0! | V98: 0 | W98: 0 | X98: =V98-W98 -> 0 | Y98: =X98/V98 -> #DIV/0! | Z98: 0.25 | AA98: =(E98-K98-S98)/W98 -> #DIV/0! | AB98: =(D98-J98-R98)/V98 -> #DIV/0! | AC98: =(E98-K98-S98)/E98 -> #DIV/0! | AD98: =SUM(D98-H98)/D98 -> #DIV/0! | AG98: Estimated months claim | AH98: 0 | AK98: =SUM(W99-W98) -> 0 | AL98: =SUM(K99-K98) -> 0
C99: Week 4 | D99: 0 | E99: 0 | F99: =D99-E99 -> 0 | G99: =F99/D99 -> #DIV/0! | H99: 0 | I99: 0 | J99: =SUM(H99-R99) -> 0 | K99: =SUM(I99-S99) -> 0 | L99: =J99-K99 -> 0 | M99: =L99/J99 -> #DIV/0! | N99: 0 | R99: 0 | S99: 0 | T99: =R99-S99 -> 0 | U99: =T99/R99 -> #DIV/0! | V99: 0 | W99: 0 | X99: =V99-W99 -> 0 | Y99: =X99/V99 -> #DIV/0! | AA99: =(E99-K99-S99)/W99 -> #DIV/0! | AB99: =(D99-J99-R99)/V99 -> #DIV/0! | AC99: =(E99-K99-S99)/E99 -> #DIV/0! | AD99: =SUM(D99-H99)/D99 -> #DIV/0! | AK99: =SUM(W100-W99) -> 0 | AL99: =SUM(K100-K99) -> 0
C100: Week 5 | D100: 0 | E100: 0 | F100: =D100-E100 -> 0 | G100: =F100/D100 -> #DIV/0! | H100: 0 | I100: 0 | J100: =SUM(H100-R100) -> 0 | K100: =SUM(I100-S100) -> 0 | L100: =J100-K100 -> 0 | M100: =L100/J100 -> #DIV/0! | N100: 0 | R100: 0 | S100: 0 | T100: =R100-S100 -> 0 | U100: =T100/R100 -> #DIV/0! | V100: 0 | W100: 0 | X100: =V100-W100 -> 0 | Y100: =X100/V100 -> #DIV/0! | AA100: =(E100-K100-S100)/W100 -> #DIV/0! | AB100: =(D100-J100-R100)/V100 -> #DIV/0! | AC100: =(E100-K100-S100)/E100 -> #DIV/0! | AD100: =SUM(D100-H100)/D100 -> #DIV/0! | AK100: =SUM(AK95,AK96,AK97,AK98,AK99) -> -295.5 | AL100: =SUM(AL95,AL96,AL97,AL98,AL99) -> -27621.5
A102: ='Main Sheet'!A32 -> 6792 | B102: ='Main Sheet'!B32 -> Major Hornbrook | C102: Start of month | D102: 27742.44 | E102: 0 | F102: =D102-E102 -> 27742.44 | G102: =F102/D102 -> 1 | H102: 20094.24 | I102: 405.4 | J102: =SUM(H102-R102) -> 11429.46 | K102: =SUM(I102-S102) -> 73.74 | L102: =J102-K102 -> 11355.72 | M102: =L102/J102 -> 0.99354825 | N102: 0 | R102: 8664.78 | S102: 331.66 | T102: =R102-S102 -> 8333.12 | U102: =T102/R102 -> 0.96172321 | V102: 173.8 | W102: 7.75 | X102: =V102-W102 -> 166.05 | Y102: =X102/V102 -> 0.95540852 | AA102: =(E102-K102-S102)/W102 -> -52.309677 | AB102: =(D102-J102-R102)/V102 -> 44.005754 | AC102: =(E102-K102-S102)/E102 -> #DIV/0! | AD102: =SUM(D102-H102)/D102 -> 0.27568592 | AG102: Hours calc for monthly claims | AH102: =AK107 -> -7.75 | AK102: =SUM(W103-W102) -> 0 | AL102: =SUM(K103-K102) -> -13.89
C103: Week 1 | D103: 27861.41 | E103: 0 | F103: =D103-E103 -> 27861.41 | G103: =F103/D103 -> 1 | H103: 20162.08 | I103: 392.27 | J103: =SUM(H103-R103) -> 11464.04 | K103: =SUM(I103-S103) -> 59.85 | L103: =J103-K103 -> 11404.19 | M103: =L103/J103 -> 0.99477933 | N103: 0 | R103: 8698.04 | S103: 332.42 | T103: =R103-S103 -> 8365.62 | U103: =T103/R103 -> 0.96178219 | V103: 174.46 | W103: 7.75 | X103: =V103-W103 -> 166.71 | Y103: =X103/V103 -> 0.95557721 | AA103: =(E103-K103-S103)/W103 -> -50.615484 | AB103: =(D103-J103-R103)/V103 -> 44.132351 | AC103: =(E103-K103-S103)/E103 -> #DIV/0! | AD103: =SUM(D103-H103)/D103 -> 0.27634387 | AG103: Materials calc for monthly claims | AH103: =AL107 -> -73.74 | AK103: =SUM(W104-W103) -> -7.75 | AL103: =SUM(K104-K103) -> -59.85
C104: Week 2 | D104: 0 | E104: 0 | F104: =D104-E104 -> 0 | G104: =F104/D104 -> #DIV/0! | H104: 0 | I104: 0 | J104: =SUM(H104-R104) -> 0 | K104: =SUM(I104-S104) -> 0 | L104: =J104-K104 -> 0 | M104: =L104/J104 -> #DIV/0! | N104: 0 | R104: 0 | S104: 0 | T104: =R104-S104 -> 0 | U104: =T104/R104 -> #DIV/0! | V104: 0 | W104: 0 | X104: =V104-W104 -> 0 | Y104: =X104/V104 -> #DIV/0! | AA104: =(E104-K104-S104)/W104 -> #DIV/0! | AB104: =(D104-J104-R104)/V104 -> #DIV/0! | AC104: =(E104-K104-S104)/E104 -> #DIV/0! | AD104: =SUM(D104-H104)/D104 -> #DIV/0! | AK104: =SUM(W105-W104) -> 0 | AL104: =SUM(K105-K104) -> 0
C105: Week 3 | D105: 0 | E105: 0 | F105: =D105-E105 -> 0 | G105: =F105/D105 -> #DIV/0! | H105: 0 | I105: 0 | J105: =SUM(H105-R105) -> 0 | K105: =SUM(I105-S105) -> 0 | L105: =J105-K105 -> 0 | M105: =L105/J105 -> #DIV/0! | N105: 0 | R105: 0 | S105: 0 | T105: =R105-S105 -> 0 | U105: =T105/R105 -> #DIV/0! | V105: 0 | W105: 0 | X105: =V105-W105 -> 0 | Y105: =X105/V105 -> #DIV/0! | AA105: =(E105-K105-S105)/W105 -> #DIV/0! | AB105: =(D105-J105-R105)/V105 -> #DIV/0! | AC105: =(E105-K105-S105)/E105 -> #DIV/0! | AD105: =SUM(D105-H105)/D105 -> #DIV/0! | AG105: Estimated months claim | AH105: 0 | AK105: =SUM(W106-W105) -> 0 | AL105: =SUM(K106-K105) -> 0
C106: Week 4 | D106: 0 | E106: 0 | F106: =D106-E106 -> 0 | G106: =F106/D106 -> #DIV/0! | H106: 0 | I106: 0 | J106: =SUM(H106-R106) -> 0 | K106: =SUM(I106-S106) -> 0 | L106: =J106-K106 -> 0 | M106: =L106/J106 -> #DIV/0! | N106: 0 | R106: 0 | S106: 0 | T106: =R106-S106 -> 0 | U106: =T106/R106 -> #DIV/0! | V106: 0 | W106: 0 | X106: =V106-W106 -> 0 | Y106: =X106/V106 -> #DIV/0! | AA106: =(E106-K106-S106)/W106 -> #DIV/0! | AB106: =(D106-J106-R106)/V106 -> #DIV/0! | AC106: =(E106-K106-S106)/E106 -> #DIV/0! | AD106: =SUM(D106-H106)/D106 -> #DIV/0! | AK106: =SUM(W107-W106) -> 0 | AL106: =SUM(K107-K106) -> 0
C107: Week 5 | D107: 0 | E107: 0 | F107: =D107-E107 -> 0 | G107: =F107/D107 -> #DIV/0! | H107: 0 | I107: 0 | J107: =SUM(H107-R107) -> 0 | K107: =SUM(I107-S107) -> 0 | L107: =J107-K107 -> 0 | M107: =L107/J107 -> #DIV/0! | N107: 0 | R107: 0 | S107: 0 | T107: =R107-S107 -> 0 | U107: =T107/R107 -> #DIV/0! | V107: 0 | W107: 0 | X107: =V107-W107 -> 0 | Y107: =X107/V107 -> #DIV/0! | AA107: =(E107-K107-S107)/W107 -> #DIV/0! | AB107: =(D107-J107-R107)/V107 -> #DIV/0! | AC107: =(E107-K107-S107)/E107 -> #DIV/0! | AD107: =SUM(D107-H107)/D107 -> #DIV/0! | AK107: =SUM(AK102,AK103,AK104,AK105,AK106) -> -7.75 | AL107: =SUM(AL102,AL103,AL104,AL105,AL106) -> -73.74
A109: ='Main Sheet'!A34 -> 8840 | B109: ='Main Sheet'!B34 -> Inline Architecture | C109: Start of month | D109: 21300.45 | E109: 5515.31 | F109: =D109-E109 -> 15785.14 | G109: =F109/D109 -> 0.74107073 | H109: 11275.69 | I109: 5128.09 | J109: =SUM(H109-R109) -> 4165.39 | K109: 815.93 | L109: =J109-K109 -> 3349.46 | M109: =L109/J109 -> 0.80411678 | N109: 1 | R109: 7110.3 | S109: 1880.39 | T109: =R109-S109 -> 5229.91 | U109: =T109/R109 -> 0.73553999 | V109: 142.36 | W109: 42.25 | X109: =V109-W109 -> 100.11 | Y109: =X109/V109 -> 0.7032172 | Z109: 1 | AA109: =(E109-K109-S109)/W109 -> 66.721657 | AB109: =(D109-J109-R109)/V109 -> 70.418376 | AC109: =(E109-K109-S109)/E109 -> 0.51112086 | AD109: =SUM(D109-H109)/D109 -> 0.47063607 | AG109: Hours calc for monthly claims | AH109: =AK114 -> -42.25 | AK109: =SUM(W110-W109) -> 14.25 | AL109: =SUM(K110-K109) -> 2844.83
C110: Week 1 | D110: 21300.45 | E110: 10143.09 | F110: =D110-E110 -> 11157.36 | G110: =F110/D110 -> 0.52380865 | H110: 11275.69 | I110: 6237.89 | J110: =SUM(H110-R110) -> 4165.39 | K110: =SUM(I110-S110) -> 3660.76 | L110: =J110-K110 -> 504.63 | M110: =L110/J110 -> 0.12114832 | N110: 1 | R110: 7110.3 | S110: 2577.13 | T110: =R110-S110 -> 4533.17 | U110: =T110/R110 -> 0.63754975 | V110: 142.36 | W110: 56.5 | X110: =V110-W110 -> 85.86 | Y110: =X110/V110 -> 0.60311885 | Z110: 1 | AA110: =(E110-K110-S110)/W110 -> 69.118584 | AB110: =(D110-J110-R110)/V110 -> 70.418376 | AC110: =(E110-K110-S110)/E110 -> 0.38501088 | AD110: =SUM(D110-H110)/D110 -> 0.47063607 | AG110: Materials calc for monthly claims | AH110: =AL114 -> -815.93 | AK110: =SUM(W111-W110) -> -56.5 | AL110: =SUM(K111-K110) -> -3660.76
C111: Week 2 | D111: 0 | E111: 0 | F111: =D111-E111 -> 0 | G111: =F111/D111 -> #DIV/0! | H111: 0 | I111: 0 | J111: =SUM(H111-R111) -> 0 | K111: =SUM(I111-S111) -> 0 | L111: =J111-K111 -> 0 | M111: =L111/J111 -> #DIV/0! | N111: 1 | R111: 0 | S111: 0 | T111: =R111-S111 -> 0 | U111: =T111/R111 -> #DIV/0! | V111: 0 | W111: 0 | X111: =V111-W111 -> 0 | Y111: =X111/V111 -> #DIV/0! | Z111: 1 | AA111: =(E111-K111-S111)/W111 -> #DIV/0! | AB111: =(D111-J111-R111)/V111 -> #DIV/0! | AC111: =(E111-K111-S111)/E111 -> #DIV/0! | AD111: =SUM(D111-H111)/D111 -> #DIV/0! | AK111: =SUM(W112-W111) -> 0 | AL111: =SUM(K112-K111) -> 0
C112: Week 3 | D112: 0 | E112: 0 | F112: =D112-E112 -> 0 | G112: =F112/D112 -> #DIV/0! | H112: 0 | I112: 0 | J112: =SUM(H112-R112) -> 0 | K112: =SUM(I112-S112) -> 0 | L112: =J112-K112 -> 0 | M112: =L112/J112 -> #DIV/0! | N112: 0 | R112: 0 | S112: 0 | T112: =R112-S112 -> 0 | U112: =T112/R112 -> #DIV/0! | V112: 0 | W112: 0 | X112: =V112-W112 -> 0 | Y112: =X112/V112 -> #DIV/0! | Z112: 0 | AA112: =(E112-K112-S112)/W112 -> #DIV/0! | AB112: =(D112-J112-R112)/V112 -> #DIV/0! | AC112: =(E112-K112-S112)/E112 -> #DIV/0! | AD112: =SUM(D112-H112)/D112 -> #DIV/0! | AG112: Estimated months claim | AH112: 0 | AK112: =SUM(W113-W112) -> 0 | AL112: =SUM(K113-K112) -> 0
C113: Week 4 | D113: 0 | E113: 0 | F113: =D113-E113 -> 0 | G113: =F113/D113 -> #DIV/0! | H113: 0 | I113: 0 | J113: =SUM(H113-R113) -> 0 | K113: =SUM(I113-S113) -> 0 | L113: =J113-K113 -> 0 | M113: =L113/J113 -> #DIV/0! | N113: 0 | R113: 0 | S113: 0 | T113: =R113-S113 -> 0 | U113: =T113/R113 -> #DIV/0! | V113: 0 | W113: 0 | X113: =V113-W113 -> 0 | Y113: =X113/V113 -> #DIV/0! | Z113: 0 | AA113: =(E113-K113-S113)/W113 -> #DIV/0! | AB113: =(D113-J113-R113)/V113 -> #DIV/0! | AC113: =(E113-K113-S113)/E113 -> #DIV/0! | AD113: =SUM(D113-H113)/D113 -> #DIV/0! | AK113: =SUM(W114-W113) -> 0 | AL113: =SUM(K114-K113) -> 0
C114: Week 5 | D114: 0 | E114: 0 | F114: =D114-E114 -> 0 | G114: =F114/D114 -> #DIV/0! | H114: 0 | I114: 0 | J114: =SUM(H114-R114) -> 0 | K114: =SUM(I114-S114) -> 0 | L114: =J114-K114 -> 0 | M114: =L114/J114 -> #DIV/0! | N114: 0 | R114: 0 | S114: 0 | T114: =R114-S114 -> 0 | U114: =T114/R114 -> #DIV/0! | V114: 0 | W114: 0 | X114: =V114-W114 -> 0 | Y114: =X114/V114 -> #DIV/0! | Z114: 0 | AA114: =(E114-K114-S114)/W114 -> #DIV/0! | AB114: =(D114-J114-R114)/V114 -> #DIV/0! | AC114: =(E114-K114-S114)/E114 -> #DIV/0! | AD114: =SUM(D114-H114)/D114 -> #DIV/0! | AK114: =SUM(AK109,AK110,AK111,AK112,AK113) -> -42.25 | AL114: =SUM(AL109,AL110,AL111,AL112,AL113) -> -815.93
A116: ='Main Sheet'!A36 -> 8769 | B116: ='Main Sheet'!B36 -> Percival Bach | C116: Start of month | D116: 63405.46 | E116: 0 | F116: =D116-E116 -> 63405.46 | G116: =F116/D116 -> 1 | H116: 43553.81 | I116: 9012.69 | J116: =SUM(H116-R116) -> 29573.66 | K116: =SUM(I116-S116) -> 8270.88 | L116: =J116-K116 -> 21302.78 | M116: =L116/J116 -> 0.72032951 | N116: 0 | R116: 13980.15 | S116: 741.81 | T116: =R116-S116 -> 13238.34 | U116: =T116/R116 -> 0.94693834 | V116: 279.87 | W116: 52 | X116: =V116-W116 -> 227.87 | Y116: =X116/V116 -> 0.81419945 | Z116: 0 | AA116: =(E116-K116-S116)/W116 -> -173.32096 | AB116: =(D116-J116-R116)/V116 -> 70.931683 | AC116: =(E116-K116-S116)/E116 -> #DIV/0! | AD116: =SUM(D116-H116)/D116 -> 0.31309054 | AG116: Hours calc for monthly claims | AH116: =AK121 -> -52 | AK116: =SUM(W117-W116) -> 36.5 | AL116: =SUM(K117-K116) -> 3381.04
...

Sheet Sheet1
A3: 340 | B3: Allowed | C3: Actual | D3: % of job
A4: Box out | B4: 30 | D4: =SUM(B4/A3) -> 0.088235294
A5: pre-wire | B5: 60 | P5: 95.35
A6: cut out | B6: 100 | P6: 102.69
A7: fit off lights | B7: 150 | P7: 134.82
P8: 324.19
P9: 415
